Workbook

Sheet Instrucciones
A1: Plataforma de Seguimiento Toyota Corregidora — versión Excel
A3: Cómo usar este archivo:
A4: 1. Ve a la pestaña 'Clientes' y da de alta cada cliente en una fila nueva (usa los menús desplegables en Vehículo, Método de Compra, Tipo de Persona, Avalúo, Primera Visita y Etapa).
A5: 2. La fila cambia de color automáticamente según la Etapa que selecciones (Prospecto, Apartado, Toma de vehículo, Pago, Contrato, Facturación, Programación, Entregado).
A6: 3. Las columnas Q a Z generan el texto del mensaje y un enlace 'Enviar' que abre WhatsApp Web con el mensaje ya redactado — solo da clic y presiona enviar.
A7: 4. En 'Requisitos' filtra por Método de Compra y Tipo de Persona con el autofiltro para ver la checklist correspondiente; ahí también están los beneficios de crédito.
A8: 5. En 'Fichas y Beneficios' tienes el nombre del PDF de cada vehículo (guárdalos en una carpeta llamada 'fichas' junto a este archivo).
A9: 6. En 'Facturación' selecciona el nombre del cliente (ya dado de alta en Clientes) y llena sus datos; el mensaje de confirmación y el enlace de WhatsApp se generan solos.
A11: Nota: los enlaces de WhatsApp requieren que el número de teléfono tenga 10 dígitos (se le agrega automáticamente el 52 de México).
A12: Nota: al abrir el archivo, Excel puede preguntar si deseas habilitar el cálculo de fórmulas o el contenido externo — acepta para que los mensajes se generen correctamente.

Sheet Config
A1: Firma (footer de mensajes) | B1: ="Atentamente."&CHAR(10)&CHAR(10)&"*Alejandro Estrada*"&CHAR(10)&"Asesor de ventas"&CHAR(10)&"Toyota Corregidora"&CHAR(10)&"4427485194"&CHAR(10)&"jestrada@toyotacorregidora.mx" | D1: Vehículos | E1: Método de Compra | F1: Tipo de Persona | G1: Sí/No | H1: Etapa | I1: Tipo de Mensaje
D2: Yaris Sedan | E2: Crédito | F2: Persona física | G2: Sí | H2: Prospecto / Visita | I2: Bienvenida (primera visita)
D3: Yaris Sedan HEV | E3: Contado | F3: Persona física con actividad empresarial | G3: No | H3: Apartado | I3: Seguimiento
D4: Yaris HB | F4: Persona moral | H4: Toma de vehículo | I4: Aviso de Etapa
D5: GR Yaris | H5: Pago vehículo a cuenta | I5: Requisitos
D6: Corolla | H6: Firma de contrato | I6: Datos de Facturación
D7: GR Corolla | H7: Facturación | I7: Cumpleaños
D8: Camry | H8: Programación de entrega | I8: Aniversario
D9: Prius | H9: Entregado
D10: Supra
D11: Raize
D12: Avanza
D13: Corolla Cross
D14: Rav-4
D15: Highlander
D16: Sienna
D17: 4Runner
D18: Sequoia
D19: Hilux
D20: Tacoma
D21: Tundra
... D23: Otro (especificar)

Sheet Clientes
A1: No. | B1: Nombre | C1: Teléfono | D1: Vehículo | E1: Versión | F1: Método de Compra | G1: Tipo de Persona | H1: Avalúo (Sí/No) | I1: Vehículo Avalúo | J1: Oferta Avalúo | K1: Comentarios | L1: Primera Visita (Sí/No) | M1: Etapa | N1: Fecha Registro | O1: Cumpleaños | P1: Fecha Entrega (Aniversario) | Q1: Mensaje Bienvenida | R1: WhatsApp Bienvenida | S1: Mensaje Seguimiento | T1: WhatsApp Seguimiento | U1: Mensaje por Etapa | V1: WhatsApp Etapa | W1: Mensaje Cumpleaños | X1: WhatsApp Cumpleaños | Y1: Mensaje Aniversario | Z1: WhatsApp Aniversario | AA1: Tipo de Mensaje a Enviar | AB1: Enviar Mensaje Seleccionado | AC1: Mensaje Requisitos (auto) | AD1: Mensaje Facturación (auto, si ya está en la pestaña Facturación)
A2: =IF(B2="","",ROW()-1) | B2: Fernando Velasco | C2: 4424479460 | D2: Corolla Cross | E2: XLE | F2: Contado | G2: Persona física | H2: No | K2: Sale de viaje a Europa y regresa en noviembre o diciembre | L2: Sí | M2: Prospecto / Visita | N2: 46253 | Q2: =IF(OR(B2="",L2<>"Sí"),"","Hola, "&B2&", excelente día. Le saluda *Alejandro Estrada* de Toyota Corregidora."&CHAR(10)&"Muchas gracias por visitarnos y conocer la *"&D2&"*. Fue un placer atenderle. Me pongo a sus órdenes por este medio para resolver cualquier duda que haya surgido o para agendarle una prueba de manejo."&CHAR(10)&"Quedo muy pendiente de lo que necesite para ayudarle a estrenar su próximo Toyota. ¡Saludos!"&CHAR(10)&CHAR(10)&Config!$B$1) | R2: =IF(Q2="","",HYPERLINK("https://wa.me/52"&C2&"?text="&_xlfn.ENCODEURL(Q2),"Enviar Bienvenida")) | S2: =IF(B2="","","Hola, "&B2&", muy buen día."&CHAR(10)&"Espero que esté teniendo una excelente semana. Le escribo para saber si tiene alguna duda sobre la oferta del *"&D2&"* que revisamos, con gusto le apoyo con información técnica o con las opciones de financiamiento disponibles."&CHAR(10)&"Quedo atento a sus comentarios para seguir avanzando hacia la entrega de su próximo Toyota. Gracias por su tiempo y confianza."&CHAR(10)&CHAR(10)&Config!$B$1) | T2: =IF(S2="","",HYPERLINK("https://wa.me/52"&C2&"?text="&_xlfn.ENCODEURL(S2),"Enviar Seguimiento")) | U2: =IF(B2="","",_xlfn.SWITCH(M2,"Apartado","Hola, "&B2&", buen día. Le confirmo que su apartado por el *"&D2&"* quedó registrado correctamente. Seguimos con el proceso y le mantendré informado(a) de cada paso.","Toma de vehículo","Hola, "&B2&", le comparto que estamos en el proceso de toma de su vehículo actual. En cuanto tengamos el resultado le aviso para continuar con el siguiente paso.","Pago vehículo a cuenta","Hola, "&B2&", quedamos en proceso de pago del vehículo que se toma a cuenta. Cualquier documento o aclaración que se requiera se lo haré saber por este medio.","Firma de contrato","Hola, "&B2&", ya estamos listos para agendar la firma de su contrato. ¿Qué día y hora se le facilita para realizarla?","Facturación","Hola, "&B2&", su unidad ya está en proceso de facturación. En breve le comparto los datos para su confirmación.","Programación de entrega","Hola, "&B2&", con gusto le comparto que ya podemos programar la entrega de su *"&D2&"*. ¿Qué día y hora le acomodan mejor?","Entregado","Hola, "&B2&", ¡muchas felicidades por estrenar su *"&D2&"*! Fue un gusto acompañarle en este proceso. Quedo pendiente de cualquier duda y con gusto le agendo su próxima cita de servicio cuando lo necesite.","Hola, "&B2&", seguimos en contacto para avanzar con el proceso de su próximo Toyota.")&CHAR(10)&CHAR(10)&Config!$B$1) | V2: =IF(U2="","",HYPERLINK("https://wa.me/52"&C2&"?text="&_xlfn.ENCODEURL(U2),"Enviar aviso de etapa")) | W2: =IF(OR(B2="",O2=""),"","Hola, "&B2&", ¡feliz cumpleaños! Le deseo un excelente día rodeado de quienes más quiere. Ha sido un placer acompañarle desde que estrenó su Toyota. ¡Un abrazo!"&CHAR(10)&CHAR(10)&Config!$B$1) | X2: =IF(W2="","",HYPERLINK("https://wa.me/52"&C2&"?text="&_xlfn.ENCODEURL(W2),"Enviar felicitación")) | Y2: =IF(OR(B2="",P2=""),"","Hola, "&B2&", hoy se cumple un año más desde que estrenó su *"&D2&"*. Espero que haya sido un gran compañero de camino. Cualquier cosa que necesite, aquí estoy para apoyarle."&CHAR(10)&CHAR(10)&Config!$B$1) | Z2: =IF(Y2="","",HYPERLINK("https://wa.me/52"&C2&"?text="&_xlfn.ENCODEURL(Y2),"Enviar aniversario")) | AB2: =IF(OR(B2="",AA2=""),"",HYPERLINK("https://wa.me/52"&C2&"?text="&_xlfn.ENCODEURL(_xlfn.SWITCH(AA2,"Bienvenida (primera visita)",Q2,"Seguimiento",S2,"Aviso de Etapa",U2,"Requisitos",AC2,"Datos de Facturación",AD2,"Cumpleaños",W2,"Aniversario",Y2,"")),"Enviar mensaje seleccionado")) | AC2: =IF(B2="","",_xlfn.SWITCH(F2&"|"&G2,"Crédito|Persona física","Hola, "&B2&", para continuar con el proceso de tu *"&D2&"* por "&F2&", estos son los documentos que necesitamos:"&CHAR(10)&CHAR(10)&"- INE"&CHAR(10)&"- Comprobante de domicilio (luz), a nombre del titular"&CHAR(10)&"- Estados de cuenta de los últimos 3 meses"&CHAR(10)&"- Constancia de situación fiscal (no mayor a 3 meses)","Crédito|Persona física con actividad empresarial","Hola, "&B2&", para continuar con el proceso de tu *"&D2&"* por "&F2&", estos son los documentos que necesitamos:"&CHAR(10)&CHAR(10)&"- INE"&CHAR(10)&"- Comprobante de domicilio (luz), a nombre del titular"&CHAR(10)&"- Estados de cuenta de los últimos 3 meses"&CHAR(10)&"- Constancia de situación fiscal (no mayor a 3 meses)"&CHAR(10)&"- Última declaración anual con acuse de recibo","Crédito|Persona moral","Hola, "&B2&", para continuar con el proceso de tu *"&D2&"* por "&F2&", estos son los documentos que necesitamos:"&CHAR(10)&CHAR(10)&"- Identificación oficial vigente del representante legal (INE o pasaporte)"&CHAR(10)&"- Comprobante de domicilio fiscal de la empresa (CFE, no mayor a 3 meses)"&CHAR(10)&"- Comprobante de domicilio del representante legal (CFE, no mayor a 3 meses)"&CHAR(10)&"- Últimos 3 meses de estados de cuenta bancarios de la empresa"&CHAR(10)&"- Constancia de situación fiscal de la empresa (no mayor a 3 meses)"&CHAR(10)&"- Constancia de situación fiscal del representante legal (no mayor a 3 meses)"&CHAR(10)&"- Declaración anual del último ejercicio, en digital, con acuse de recibo"&CHAR(10)&"- Estados financieros de la empresa (Resultados y Balance General), no mayor a 3 meses"&CHAR(10)&"- Escritura constitutiva, poderes o reformas de estatutos (primer acta, poder del representante y última acta)","Contado|Persona física","Hola, "&B2&", para continuar con el proceso de tu *"&D2&"* por "&F2&", estos son los documentos que necesitamos:"&CHAR(10)&CHAR(10)&"- INE"&CHAR(10)&"- Comprobante de domicilio"&CHAR(10)&"- Constancia de situación fiscal (no mayor a 3 meses)","Contado|Persona física con actividad empresarial","Hola, "&B2&", para continuar con el proceso de tu *"&D2&"* por "&F2&", estos son los documentos que necesitamos:"&CHAR(10)&CHAR(10)&"- INE"&CHAR(10)&"- Comprobante de domicilio"&CHAR(10)&"- Constancia de situación fiscal (no mayor a 3 meses)","Contado|Persona moral","Hola, "&B2&", para continuar con el proceso de tu *"&D2&"* por "&F2&", estos son los documentos que necesitamos:"&CHAR(10)&CHAR(10)&"- Identificación oficial vigente del representante legal y accionistas"&CHAR(10)&"- Comprobante de domicilio fiscal de la empresa (no mayor a 3 meses)"&CHAR(10)&"- Comprobante de domicilio del representante legal y accionistas (no mayor a 3 meses)"&CHAR(10)&"- Constancia de situación fiscal de la empresa (no mayor a 3 meses)"&CHAR(10)&"- Constancia de situación fiscal del representante legal y accionistas (no mayor a 3 meses)"&CHAR(10)&"- Escritura constitutiva, poderes o reformas de estatutos (primer acta, poder del representante y última acta)","Selecciona Método de Compra y Tipo de Persona.")&CHAR(10)&CHAR(10)&Config!$B$1) | AD2: =IFERROR(INDEX(Facturación!$Q:$Q,MATCH(B2,Facturación!$A:$A,0)),"")
A3: =IF(B3="","",ROW()-1) | B3: Adalberto Rusiles | C3: 4422055531 | D3: Hilux | E3: Base | F3: Crédito | G3: Persona física | H3: No | K3: En busca de la pickup mas pequeña | L3: Sí | M3: Prospecto / Visita | N3: 46251 | Q3: =IF(OR(B3="",L3<>"Sí"),"","Hola, "&B3&", excelente día. Le saluda *Alejandro Estrada* de Toyota Corregidora."&CHAR(10)&"Muchas gracias por visitarnos y conocer la *"&D3&"*. Fue un placer atenderle. Me pongo a sus órdenes por este medio para resolver cualquier duda que haya surgido o para agendarle una prueba de manejo."&CHAR(10)&"Quedo muy pendiente de lo que necesite para ayudarle a estrenar su próximo Toyota. ¡Saludos!"&CHAR(10)&CHAR(10)&Config!$B$1) | R3: =IF(Q3="","",HYPERLINK("https://wa.me/52"&C3&"?text="&_xlfn.ENCODEURL(Q3),"Enviar Bienvenida")) | S3: =IF(B3="","","Hola, "&B3&", muy buen día."&CHAR(10)&"Espero que esté teniendo una excelente semana. Le escribo para saber si tiene alguna duda sobre la oferta del *"&D3&"* que revisamos, con gusto le apoyo con información técnica o con las opciones de financiamiento disponibles."&CHAR(10)&"Quedo atento a sus comentarios para seguir avanzando hacia la entrega de su próximo Toyota. Gracias por su tiempo y confianza."&CHAR(10)&CHAR(10)&Config!$B$1) | T3: =IF(S3="","",HYPERLINK("https://wa.me/52"&C3&"?text="&_xlfn.ENCODEURL(S3),"Enviar Seguimiento")) | U3: =IF(B3="","",_xlfn.SWITCH(M3,"Apartado","Hola, "&B3&", buen día. Le confirmo que su apartado por el *"&D3&"* quedó registrado correctamente. Seguimos con el proceso y le mantendré informado(a) de cada paso.","Toma de vehículo","Hola, "&B3&", le comparto que estamos en el proceso de toma de su vehículo actual. En cuanto tengamos el resultado le aviso para continuar con el siguiente paso.","Pago vehículo a cuenta","Hola, "&B3&", quedamos en proceso de pago del vehículo que se toma a cuenta. Cualquier documento o aclaración que se requiera se lo haré saber por este medio.","Firma de contrato","Hola, "&B3&", ya estamos listos para agendar la firma de su contrato. ¿Qué día y hora se le facilita para realizarla?","Facturación","Hola, "&B3&", su unidad ya está en proceso de facturación. En breve le comparto los datos para su confirmación.","Programación de entrega","Hola, "&B3&", con gusto le comparto que ya podemos programar la entrega de su *"&D3&"*. ¿Qué día y hora le acomodan mejor?","Entregado","Hola, "&B3&", ¡muchas felicidades por estrenar su *"&D3&"*! Fue un gusto acompañarle en este proceso. Quedo pendiente de cualquier duda y con gusto le agendo su próxima cita de servicio cuando lo necesite.","Hola, "&B3&", seguimos en contacto para avanzar con el proceso de su próximo Toyota.")&CHAR(10)&CHAR(10)&Config!$B$1) | V3: =IF(U3="","",HYPERLINK("https://wa.me/52"&C3&"?text="&_xlfn.ENCODEURL(U3),"Enviar aviso de etapa")) | W3: =IF(OR(B3="",O3=""),"","Hola, "&B3&", ¡feliz cumpleaños! Le deseo un excelente día rodeado de quienes más quiere. Ha sido un placer acompañarle desde que estrenó su Toyota. ¡Un abrazo!"&CHAR(10)&CHAR(10)&Config!$B$1) | X3: =IF(W3="","",HYPERLINK("https://wa.me/52"&C3&"?text="&_xlfn.ENCODEURL(W3),"Enviar felicitación")) | Y3: =IF(OR(B3="",P3=""),"","Hola, "&B3&", hoy se cumple un año más desde que estrenó su *"&D3&"*. Espero que haya sido un gran compañero de camino. Cualquier cosa que necesite, aquí estoy para apoyarle."&CHAR(10)&CHAR(10)&Config!$B$1) | Z3: =IF(Y3="","",HYPERLINK("https://wa.me/52"&C3&"?text="&_xlfn.ENCODEURL(Y3),"Enviar aniversario")) | AB3: =IF(OR(B3="",AA3=""),"",HYPERLINK("https://wa.me/52"&C3&"?text="&_xlfn.ENCODEURL(_xlfn.SWITCH(AA3,"Bienvenida (primera visita)",Q3,"Seguimiento",S3,"Aviso de Etapa",U3,"Requisitos",AC3,"Datos de Facturación",AD3,"Cumpleaños",W3,"Aniversario",Y3,"")),"Enviar mensaje seleccionado")) | AC3: =IF(B3="","",_xlfn.SWITCH(F3&"|"&G3,"Crédito|Persona física","Hola, "&B3&", para continuar con el proceso de tu *"&D3&"* por "&F3&", estos son los documentos que necesitamos:"&CHAR(10)&CHAR(10)&"- INE"&CHAR(10)&"- Comprobante de domicilio (luz), a nombre del titular"&CHAR(10)&"- Estados de cuenta de los últimos 3 meses"&CHAR(10)&"- Constancia de situación fiscal (no mayor a 3 meses)","Crédito|Persona física con actividad empresarial","Hola, "&B3&", para continuar con el proceso de tu *"&D3&"* por "&F3&", estos son los documentos que necesitamos:"&CHAR(10)&CHAR(10)&"- INE"&CHAR(10)&"- Comprobante de domicilio (luz), a nombre del titular"&CHAR(10)&"- Estados de cuenta de los últimos 3 meses"&CHAR(10)&"- Constancia de situación fiscal (no mayor a 3 meses)"&CHAR(10)&"- Última declaración anual con acuse de recibo","Crédito|Persona moral","Hola, "&B3&", para continuar con el proceso de tu *"&D3&"* por "&F3&", estos son los documentos que necesitamos:"&CHAR(10)&CHAR(10)&"- Identificación oficial vigente del representante legal (INE o pasaporte)"&CHAR(10)&"- Comprobante de domicilio fiscal de la empresa (CFE, no mayor a 3 meses)"&CHAR(10)&"- Comprobante de domicilio del representante legal (CFE, no mayor a 3 meses)"&CHAR(10)&"- Últimos 3 meses de estados de cuenta bancarios de la empresa"&CHAR(10)&"- Constancia de situación fiscal de la empresa (no mayor a 3 meses)"&CHAR(10)&"- Constancia de situación fiscal del representante legal (no mayor a 3 meses)"&CHAR(10)&"- Declaración anual del último ejercicio, en digital, con acuse de recibo"&CHAR(10)&"- Estados financieros de la empresa (Resultados y Balance General), no mayor a 3 meses"&CHAR(10)&"- Escritura constitutiva, poderes o reformas de estatutos (primer acta, poder del representante y última acta)","Contado|Persona física","Hola, "&B3&", para continuar con el proceso de tu *"&D3&"* por "&F3&", estos son los documentos que necesitamos:"&CHAR(10)&CHAR(10)&"- INE"&CHAR(10)&"- Comprobante de domicilio"&CHAR(10)&"- Constancia de situación fiscal (no mayor a 3 meses)","Contado|Persona física con actividad empresarial","Hola, "&B3&", para continuar con el proceso de tu *"&D3&"* por "&F3&", estos son los documentos que necesitamos:"&CHAR(10)&CHAR(10)&"- INE"&CHAR(10)&"- Comprobante de domicilio"&CHAR(10)&"- Constancia de situación fiscal (no mayor a 3 meses)","Contado|Persona moral","Hola, "&B3&", para continuar con el proceso de tu *"&D3&"* por "&F3&", estos son los documentos que necesitamos:"&CHAR(10)&CHAR(10)&"- Identificación oficial vigente del representante legal y accionistas"&CHAR(10)&"- Comprobante de domicilio fiscal de la empresa (no mayor a 3 meses)"&CHAR(10)&"- Comprobante de domicilio del representante legal y accionistas (no mayor a 3 meses)"&CHAR(10)&"- Constancia de situación fiscal de la empresa (no mayor a 3 meses)"&CHAR(10)&"- Constancia de situación fiscal del representante legal y accionistas (no mayor a 3 meses)"&CHAR(10)&"- Escritura constitutiva, poderes o reformas de estatutos (primer acta, poder del representante y última acta)","Selecciona Método de Compra y Tipo de Persona.")&CHAR(10)&CHAR(10)&Config!$B$1) | AD3: =IFERROR(INDEX(Facturación!$Q:$Q,MATCH(B3,Facturación!$A:$A,0)),"")
A4: =IF(B4="","",ROW()-1) | B4: Miguel Corona | C4: 4424479460 | D4: Rav-4 | E4: XLE | F4: Contado | G4: Persona física | H4: No | K4: Cambiar a credito 100k | L4: Sí | M4: Apartado | N4: 46251 | O4: 46363 | Q4: =IF(OR(B4="",L4<>"Sí"),"","Hola, "&B4&", excelente día. Le saluda *Alejandro Estrada* de Toyota Corregidora."&CHAR(10)&"Muchas gracias por visitarnos y conocer la *"&D4&"*. Fue un placer atenderle. Me pongo a sus órdenes por este medio para resolver cualquier duda que haya surgido o para agendarle una prueba de manejo."&CHAR(10)&"Quedo muy pendiente de lo que necesite para ayudarle a estrenar su próximo Toyota. ¡Saludos!"&CHAR(10)&CHAR(10)&Config!$B$1) | R4: =IF(Q4="","",HYPERLINK("https://wa.me/52"&C4&"?text="&_xlfn.ENCODEURL(Q4),"Enviar Bienvenida")) | S4: =IF(B4="","","Hola, "&B4&", muy buen día."&CHAR(10)&"Espero que esté teniendo una excelente semana. Le escribo para saber si tiene alguna duda sobre la oferta del *"&D4&"* que revisamos, con gusto le apoyo con información técnica o con las opciones de financiamiento disponibles."&CHAR(10)&"Quedo atento a sus comentarios para seguir avanzando hacia la entrega de su próximo Toyota. Gracias por su tiempo y confianza."&CHAR(10)&CHAR(10)&Config!$B$1) | T4: =IF(S4="","",HYPERLINK("https://wa.me/52"&C4&"?text="&_xlfn.ENCODEURL(S4),"Enviar Seguimiento")) | U4: =IF(B4="","",_xlfn.SWITCH(M4,"Apartado","Hola, "&B4&", buen día. Le confirmo que su apartado por el *"&D4&"* quedó registrado correctamente. Seguimos con el proceso y le mantendré informado(a) de cada paso.","Toma de vehículo","Hola, "&B4&", le comparto que estamos en el proceso de toma de su vehículo actual. En cuanto tengamos el resultado le aviso para continuar con el siguiente paso.","Pago vehículo a cuenta","Hola, "&B4&", quedamos en proceso de pago del vehículo que se toma a cuenta. Cualquier documento o aclaración que se requiera se lo haré saber por este medio.","Firma de contrato","Hola, "&B4&", ya estamos listos para agendar la firma de su contrato. ¿Qué día y hora se le facilita para realizarla?","Facturación","Hola, "&B4&", su unidad ya está en proceso de facturación. En breve le comparto los datos para su confirmación.","Programación de entrega","Hola, "&B4&", con gusto le comparto que ya podemos programar la entrega de su *"&D4&"*. ¿Qué día y hora le acomodan mejor?","Entregado","Hola, "&B4&", ¡muchas felicidades por estrenar su *"&D4&"*! Fue un gusto acompañarle en este proceso. Quedo pendiente de cualquier duda y con gusto le agendo su próxima cita de servicio cuando lo necesite.","Hola, "&B4&", seguimos en contacto para avanzar con el proceso de su próximo Toyota.")&CHAR(10)&CHAR(10)&Config!$B$1) | V4: =IF(U4="","",HYPERLINK("https://wa.me/52"&C4&"?text="&_xlfn.ENCODEURL(U4),"Enviar aviso de etapa")) | W4: =IF(OR(B4="",O4=""),"","Hola, "&B4&", ¡feliz cumpleaños! Le deseo un excelente día rodeado de quienes más quiere. Ha sido un placer acompañarle desde que estrenó su Toyota. ¡Un abrazo!"&CHAR(10)&CHAR(10)&Config!$B$1) | X4: =IF(W4="","",HYPERLINK("https://wa.me/52"&C4&"?text="&_xlfn.ENCODEURL(W4),"Enviar felicitación")) | Y4: =IF(OR(B4="",P4=""),"","Hola, "&B4&", hoy se cumple un año más desde que estrenó su *"&D4&"*. Espero que haya sido un gran compañero de camino. Cualquier cosa que necesite, aquí estoy para apoyarle."&CHAR(10)&CHAR(10)&Config!$B$1) | Z4: =IF(Y4="","",HYPERLINK("https://wa.me/52"&C4&"?text="&_xlfn.ENCODEURL(Y4),"Enviar aniversario")) | AB4: =IF(OR(B4="",AA4=""),"",HYPERLINK("https://wa.me/52"&C4&"?text="&_xlfn.ENCODEURL(_xlfn.SWITCH(AA4,"Bienvenida (primera visita)",Q4,"Seguimiento",S4,"Aviso de Etapa",U4,"Requisitos",AC4,"Datos de Facturación",AD4,"Cumpleaños",W4,"Aniversario",Y4,"")),"Enviar mensaje seleccionado")) | AC4: =IF(B4="","",_xlfn.SWITCH(F4&"|"&G4,"Crédito|Persona física","Hola, "&B4&", para continuar con el proceso de tu *"&D4&"* por "&F4&", estos son los documentos que necesitamos:"&CHAR(10)&CHAR(10)&"- INE"&CHAR(10)&"- Comprobante de domicilio (luz), a nombre del titular"&CHAR(10)&"- Estados de cuenta de los últimos 3 meses"&CHAR(10)&"- Constancia de situación fiscal (no mayor a 3 meses)","Crédito|Persona física con actividad empresarial","Hola, "&B4&", para continuar con el proceso de tu *"&D4&"* por "&F4&", estos son los documentos que necesitamos:"&CHAR(10)&CHAR(10)&"- INE"&CHAR(10)&"- Comprobante de domicilio (luz), a nombre del titular"&CHAR(10)&"- Estados de cuenta de los últimos 3 meses"&CHAR(10)&"- Constancia de situación fiscal (no mayor a 3 meses)"&CHAR(10)&"- Última declaración anual con acuse de recibo","Crédito|Persona moral","Hola, "&B4&", para continuar con el proceso de tu *"&D4&"* por "&F4&", estos son los documentos que necesitamos:"&CHAR(10)&CHAR(10)&"- Identificación oficial vigente del representante legal (INE o pasaporte)"&CHAR(10)&"- Comprobante de domicilio fiscal de la empresa (CFE, no mayor a 3 meses)"&CHAR(10)&"- Comprobante de domicilio del representante legal (CFE, no mayor a 3 meses)"&CHAR(10)&"- Últimos 3 meses de estados de cuenta bancarios de la empresa"&CHAR(10)&"- Constancia de situación fiscal de la empresa (no mayor a 3 meses)"&CHAR(10)&"- Constancia de situación fiscal del representante legal (no mayor a 3 meses)"&CHAR(10)&"- Declaración anual del último ejercicio, en digital, con acuse de recibo"&CHAR(10)&"- Estados financieros de la empresa (Resultados y Balance General), no mayor a 3 meses"&CHAR(10)&"- Escritura constitutiva, poderes o reformas de estatutos (primer acta, poder del representante y última acta)","Contado|Persona física","Hola, "&B4&", para continuar con el proceso de tu *"&D4&"* por "&F4&", estos son los documentos que necesitamos:"&CHAR(10)&CHAR(10)&"- INE"&CHAR(10)&"- Comprobante de domicilio"&CHAR(10)&"- Constancia de situación fiscal (no mayor a 3 meses)","Contado|Persona física con actividad empresarial","Hola, "&B4&", para continuar con el proceso de tu *"&D4&"* por "&F4&", estos son los documentos que necesitamos:"&CHAR(10)&CHAR(10)&"- INE"&CHAR(10)&"- Comprobante de domicilio"&CHAR(10)&"- Constancia de situación fiscal (no mayor a 3 meses)","Contado|Persona moral","Hola, "&B4&", para continuar con el proceso de tu *"&D4&"* por "&F4&", estos son los documentos que necesitamos:"&CHAR(10)&CHAR(10)&"- Identificación oficial vigente del representante legal y accionistas"&CHAR(10)&"- Comprobante de domicilio fiscal de la empresa (no mayor a 3 meses)"&CHAR(10)&"- Comprobante de domicilio del representante legal y accionistas (no mayor a 3 meses)"&CHAR(10)&"- Constancia de situación fiscal de la empresa (no mayor a 3 meses)"&CHAR(10)&"- Constancia de situación fiscal del representante legal y accionistas (no mayor a 3 meses)"&CHAR(10)&"- Escritura constitutiva, poderes o reformas de estatutos (primer acta, poder del representante y última acta)","Selecciona Método de Compra y Tipo de Persona.")&CHAR(10)&CHAR(10)&Config!$B$1) | AD4: =IFERROR(INDEX(Facturación!$Q:$Q,MATCH(B4,Facturación!$A:$A,0)),"")
A5: =IF(B5="","",ROW()-1) | B5: Alejandra Arzate | C5: 4423050736 | D5: Hilux | E5: Base | F5: Crédito | G5: Persona física | H5: No | K5: Son de Jalpan, no tenian tiempo y se les envio cotizacion | L5: Sí | M5: Prospecto / Visita | N5: 46250 | Q5: =IF(OR(B5="",L5<>"Sí"),"","Hola, "&B5&", excelente día. Le saluda *Alejandro Estrada* de Toyota Corregidora."&CHAR(10)&"Muchas gracias por visitarnos y conocer la *"&D5&"*. Fue un placer atenderle. Me pongo a sus órdenes por este medio para resolver cualquier duda que haya surgido o para agendarle una prueba de manejo."&CHAR(10)&"Quedo muy pendiente de lo que necesite para ayudarle a estrenar su próximo Toyota. ¡Saludos!"&CHAR(10)&CHAR(10)&Config!$B$1) | R5: =IF(Q5="","",HYPERLINK("https://wa.me/52"&C5&"?text="&_xlfn.ENCODEURL(Q5),"Enviar Bienvenida")) | S5: =IF(B5="","","Hola, "&B5&", muy buen día."&CHAR(10)&"Espero que esté teniendo una excelente semana. Le escribo para saber si tiene alguna duda sobre la oferta del *"&D5&"* que revisamos, con gusto le apoyo con información técnica o con las opciones de financiamiento disponibles."&CHAR(10)&"Quedo atento a sus comentarios para seguir avanzando hacia la entrega de su próximo Toyota. Gracias por su tiempo y confianza."&CHAR(10)&CHAR(10)&Config!$B$1) | T5: =IF(S5="","",HYPERLINK("https://wa.me/52"&C5&"?text="&_xlfn.ENCODEURL(S5),"Enviar Seguimiento")) | U5: =IF(B5="","",_xlfn.SWITCH(M5,"Apartado","Hola, "&B5&", buen día. Le confirmo que su apartado por el *"&D5&"* quedó registrado correctamente. Seguimos con el proceso y le mantendré informado(a) de cada paso.","Toma de vehículo","Hola, "&B5&", le comparto que estamos en el proceso de toma de su vehículo actual. En cuanto tengamos el resultado le aviso para continuar con el siguiente paso.","Pago vehículo a cuenta","Hola, "&B5&", quedamos en proceso de pago del vehículo que se toma a cuenta. Cualquier documento o aclaración que se requiera se lo haré saber por este medio.","Firma de contrato","Hola, "&B5&", ya estamos listos para agendar la firma de su contrato. ¿Qué día y hora se le facilita para realizarla?","Facturación","Hola, "&B5&", su unidad ya está en proceso de facturación. En breve le comparto los datos para su confirmación.","Programación de entrega","Hola, "&B5&", con gusto le comparto que ya podemos programar la entrega de su *"&D5&"*. ¿Qué día y hora le acomodan mejor?","Entregado","Hola, "&B5&", ¡muchas felicidades por estrenar su *"&D5&"*! Fue un gusto acompañarle en este proceso. Quedo pendiente de cualquier duda y con gusto le agendo su próxima cita de servicio cuando lo necesite.","Hola, "&B5&", seguimos en contacto para avanzar con el proceso de su próximo Toyota.")&CHAR(10)&CHAR(10)&Config!$B$1) | V5: =IF(U5="","",HYPERLINK("https://wa.me/52"&C5&"?text="&_xlfn.ENCODEURL(U5),"Enviar aviso de etapa")) | W5: =IF(OR(B5="",O5=""),"","Hola, "&B5&", ¡feliz cumpleaños! Le deseo un excelente día rodeado de quienes más quiere. Ha sido un placer acompañarle desde que estrenó su Toyota. ¡Un abrazo!"&CHAR(10)&CHAR(10)&Config!$B$1) | X5: =IF(W5="","",HYPERLINK("https://wa.me/52"&C5&"?text="&_xlfn.ENCODEURL(W5),"Enviar felicitación")) | Y5: =IF(OR(B5="",P5=""),"","Hola, "&B5&", hoy se cumple un año más desde que estrenó su *"&D5&"*. Espero que haya sido un gran compañero de camino. Cualquier cosa que necesite, aquí estoy para apoyarle."&CHAR(10)&CHAR(10)&Config!$B$1) | Z5: =IF(Y5="","",HYPERLINK("https://wa.me/52"&C5&"?text="&_xlfn.ENCODEURL(Y5),"Enviar aniversario")) | AB5: =IF(OR(B5="",AA5=""),"",HYPERLINK("https://wa.me/52"&C5&"?text="&_xlfn.ENCODEURL(_xlfn.SWITCH(AA5,"Bienvenida (primera visita)",Q5,"Seguimiento",S5,"Aviso de Etapa",U5,"Requisitos",AC5,"Datos de Facturación",AD5,"Cumpleaños",W5,"Aniversario",Y5,"")),"Enviar mensaje seleccionado")) | AC5: =IF(B5="","",_xlfn.SWITCH(F5&"|"&G5,"Crédito|Persona física","Hola, "&B5&", para continuar con el proceso de tu *"&D5&"* por "&F5&", estos son los documentos que necesitamos:"&CHAR(10)&CHAR(10)&"- INE"&CHAR(10)&"- Comprobante de domicilio (luz), a nombre del titular"&CHAR(10)&"- Estados de cuenta de los últimos 3 meses"&CHAR(10)&"- Constancia de situación fiscal (no mayor a 3 meses)","Crédito|Persona física con actividad empresarial","Hola, "&B5&", para continuar con el proceso de tu *"&D5&"* por "&F5&", estos son los documentos que necesitamos:"&CHAR(10)&CHAR(10)&"- INE"&CHAR(10)&"- Comprobante de domicilio (luz), a nombre del titular"&CHAR(10)&"- Estados de cuenta de los últimos 3 meses"&CHAR(10)&"- Constancia de situación fiscal (no mayor a 3 meses)"&CHAR(10)&"- Última declaración anual con acuse de recibo","Crédito|Persona moral","Hola, "&B5&", para continuar con el proceso de tu *"&D5&"* por "&F5&", estos son los documentos que necesitamos:"&CHAR(10)&CHAR(10)&"- Identificación oficial vigente del representante legal (INE o pasaporte)"&CHAR(10)&"- Comprobante de domicilio fiscal de la empresa (CFE, no mayor a 3 meses)"&CHAR(10)&"- Comprobante de domicilio del representante legal (CFE, no mayor a 3 meses)"&CHAR(10)&"- Últimos 3 meses de estados de cuenta bancarios de la empresa"&CHAR(10)&"- Constancia de situación fiscal de la empresa (no mayor a 3 meses)"&CHAR(10)&"- Constancia de situación fiscal del representante legal (no mayor a 3 meses)"&CHAR(10)&"- Declaración anual del último ejercicio, en digital, con acuse de recibo"&CHAR(10)&"- Estados financieros de la empresa (Resultados y Balance General), no mayor a 3 meses"&CHAR(10)&"- Escritura constitutiva, poderes o reformas de estatutos (primer acta, poder del representante y última acta)","Contado|Persona física","Hola, "&B5&", para continuar con el proceso de tu *"&D5&"* por "&F5&", estos son los documentos que necesitamos:"&CHAR(10)&CHAR(10)&"- INE"&CHAR(10)&"- Comprobante de domicilio"&CHAR(10)&"- Constancia de situación fiscal (no mayor a 3 meses)","Contado|Persona física con actividad empresarial","Hola, "&B5&", para continuar con el proceso de tu *"&D5&"* por "&F5&", estos son los documentos que necesitamos:"&CHAR(10)&CHAR(10)&"- INE"&CHAR(10)&"- Comprobante de domicilio"&CHAR(10)&"- Constancia de situación fiscal (no mayor a 3 meses)","Contado|Persona moral","Hola, "&B5&", para continuar con el proceso de tu *"&D5&"* por "&F5&", estos son los documentos que necesitamos:"&CHAR(10)&CHAR(10)&"- Identificación oficial vigente del representante legal y accionistas"&CHAR(10)&"- Comprobante de domicilio fiscal de la empresa (no mayor a 3 meses)"&CHAR(10)&"- Comprobante de domicilio del representante legal y accionistas (no mayor a 3 meses)"&CHAR(10)&"- Constancia de situación fiscal de la empresa (no mayor a 3 meses)"&CHAR(10)&"- Constancia de situación fiscal del representante legal y accionistas (no mayor a 3 meses)"&CHAR(10)&"- Escritura constitutiva, poderes o reformas de estatutos (primer acta, poder del representante y última acta)","Selecciona Método de Compra y Tipo de Persona.")&CHAR(10)&CHAR(10)&Config!$B$1) | AD5: =IFERROR(INDEX(Facturación!$Q:$Q,MATCH(B5,Facturación!$A:$A,0)),"")
A6: =IF(B6="","",ROW()-1) | B6: Arelis Aguilar | C6: 4425994079 | D6: Sienna | E6: XSE | F6: Crédito | G6: Persona física | H6: No | K6: Está validando si sienna o corolla cross | L6: Sí | M6: Prospecto / Visita | N6: 46250 | Q6: =IF(OR(B6="",L6<>"Sí"),"","Hola, "&B6&", excelente día. Le saluda *Alejandro Estrada* de Toyota Corregidora."&CHAR(10)&"Muchas gracias por visitarnos y conocer la *"&D6&"*. Fue un placer atenderle. Me pongo a sus órdenes por este medio para resolver cualquier duda que haya surgido o para agendarle una prueba de manejo."&CHAR(10)&"Quedo muy pendiente de lo que necesite para ayudarle a estrenar su próximo Toyota. ¡Saludos!"&CHAR(10)&CHAR(10)&Config!$B$1) | R6: =IF(Q6="","",HYPERLINK("https://wa.me/52"&C6&"?text="&_xlfn.ENCODEURL(Q6),"Enviar Bienvenida")) | S6: =IF(B6="","","Hola, "&B6&", muy buen día."&CHAR(10)&"Espero que esté teniendo una excelente semana. Le escribo para saber si tiene alguna duda sobre la oferta del *"&D6&"* que revisamos, con gusto le apoyo con información técnica o con las opciones de financiamiento disponibles."&CHAR(10)&"Quedo atento a sus comentarios para seguir avanzando hacia la entrega de su próximo Toyota. Gracias por su tiempo y confianza."&CHAR(10)&CHAR(10)&Config!$B$1) | T6: =IF(S6="","",HYPERLINK("https://wa.me/52"&C6&"?text="&_xlfn.ENCODEURL(S6),"Enviar Seguimiento")) | U6: =IF(B6="","",_xlfn.SWITCH(M6,"Apartado","Hola, "&B6&", buen día. Le confirmo que su apartado por el *"&D6&"* quedó registrado correctamente. Seguimos con el proceso y le mantendré informado(a) de cada paso.","Toma de vehículo","Hola, "&B6&", le comparto que estamos en el proceso de toma de su vehículo actual. En cuanto tengamos el resultado le aviso para continuar con el siguiente paso.","Pago vehículo a cuenta","Hola, "&B6&", quedamos en proceso de pago del vehículo que se toma a cuenta. Cualquier documento o aclaración que se requiera se lo haré saber por este medio.","Firma de contrato","Hola, "&B6&", ya estamos listos para agendar la firma de su contrato. ¿Qué día y hora se le facilita para realizarla?","Facturación","Hola, "&B6&", su unidad ya está en proceso de facturación. En breve le comparto los datos para su confirmación.","Programación de entrega","Hola, "&B6&", con gusto le comparto que ya podemos programar la entrega de su *"&D6&"*. ¿Qué día y hora le acomodan mejor?","Entregado","Hola, "&B6&", ¡muchas felicidades por estrenar su *"&D6&"*! Fue un gusto acompañarle en este proceso. Quedo pendiente de cualquier duda y con gusto le agendo su próxima cita de servicio cuando lo necesite.","Hola, "&B6&", seguimos en contacto para avanzar con el proceso de su próximo Toyota.")&CHAR(10)&CHAR(10)&Config!$B$1) | V6: =IF(U6="","",HYPERLINK("https://wa.me/52"&C6&"?text="&_xlfn.ENCODEURL(U6),"Enviar aviso de etapa")) | W6: =IF(OR(B6="",O6=""),"","Hola, "&B6&", ¡feliz cumpleaños! Le deseo un excelente día rodeado de quienes más quiere. Ha sido un placer acompañarle desde que estrenó su Toyota. ¡Un abrazo!"&CHAR(10)&CHAR(10)&Config!$B$1) | X6: =IF(W6="","",HYPERLINK("https://wa.me/52"&C6&"?text="&_xlfn.ENCODEURL(W6),"Enviar felicitación")) | Y6: =IF(OR(B6="",P6=""),"","Hola, "&B6&", hoy se cumple un año más desde que estrenó su *"&D6&"*. Espero que haya sido un gran compañero de camino. Cualquier cosa que necesite, aquí estoy para apoyarle."&CHAR(10)&CHAR(10)&Config!$B$1) | Z6: =IF(Y6="","",HYPERLINK("https://wa.me/52"&C6&"?text="&_xlfn.ENCODEURL(Y6),"Enviar aniversario")) | AB6: =IF(OR(B6="",AA6=""),"",HYPERLINK("https://wa.me/52"&C6&"?text="&_xlfn.ENCODEURL(_xlfn.SWITCH(AA6,"Bienvenida (primera visita)",Q6,"Seguimiento",S6,"Aviso de Etapa",U6,"Requisitos",AC6,"Datos de Facturación",AD6,"Cumpleaños",W6,"Aniversario",Y6,"")),"Enviar mensaje seleccionado")) | AC6: =IF(B6="","",_xlfn.SWITCH(F6&"|"&G6,"Crédito|Persona física","Hola, "&B6&", para continuar con el proceso de tu *"&D6&"* por "&F6&", estos son los documentos que necesitamos:"&CHAR(10)&CHAR(10)&"- INE"&CHAR(10)&"- Comprobante de domicilio (luz), a nombre del titular"&CHAR(10)&"- Estados de cuenta de los últimos 3 meses"&CHAR(10)&"- Constancia de situación fiscal (no mayor a 3 meses)","Crédito|Persona física con actividad empresarial","Hola, "&B6&", para continuar con el proceso de tu *"&D6&"* por "&F6&", estos son los documentos que necesitamos:"&CHAR(10)&CHAR(10)&"- INE"&CHAR(10)&"- Comprobante de domicilio (luz), a nombre del titular"&CHAR(10)&"- Estados de cuenta de los últimos 3 meses"&CHAR(10)&"- Constancia de situación fiscal (no mayor a 3 meses)"&CHAR(10)&"- Última declaración anual con acuse de recibo","Crédito|Persona moral","Hola, "&B6&", para continuar con el proceso de tu *"&D6&"* por "&F6&", estos son los documentos que necesitamos:"&CHAR(10)&CHAR(10)&"- Identificación oficial vigente del representante legal (INE o pasaporte)"&CHAR(10)&"- Comprobante de domicilio fiscal de la empresa (CFE, no mayor a 3 meses)"&CHAR(10)&"- Comprobante de domicilio del representante legal (CFE, no mayor a 3 meses)"&CHAR(10)&"- Últimos 3 meses de estados de cuenta bancarios de la empresa"&CHAR(10)&"- Constancia de situación fiscal de la empresa (no mayor a 3 meses)"&CHAR(10)&"- Constancia de situación fiscal del representante legal (no mayor a 3 meses)"&CHAR(10)&"- Declaración anual del último ejercicio, en digital, con acuse de recibo"&CHAR(10)&"- Estados financieros de la empresa (Resultados y Balance General), no mayor a 3 meses"&CHAR(10)&"- Escritura constitutiva, poderes o reformas de estatutos (primer acta, poder del representante y última acta)","Contado|Persona física","Hola, "&B6&", para continuar con el proceso de tu *"&D6&"* por "&F6&", estos son los documentos que necesitamos:"&CHAR(10)&CHAR(10)&"- INE"&CHAR(10)&"- Comprobante de domicilio"&CHAR(10)&"- Constancia de situación fiscal (no mayor a 3 meses)","Contado|Persona física con actividad empresarial","Hola, "&B6&", para continuar con el proceso de tu *"&D6&"* por "&F6&", estos son los documentos que necesitamos:"&CHAR(10)&CHAR(10)&"- INE"&CHAR(10)&"- Comprobante de domicilio"&CHAR(10)&"- Constancia de situación fiscal (no mayor a 3 meses)","Contado|Persona moral","Hola, "&B6&", para continuar con el proceso de tu *"&D6&"* por "&F6&", estos son los documentos que necesitamos:"&CHAR(10)&CHAR(10)&"- Identificación oficial vigente del representante legal y accionistas"&CHAR(10)&"- Comprobante de domicilio fiscal de la empresa (no mayor a 3 meses)"&CHAR(10)&"- Comprobante de domicilio del representante legal y accionistas (no mayor a 3 meses)"&CHAR(10)&"- Constancia de situación fiscal de la empresa (no mayor a 3 meses)"&CHAR(10)&"- Constancia de situación fiscal del representante legal y accionistas (no mayor a 3 meses)"&CHAR(10)&"- Escritura constitutiva, poderes o reformas de estatutos (primer acta, poder del representante y última acta)","Selecciona Método de Compra y Tipo de Persona.")&CHAR(10)&CHAR(10)&Config!$B$1) | AD6: =IFERROR(INDEX(Facturación!$Q:$Q,MATCH(B6,Facturación!$A:$A,0)),"")
A7: =IF(B7="","",ROW()-1) | B7: Jesus Gonzalez | C7: 4421834457 | D7: Hilux | E7: Base | F7: Crédito | G7: Persona física | H7: No | K7: Seguimiento para validar si la compra | L7: Sí | M7: Prospecto / Visita | N7: 46250 | Q7: =IF(OR(B7="",L7<>"Sí"),"","Hola, "&B7&", excelente día. Le saluda *Alejandro Estrada* de Toyota Corregidora."&CHAR(10)&"Muchas gracias por visitarnos y conocer la *"&D7&"*. Fue un placer atenderle. Me pongo a sus órdenes por este medio para resolver cualquier duda que haya surgido o para agendarle una prueba de manejo."&CHAR(10)&"Quedo muy pendiente de lo que necesite para ayudarle a estrenar su próximo Toyota. ¡Saludos!"&CHAR(10)&CHAR(10)&Config!$B$1) | R7: =IF(Q7="","",HYPERLINK("https://wa.me/52"&C7&"?text="&_xlfn.ENCODEURL(Q7),"Enviar Bienvenida")) | S7: =IF(B7="","","Hola, "&B7&", muy buen día."&CHAR(10)&"Espero que esté teniendo una excelente semana. Le escribo para saber si tiene alguna duda sobre la oferta del *"&D7&"* que revisamos, con gusto le apoyo con información técnica o con las opciones de financiamiento disponibles."&CHAR(10)&"Quedo atento a sus comentarios para seguir avanzando hacia la entrega de su próximo Toyota. Gracias por su tiempo y confianza."&CHAR(10)&CHAR(10)&Config!$B$1) | T7: =IF(S7="","",HYPERLINK("https://wa.me/52"&C7&"?text="&_xlfn.ENCODEURL(S7),"Enviar Seguimiento")) | U7: =IF(B7="","",_xlfn.SWITCH(M7,"Apartado","Hola, "&B7&", buen día. Le confirmo que su apartado por el *"&D7&"* quedó registrado correctamente. Seguimos con el proceso y le mantendré informado(a) de cada paso.","Toma de vehículo","Hola, "&B7&", le comparto que estamos en el proceso de toma de su vehículo actual. En cuanto tengamos el resultado le aviso para continuar con el siguiente paso.","Pago vehículo a cuenta","Hola, "&B7&", quedamos en proceso de pago del vehículo que se toma a cuenta. Cualquier documento o aclaración que se requiera se lo haré saber por este medio.","Firma de contrato","Hola, "&B7&", ya estamos listos para agendar la firma de su contrato. ¿Qué día y hora se le facilita para realizarla?","Facturación","Hola, "&B7&", su unidad ya está en proceso de facturación. En breve le comparto los datos para su confirmación.","Programación de entrega","Hola, "&B7&", con gusto le comparto que ya podemos programar la entrega de su *"&D7&"*. ¿Qué día y hora le acomodan mejor?","Entregado","Hola, "&B7&", ¡muchas felicidades por estrenar su *"&D7&"*! Fue un gusto acompañarle en este proceso. Quedo pendiente de cualquier duda y con gusto le agendo su próxima cita de servicio cuando lo necesite.","Hola, "&B7&", seguimos en contacto para avanzar con el proceso de su próximo Toyota.")&CHAR(10)&CHAR(10)&Config!$B$1) | V7: =IF(U7="","",HYPERLINK("https://wa.me/52"&C7&"?text="&_xlfn.ENCODEURL(U7),"Enviar aviso de etapa")) | W7: =IF(OR(B7="",O7=""),"","Hola, "&B7&", ¡feliz cumpleaños! Le deseo un excelente día rodeado de quienes más quiere. Ha sido un placer acompañarle desde que estrenó su Toyota. ¡Un abrazo!"&CHAR(10)&CHAR(10)&Config!$B$1) | X7: =IF(W7="","",HYPERLINK("https://wa.me/52"&C7&"?text="&_xlfn.ENCODEURL(W7),"Enviar felicitación")) | Y7: =IF(OR(B7="",P7=""),"","Hola, "&B7&", hoy se cumple un año más desde que estrenó su *"&D7&"*. Espero que haya sido un gran compañero de camino. Cualquier cosa que necesite, aquí estoy para apoyarle."&CHAR(10)&CHAR(10)&Config!$B$1) | Z7: =IF(Y7="","",HYPERLINK("https://wa.me/52"&C7&"?text="&_xlfn.ENCODEURL(Y7),"Enviar aniversario")) | AB7: =IF(OR(B7="",AA7=""),"",HYPERLINK("https://wa.me/52"&C7&"?text="&_xlfn.ENCODEURL(_xlfn.SWITCH(AA7,"Bienvenida (primera visita)",Q7,"Seguimiento",S7,"Aviso de Etapa",U7,"Requisitos",AC7,"Datos de Facturación",AD7,"Cumpleaños",W7,"Aniversario",Y7,"")),"Enviar mensaje seleccionado")) | AC7: =IF(B7="","",_xlfn.SWITCH(F7&"|"&G7,"Crédito|Persona física","Hola, "&B7&", para continuar con el proceso de tu *"&D7&"* por "&F7&", estos son los documentos que necesitamos:"&CHAR(10)&CHAR(10)&"- INE"&CHAR(10)&"- Comprobante de domicilio (luz), a nombre del titular"&CHAR(10)&"- Estados de cuenta de los últimos 3 meses"&CHAR(10)&"- Constancia de situación fiscal (no mayor a 3 meses)","Crédito|Persona física con actividad empresarial","Hola, "&B7&", para continuar con el proceso de tu *"&D7&"* por "&F7&", estos son los documentos que necesitamos:"&CHAR(10)&CHAR(10)&"- INE"&CHAR(10)&"- Comprobante de domicilio (luz), a nombre del titular"&CHAR(10)&"- Estados de cuenta de los últimos 3 meses"&CHAR(10)&"- Constancia de situación fiscal (no mayor a 3 meses)"&CHAR(10)&"- Última declaración anual con acuse de recibo","Crédito|Persona moral","Hola, "&B7&", para continuar con el proceso de tu *"&D7&"* por "&F7&", estos son los documentos que necesitamos:"&CHAR(10)&CHAR(10)&"- Identificación oficial vigente del representante legal (INE o pasaporte)"&CHAR(10)&"- Comprobante de domicilio fiscal de la empresa (CFE, no mayor a 3 meses)"&CHAR(10)&"- Comprobante de domicilio del representante legal (CFE, no mayor a 3 meses)"&CHAR(10)&"- Últimos 3 meses de estados de cuenta bancarios de la empresa"&CHAR(10)&"- Constancia de situación fiscal de la empresa (no mayor a 3 meses)"&CHAR(10)&"- Constancia de situación fiscal del representante legal (no mayor a 3 meses)"&CHAR(10)&"- Declaración anual del último ejercicio, en digital, con acuse de recibo"&CHAR(10)&"- Estados financieros de la empresa (Resultados y Balance General), no mayor a 3 meses"&CHAR(10)&"- Escritura constitutiva, poderes o reformas de estatutos (primer acta, poder del representante y última acta)","Contado|Persona física","Hola, "&B7&", para continuar con el proceso de tu *"&D7&"* por "&F7&", estos son los documentos que necesitamos:"&CHAR(10)&CHAR(10)&"- INE"&CHAR(10)&"- Comprobante de domicilio"&CHAR(10)&"- Constancia de situación fiscal (no mayor a 3 meses)","Contado|Persona física con actividad empresarial","Hola, "&B7&", para continuar con el proceso de tu *"&D7&"* por "&F7&", estos son los documentos que necesitamos:"&CHAR(10)&CHAR(10)&"- INE"&CHAR(10)&"- Comprobante de domicilio"&CHAR(10)&"- Constancia de situación fiscal (no mayor a 3 meses)","Contado|Persona moral","Hola, "&B7&", para continuar con el proceso de tu *"&D7&"* por "&F7&", estos son los documentos que necesitamos:"&CHAR(10)&CHAR(10)&"- Identificación oficial vigente del representante legal y accionistas"&CHAR(10)&"- Comprobante de domicilio fiscal de la empresa (no mayor a 3 meses)"&CHAR(10)&"- Comprobante de domicilio del representante legal y accionistas (no mayor a 3 meses)"&CHAR(10)&"- Constancia de situación fiscal de la empresa (no mayor a 3 meses)"&CHAR(10)&"- Constancia de situación fiscal del representante legal y accionistas (no mayor a 3 meses)"&CHAR(10)&"- Escritura constitutiva, poderes o reformas de estatutos (primer acta, poder del representante y última acta)","Selecciona Método de Compra y Tipo de Persona.")&CHAR(10)&CHAR(10)&Config!$B$1) | AD7: =IFERROR(INDEX(Facturación!$Q:$Q,MATCH(B7,Facturación!$A:$A,0)),"")
A8: =IF(B8="","",ROW()-1) | B8: José Juan Gonzalez | C8: 4422192465 | D8: Corolla | E8: Base | F8: Crédito | G8: Persona física | H8: No | K8: En seguimiento | L8: Sí | M8: Prospecto / Visita | N8: 46248 | Q8: =IF(OR(B8="",L8<>"Sí"),"","Hola, "&B8&", excelente día. Le saluda *Alejandro Estrada* de Toyota Corregidora."&CHAR(10)&"Muchas gracias por visitarnos y conocer la *"&D8&"*. Fue un placer atenderle. Me pongo a sus órdenes por este medio para resolver cualquier duda que haya surgido o para agendarle una prueba de manejo."&CHAR(10)&"Quedo muy pendiente de lo que necesite para ayudarle a estrenar su próximo Toyota. ¡Saludos!"&CHAR(10)&CHAR(10)&Config!$B$1) | R8: =IF(Q8="","",HYPERLINK("https://wa.me/52"&C8&"?text="&_xlfn.ENCODEURL(Q8),"Enviar Bienvenida")) | S8: =IF(B8="","","Hola, "&B8&", muy buen día."&CHAR(10)&"Espero que esté teniendo una excelente semana. Le escribo para saber si tiene alguna duda sobre la oferta del *"&D8&"* que revisamos, con gusto le apoyo con información técnica o con las opciones de financiamiento disponibles."&CHAR(10)&"Quedo atento a sus comentarios para seguir avanzando hacia la entrega de su próximo Toyota. Gracias por su tiempo y confianza."&CHAR(10)&CHAR(10)&Config!$B$1) | T8: =IF(S8="","",HYPERLINK("https://wa.me/52"&C8&"?text="&_xlfn.ENCODEURL(S8),"Enviar Seguimiento")) | U8: =IF(B8="","",_xlfn.SWITCH(M8,"Apartado","Hola, "&B8&", buen día. Le confirmo que su apartado por el *"&D8&"* quedó registrado correctamente. Seguimos con el proceso y le mantendré informado(a) de cada paso.","Toma de vehículo","Hola, "&B8&", le comparto que estamos en el proceso de toma de su vehículo actual. En cuanto tengamos el resultado le aviso para continuar con el siguiente paso.","Pago vehículo a cuenta","Hola, "&B8&", quedamos en proceso de pago del vehículo que se toma a cuenta. Cualquier documento o aclaración que se requiera se lo haré saber por este medio.","Firma de contrato","Hola, "&B8&", ya estamos listos para agendar la firma de su contrato. ¿Qué día y hora se le facilita para realizarla?","Facturación","Hola, "&B8&", su unidad ya está en proceso de facturación. En breve le comparto los datos para su confirmación.","Programación de entrega","Hola, "&B8&", con gusto le comparto que ya podemos programar la entrega de su *"&D8&"*. ¿Qué día y hora le acomodan mejor?","Entregado","Hola, "&B8&", ¡muchas felicidades por estrenar su *"&D8&"*! Fue un gusto acompañarle en este proceso. Quedo pendiente de cualquier duda y con gusto le agendo su próxima cita de servicio cuando lo necesite.","Hola, "&B8&", seguimos en contacto para avanzar con el proceso de su próximo Toyota.")&CHAR(10)&CHAR(10)&Config!$B$1) | V8: =IF(U8="","",HYPERLINK("https://wa.me/52"&C8&"?text="&_xlfn.ENCODEURL(U8),"Enviar aviso de etapa")) | W8: =IF(OR(B8="",O8=""),"","Hola, "&B8&", ¡feliz cumpleaños! Le deseo un excelente día rodeado de quienes más quiere. Ha sido un placer acompañarle desde que estrenó su Toyota. ¡Un abrazo!"&CHAR(10)&CHAR(10)&Config!$B$1) | X8: =IF(W8="","",HYPERLINK("https://wa.me/52"&C8&"?text="&_xlfn.ENCODEURL(W8),"Enviar felicitación")) | Y8: =IF(OR(B8="",P8=""),"","Hola, "&B8&", hoy se cumple un año más desde que estrenó su *"&D8&"*. Espero que haya sido un gran compañero de camino. Cualquier cosa que necesite, aquí estoy para apoyarle."&CHAR(10)&CHAR(10)&Config!$B$1) | Z8: =IF(Y8="","",HYPERLINK("https://wa.me/52"&C8&"?text="&_xlfn.ENCODEURL(Y8),"Enviar aniversario")) | AB8: =IF(OR(B8="",AA8=""),"",HYPERLINK("https://wa.me/52"&C8&"?text="&_xlfn.ENCODEURL(_xlfn.SWITCH(AA8,"Bienvenida (primera visita)",Q8,"Seguimiento",S8,"Aviso de Etapa",U8,"Requisitos",AC8,"Datos de Facturación",AD8,"Cumpleaños",W8,"Aniversario",Y8,"")),"Enviar mensaje seleccionado")) | AC8: =IF(B8="","",_xlfn.SWITCH(F8&"|"&G8,"Crédito|Persona física","Hola, "&B8&", para continuar con el proceso de tu *"&D8&"* por "&F8&", estos son los documentos que necesitamos:"&CHAR(10)&CHAR(10)&"- INE"&CHAR(10)&"- Comprobante de domicilio (luz), a nombre del titular"&CHAR(10)&"- Estados de cuenta de los últimos 3 meses"&CHAR(10)&"- Constancia de situación fiscal (no mayor a 3 meses)","Crédito|Persona física con actividad empresarial","Hola, "&B8&", para continuar con el proceso de tu *"&D8&"* por "&F8&", estos son los documentos que necesitamos:"&CHAR(10)&CHAR(10)&"- INE"&CHAR(10)&"- Comprobante de domicilio (luz), a nombre del titular"&CHAR(10)&"- Estados de cuenta de los últimos 3 meses"&CHAR(10)&"- Constancia de situación fiscal (no mayor a 3 meses)"&CHAR(10)&"- Última declaración anual con acuse de recibo","Crédito|Persona moral","Hola, "&B8&", para continuar con el proceso de tu *"&D8&"* por "&F8&", estos son los documentos que necesitamos:"&CHAR(10)&CHAR(10)&"- Identificación oficial vigente del representante legal (INE o pasaporte)"&CHAR(10)&"- Comprobante de domicilio fiscal de la empresa (CFE, no mayor a 3 meses)"&CHAR(10)&"- Comprobante de domicilio del representante legal (CFE, no mayor a 3 meses)"&CHAR(10)&"- Últimos 3 meses de estados de cuenta bancarios de la empresa"&CHAR(10)&"- Constancia de situación fiscal de la empresa (no mayor a 3 meses)"&CHAR(10)&"- Constancia de situación fiscal del representante legal (no mayor a 3 meses)"&CHAR(10)&"- Declaración anual del último ejercicio, en digital, con acuse de recibo"&CHAR(10)&"- Estados financieros de la empresa (Resultados y Balance General), no mayor a 3 meses"&CHAR(10)&"- Escritura constitutiva, poderes o reformas de estatutos (primer acta, poder del representante y última acta)","Contado|Persona física","Hola, "&B8&", para continuar con el proceso de tu *"&D8&"* por "&F8&", estos son los documentos que necesitamos:"&CHAR(10)&CHAR(10)&"- INE"&CHAR(10)&"- Comprobante de domicilio"&CHAR(10)&"- Constancia de situación fiscal (no mayor a 3 meses)","Contado|Persona física con actividad empresarial","Hola, "&B8&", para continuar con el proceso de tu *"&D8&"* por "&F8&", estos son los documentos que necesitamos:"&CHAR(10)&CHAR(10)&"- INE"&CHAR(10)&"- Comprobante de domicilio"&CHAR(10)&"- Constancia de situación fiscal (no mayor a 3 meses)","Contado|Persona moral","Hola, "&B8&", para continuar con el proceso de tu *"&D8&"* por "&F8&", estos son los documentos que necesitamos:"&CHAR(10)&CHAR(10)&"- Identificación oficial vigente del representante legal y accionistas"&CHAR(10)&"- Comprobante de domicilio fiscal de la empresa (no mayor a 3 meses)"&CHAR(10)&"- Comprobante de domicilio del representante legal y accionistas (no mayor a 3 meses)"&CHAR(10)&"- Constancia de situación fiscal de la empresa (no mayor a 3 meses)"&CHAR(10)&"- Constancia de situación fiscal del representante legal y accionistas (no mayor a 3 meses)"&CHAR(10)&"- Escritura constitutiva, poderes o reformas de estatutos (primer acta, poder del representante y última acta)","Selecciona Método de Compra y Tipo de Persona.")&CHAR(10)&CHAR(10)&Config!$B$1) | AD8: =IFERROR(INDEX(Facturación!$Q:$Q,MATCH(B8,Facturación!$A:$A,0)),"")
A9: =IF(B9="","",ROW()-1) | B9: Rodrigo Aguilera | C9: 4421916064 | D9: Rav-4 | E9: XLE | F9: Crédito | G9: Persona física | H9: No | K9: No le gusto el tiempo de espera | L9: Sí | M9: Prospecto / Visita | N9: 46248 | Q9: =IF(OR(B9="",L9<>"Sí"),"","Hola, "&B9&", excelente día. Le saluda *Alejandro Estrada* de Toyota Corregidora."&CHAR(10)&"Muchas gracias por visitarnos y conocer la *"&D9&"*. Fue un placer atenderle. Me pongo a sus órdenes por este medio para resolver cualquier duda que haya surgido o para agendarle una prueba de manejo."&CHAR(10)&"Quedo muy pendiente de lo que necesite para ayudarle a estrenar su próximo Toyota. ¡Saludos!"&CHAR(10)&CHAR(10)&Config!$B$1) | R9: =IF(Q9="","",HYPERLINK("https://wa.me/52"&C9&"?text="&_xlfn.ENCODEURL(Q9),"Enviar Bienvenida")) | S9: =IF(B9="","","Hola, "&B9&", muy buen día."&CHAR(10)&"Espero que esté teniendo una excelente semana. Le escribo para saber si tiene alguna duda sobre la oferta del *"&D9&"* que revisamos, con gusto le apoyo con información técnica o con las opciones de financiamiento disponibles."&CHAR(10)&"Quedo atento a sus comentarios para seguir avanzando hacia la entrega de su próximo Toyota. Gracias por su tiempo y confianza."&CHAR(10)&CHAR(10)&Config!$B$1) | T9: =IF(S9="","",HYPERLINK("https://wa.me/52"&C9&"?text="&_xlfn.ENCODEURL(S9),"Enviar Seguimiento")) | U9: =IF(B9="","",_xlfn.SWITCH(M9,"Apartado","Hola, "&B9&", buen día. Le confirmo que su apartado por el *"&D9&"* quedó registrado correctamente. Seguimos con el proceso y le mantendré informado(a) de cada paso.","Toma de vehículo","Hola, "&B9&", le comparto que estamos en el proceso de toma de su vehículo actual. En cuanto tengamos el resultado le aviso para continuar con el siguiente paso.","Pago vehículo a cuenta","Hola, "&B9&", quedamos en proceso de pago del vehículo que se toma a cuenta. Cualquier documento o aclaración que se requiera se lo haré saber por este medio.","Firma de contrato","Hola, "&B9&", ya estamos listos para agendar la firma de su contrato. ¿Qué día y hora se le facilita para realizarla?","Facturación","Hola, "&B9&", su unidad ya está en proceso de facturación. En breve le comparto los datos para su confirmación.","Programación de entrega","Hola, "&B9&", con gusto le comparto que ya podemos programar la entrega de su *"&D9&"*. ¿Qué día y hora le acomodan mejor?","Entregado","Hola, "&B9&", ¡muchas felicidades por estrenar su *"&D9&"*! Fue un gusto acompañarle en este proceso. Quedo pendiente de cualquier duda y con gusto le agendo su próxima cita de servicio cuando lo necesite.","Hola, "&B9&", seguimos en contacto para avanzar con el proceso de su próximo Toyota.")&CHAR(10)&CHAR(10)&Config!$B$1) | V9: =IF(U9="","",HYPERLINK("https://wa.me/52"&C9&"?text="&_xlfn.ENCODEURL(U9),"Enviar aviso de etapa")) | W9: =IF(OR(B9="",O9=""),"","Hola, "&B9&", ¡feliz cumpleaños! Le deseo un excelente día rodeado de quienes más quiere. Ha sido un placer acompañarle desde que estrenó su Toyota. ¡Un abrazo!"&CHAR(10)&CHAR(10)&Config!$B$1) | X9: =IF(W9="","",HYPERLINK("https://wa.me/52"&C9&"?text="&_xlfn.ENCODEURL(W9),"Enviar felicitación")) | Y9: =IF(OR(B9="",P9=""),"","Hola, "&B9&", hoy se cumple un año más desde que estrenó su *"&D9&"*. Espero que haya sido un gran compañero de camino. Cualquier cosa que necesite, aquí estoy para apoyarle."&CHAR(10)&CHAR(10)&Config!$B$1) | Z9: =IF(Y9="","",HYPERLINK("https://wa.me/52"&C9&"?text="&_xlfn.ENCODEURL(Y9),"Enviar aniversario")) | AB9: =IF(OR(B9="",AA9=""),"",HYPERLINK("https://wa.me/52"&C9&"?text="&_xlfn.ENCODEURL(_xlfn.SWITCH(AA9,"Bienvenida (primera visita)",Q9,"Seguimiento",S9,"Aviso de Etapa",U9,"Requisitos",AC9,"Datos de Facturación",AD9,"Cumpleaños",W9,"Aniversario",Y9,"")),"Enviar mensaje seleccionado")) | AC9: =IF(B9="","",_xlfn.SWITCH(F9&"|"&G9,"Crédito|Persona física","Hola, "&B9&", para continuar con el proceso de tu *"&D9&"* por "&F9&", estos son los documentos que necesitamos:"&CHAR(10)&CHAR(10)&"- INE"&CHAR(10)&"- Comprobante de domicilio (luz), a nombre del titular"&CHAR(10)&"- Estados de cuenta de los últimos 3 meses"&CHAR(10)&"- Constancia de situación fiscal (no mayor a 3 meses)","Crédito|Persona física con actividad empresarial","Hola, "&B9&", para continuar con el proceso de tu *"&D9&"* por "&F9&", estos son los documentos que necesitamos:"&CHAR(10)&CHAR(10)&"- INE"&CHAR(10)&"- Comprobante de domicilio (luz), a nombre del titular"&CHAR(10)&"- Estados de cuenta de los últimos 3 meses"&CHAR(10)&"- Constancia de situación fiscal (no mayor a 3 meses)"&CHAR(10)&"- Última declaración anual con acuse de recibo","Crédito|Persona moral","Hola, "&B9&", para continuar con el proceso de tu *"&D9&"* por "&F9&", estos son los documentos que necesitamos:"&CHAR(10)&CHAR(10)&"- Identificación oficial vigente del representante legal (INE o pasaporte)"&CHAR(10)&"- Comprobante de domicilio fiscal de la empresa (CFE, no mayor a 3 meses)"&CHAR(10)&"- Comprobante de domicilio del representante legal (CFE, no mayor a 3 meses)"&CHAR(10)&"- Últimos 3 meses de estados de cuenta bancarios de la empresa"&CHAR(10)&"- Constancia de situación fiscal de la empresa (no mayor a 3 meses)"&CHAR(10)&"- Constancia de situación fiscal del representante legal (no mayor a 3 meses)"&CHAR(10)&"- Declaración anual del último ejercicio, en digital, con acuse de recibo"&CHAR(10)&"- Estados financieros de la empresa (Resultados y Balance General), no mayor a 3 meses"&CHAR(10)&"- Escritura constitutiva, poderes o reformas de estatutos (primer acta, poder del representante y última acta)","Contado|Persona física","Hola, "&B9&", para continuar con el proceso de tu *"&D9&"* por "&F9&", estos son los documentos que necesitamos:"&CHAR(10)&CHAR(10)&"- INE"&CHAR(10)&"- Comprobante de domicilio"&CHAR(10)&"- Constancia de situación fiscal (no mayor a 3 meses)","Contado|Persona física con actividad empresarial","Hola, "&B9&", para continuar con el proceso de tu *"&D9&"* por "&F9&", estos son los documentos que necesitamos:"&CHAR(10)&CHAR(10)&"- INE"&CHAR(10)&"- Comprobante de domicilio"&CHAR(10)&"- Constancia de situación fiscal (no mayor a 3 meses)","Contado|Persona moral","Hola, "&B9&", para continuar con el proceso de tu *"&D9&"* por "&F9&", estos son los documentos que necesitamos:"&CHAR(10)&CHAR(10)&"- Identificación oficial vigente del representante legal y accionistas"&CHAR(10)&"- Comprobante de domicilio fiscal de la empresa (no mayor a 3 meses)"&CHAR(10)&"- Comprobante de domicilio del representante legal y accionistas (no mayor a 3 meses)"&CHAR(10)&"- Constancia de situación fiscal de la empresa (no mayor a 3 meses)"&CHAR(10)&"- Constancia de situación fiscal del representante legal y accionistas (no mayor a 3 meses)"&CHAR(10)&"- Escritura constitutiva, poderes o reformas de estatutos (primer acta, poder del representante y última acta)","Selecciona Método de Compra y Tipo de Persona.")&CHAR(10)&CHAR(10)&Config!$B$1) | AD9: =IFERROR(INDEX(Facturación!$Q:$Q,MATCH(B9,Facturación!$A:$A,0)),"")
A10: =IF(B10="","",ROW()-1) | B10: Elias Hernandez | C10: 7711120165 | D10: Hilux | E10: Base | F10: Creidito | G10: Persona moral | H10: No | K10: En espera de documentos para tfs | L10: Sí | M10: Prospecto / Visita | N10: 46248 | Q10: =IF(OR(B10="",L10<>"Sí"),"","Hola, "&B10&", excelente día. Le saluda *Alejandro Estrada* de Toyota Corregidora."&CHAR(10)&"Muchas gracias por visitarnos y conocer la *"&D10&"*. Fue un placer atenderle. Me pongo a sus órdenes por este medio para resolver cualquier duda que haya surgido o para agendarle una prueba de manejo."&CHAR(10)&"Quedo muy pendiente de lo que necesite para ayudarle a estrenar su próximo Toyota. ¡Saludos!"&CHAR(10)&CHAR(10)&Config!$B$1) | R10: =IF(Q10="","",HYPERLINK("https://wa.me/52"&C10&"?text="&_xlfn.ENCODEURL(Q10),"Enviar Bienvenida")) | S10: =IF(B10="","","Hola, "&B10&", muy buen día."&CHAR(10)&"Espero que esté teniendo una excelente semana. Le escribo para saber si tiene alguna duda sobre la oferta del *"&D10&"* que revisamos, con gusto le apoyo con información técnica o con las opciones de financiamiento disponibles."&CHAR(10)&"Quedo atento a sus comentarios para seguir avanzando hacia la entrega de su próximo Toyota. Gracias por su tiempo y confianza."&CHAR(10)&CHAR(10)&Config!$B$1) | T10: =IF(S10="","",HYPERLINK("https://wa.me/52"&C10&"?text="&_xlfn.ENCODEURL(S10),"Enviar Seguimiento")) | U10: =IF(B10="","",_xlfn.SWITCH(M10,"Apartado","Hola, "&B10&", buen día. Le confirmo que su apartado por el *"&D10&"* quedó registrado correctamente. Seguimos con el proceso y le mantendré informado(a) de cada paso.","Toma de vehículo","Hola, "&B10&", le comparto que estamos en el proceso de toma de su vehículo actual. En cuanto tengamos el resultado le aviso para continuar con el siguiente paso.","Pago vehículo a cuenta","Hola, "&B10&", quedamos en proceso de pago del vehículo que se toma a cuenta. Cualquier documento o aclaración que se requiera se lo haré saber por este medio.","Firma de contrato","Hola, "&B10&", ya estamos listos para agendar la firma de su contrato. ¿Qué día y hora se le facilita para realizarla?","Facturación","Hola, "&B10&", su unidad ya está en proceso de facturación. En breve le comparto los datos para su confirmación.","Programación de entrega","Hola, "&B10&", con gusto le comparto que ya podemos programar la entrega de su *"&D10&"*. ¿Qué día y hora le acomodan mejor?","Entregado","Hola, "&B10&", ¡muchas felicidades por estrenar su *"&D10&"*! Fue un gusto acompañarle en este proceso. Quedo pendiente de cualquier duda y con gusto le agendo su próxima cita de servicio cuando lo necesite.","Hola, "&B10&", seguimos en contacto para avanzar con el proceso de su próximo Toyota.")&CHAR(10)&CHAR(10)&Config!$B$1) | V10: =IF(U10="","",HYPERLINK("https://wa.me/52"&C10&"?text="&_xlfn.ENCODEURL(U10),"Enviar aviso de etapa")) | W10: =IF(OR(B10="",O10=""),"","Hola, "&B10&", ¡feliz cumpleaños! Le deseo un excelente día rodeado de quienes más quiere. Ha sido un placer acompañarle desde que estrenó su Toyota. ¡Un abrazo!"&CHAR(10)&CHAR(10)&Config!$B$1) | X10: =IF(W10="","",HYPERLINK("https://wa.me/52"&C10&"?text="&_xlfn.ENCODEURL(W10),"Enviar felicitación")) | Y10: =IF(OR(B10="",P10=""),"","Hola, "&B10&", hoy se cumple un año más desde que estrenó su *"&D10&"*. Espero que haya sido un gran compañero de camino. Cualquier cosa que necesite, aquí estoy para apoyarle."&CHAR(10)&CHAR(10)&Config!$B$1) | Z10: =IF(Y10="","",HYPERLINK("https://wa.me/52"&C10&"?text="&_xlfn.ENCODEURL(Y10),"Enviar aniversario")) | AB10: =IF(OR(B10="",AA10=""),"",HYPERLINK("https://wa.me/52"&C10&"?text="&_xlfn.ENCODEURL(_xlfn.SWITCH(AA10,"Bienvenida (primera visita)",Q10,"Seguimiento",S10,"Aviso de Etapa",U10,"Requisitos",AC10,"Datos de Facturación",AD10,"Cumpleaños",W10,"Aniversario",Y10,"")),"Enviar mensaje seleccionado")) | AC10: =IF(B10="","",_xlfn.SWITCH(F10&"|"&G10,"Crédito|Persona física","Hola, "&B10&", para continuar con el proceso de tu *"&D10&"* por "&F10&", estos son los documentos que necesitamos:"&CHAR(10)&CHAR(10)&"- INE"&CHAR(10)&"- Comprobante de domicilio (luz), a nombre del titular"&CHAR(10)&"- Estados de cuenta de los últimos 3 meses"&CHAR(10)&"- Constancia de situación fiscal (no mayor a 3 meses)","Crédito|Persona física con actividad empresarial","Hola, "&B10&", para continuar con el proceso de tu *"&D10&"* por "&F10&", estos son los documentos que necesitamos:"&CHAR(10)&CHAR(10)&"- INE"&CHAR(10)&"- Comprobante de domicilio (luz), a nombre del titular"&CHAR(10)&"- Estados de cuenta de los últimos 3 meses"&CHAR(10)&"- Constancia de situación fiscal (no mayor a 3 meses)"&CHAR(10)&"- Última declaración anual con acuse de recibo","Crédito|Persona moral","Hola, "&B10&", para continuar con el proceso de tu *"&D10&"* por "&F10&", estos son los documentos que necesitamos:"&CHAR(10)&CHAR(10)&"- Identificación oficial vigente del representante legal (INE o pasaporte)"&CHAR(10)&"- Comprobante de domicilio fiscal de la empresa (CFE, no mayor a 3 meses)"&CHAR(10)&"- Comprobante de domicilio del representante legal (CFE, no mayor a 3 meses)"&CHAR(10)&"- Últimos 3 meses de estados de cuenta bancarios de la empresa"&CHAR(10)&"- Constancia de situación fiscal de la empresa (no mayor a 3 meses)"&CHAR(10)&"- Constancia de situación fiscal del representante legal (no mayor a 3 meses)"&CHAR(10)&"- Declaración anual del último ejercicio, en digital, con acuse de recibo"&CHAR(10)&"- Estados financieros de la empresa (Resultados y Balance General), no mayor a 3 meses"&CHAR(10)&"- Escritura constitutiva, poderes o reformas de estatutos (primer acta, poder del representante y última acta)","Contado|Persona física","Hola, "&B10&", para continuar con el proceso de tu *"&D10&"* por "&F10&", estos son los documentos que necesitamos:"&CHAR(10)&CHAR(10)&"- INE"&CHAR(10)&"- Comprobante de domicilio"&CHAR(10)&"- Constancia de situación fiscal (no mayor a 3 meses)","Contado|Persona física con actividad empresarial","Hola, "&B10&", para continuar con el proceso de tu *"&D10&"* por "&F10&", estos son los documentos que necesitamos:"&CHAR(10)&CHAR(10)&"- INE"&CHAR(10)&"- Comprobante de domicilio"&CHAR(10)&"- Constancia de situación fiscal (no mayor a 3 meses)","Contado|Persona moral","Hola, "&B10&", para continuar con el proceso de tu *"&D10&"* por "&F10&", estos son los documentos que necesitamos:"&CHAR(10)&CHAR(10)&"- Identificación oficial vigente del representante legal y accionistas"&CHAR(10)&"- Comprobante de domicilio fiscal de la empresa (no mayor a 3 meses)"&CHAR(10)&"- Comprobante de domicilio del representante legal y accionistas (no mayor a 3 meses)"&CHAR(10)&"- Constancia de situación fiscal de la empresa (no mayor a 3 meses)"&CHAR(10)&"- Constancia de situación fiscal del representante legal y accionistas (no mayor a 3 meses)"&CHAR(10)&"- Escritura constitutiva, poderes o reformas de estatutos (primer acta, poder del representante y última acta)","Selecciona Método de Compra y Tipo de Persona.")&CHAR(10)&CHAR(10)&Config!$B$1) | AD10: =IFERROR(INDEX(Facturación!$Q:$Q,MATCH(B10,Facturación!$A:$A,0)),"")
A11: =IF(B11="","",ROW()-1) | B11: YESICA NAYELLI REYES MARTINEZ | C11: 5516524745 | D11: COROLLA CROSS, LE, COLOR NEGRO, AUTOMATICA | N11: 46300 | Q11: =IF(OR(B11="",L11<>"Sí"),"","Hola, "&B11&", excelente día. Le saluda *Alejandro Estrada* de Toyota Corregidora."&CHAR(10)&"Muchas gracias por visitarnos y conocer la *"&D11&"*. Fue un placer atenderle. Me pongo a sus órdenes por este medio para resolver cualquier duda que haya surgido o para agendarle una prueba de manejo."&CHAR(10)&"Quedo muy pendiente de lo que necesite para ayudarle a estrenar su próximo Toyota. ¡Saludos!"&CHAR(10)&CHAR(10)&Config!$B$1) | R11: =IF(Q11="","",HYPERLINK("https://wa.me/52"&C11&"?text="&_xlfn.ENCODEURL(Q11),"Enviar Bienvenida")) | S11: =IF(B11="","","Hola, "&B11&", muy buen día."&CHAR(10)&"Espero que esté teniendo una excelente semana. Le escribo para saber si tiene alguna duda sobre la oferta del *"&D11&"* que revisamos, con gusto le apoyo con información técnica o con las opciones de financiamiento disponibles."&CHAR(10)&"Quedo atento a sus comentarios para seguir avanzando hacia la entrega de su próximo Toyota. Gracias por su tiempo y confianza."&CHAR(10)&CHAR(10)&Config!$B$1) | T11: =IF(S11="","",HYPERLINK("https://wa.me/52"&C11&"?text="&_xlfn.ENCODEURL(S11),"Enviar Seguimiento")) | U11: =IF(B11="","",_xlfn.SWITCH(M11,"Apartado","Hola, "&B11&", buen día. Le confirmo que su apartado por el *"&D11&"* quedó registrado correctamente. Seguimos con el proceso y le mantendré informado(a) de cada paso.","Toma de vehículo","Hola, "&B11&", le comparto que estamos en el proceso de toma de su vehículo actual. En cuanto tengamos el resultado le aviso para continuar con el siguiente paso.","Pago vehículo a cuenta","Hola, "&B11&", quedamos en proceso de pago del vehículo que se toma a cuenta. Cualquier documento o aclaración que se requiera se lo haré saber por este medio.","Firma de contrato","Hola, "&B11&", ya estamos listos para agendar la firma de su contrato. ¿Qué día y hora se le facilita para realizarla?","Facturación","Hola, "&B11&", su unidad ya está en proceso de facturación. En breve le comparto los datos para su confirmación.","Programación de entrega","Hola, "&B11&", con gusto le comparto que ya podemos programar la entrega de su *"&D11&"*. ¿Qué día y hora le acomodan mejor?","Entregado","Hola, "&B11&", ¡muchas felicidades por estrenar su *"&D11&"*! Fue un gusto acompañarle en este proceso. Quedo pendiente de cualquier duda y con gusto le agendo su próxima cita de servicio cuando lo necesite.","Hola, "&B11&", seguimos en contacto para avanzar con el proceso de su próximo Toyota.")&CHAR(10)&CHAR(10)&Config!$B$1) | V11: =IF(U11="","",HYPERLINK("https://wa.me/52"&C11&"?text="&_xlfn.ENCODEURL(U11),"Enviar aviso de etapa")) | W11: =IF(OR(B11="",O11=""),"","Hola, "&B11&", ¡feliz cumpleaños! Le deseo un excelente día rodeado de quienes más quiere. Ha sido un placer acompañarle desde que estrenó su Toyota. ¡Un abrazo!"&CHAR(10)&CHAR(10)&Config!$B$1) | X11: =IF(W11="","",HYPERLINK("https://wa.me/52"&C11&"?text="&_xlfn.ENCODEURL(W11),"Enviar felicitación")) | Y11: =IF(OR(B11="",P11=""),"","Hola, "&B11&", hoy se cumple un año más desde que estrenó su *"&D11&"*. Espero que haya sido un gran compañero de camino. Cualquier cosa que necesite, aquí estoy para apoyarle."&CHAR(10)&CHAR(10)&Config!$B$1) | Z11: =IF(Y11="","",HYPERLINK("https://wa.me/52"&C11&"?text="&_xlfn.ENCODEURL(Y11),"Enviar aniversario")) | AB11: =IF(OR(B11="",AA11=""),"",HYPERLINK("https://wa.me/52"&C11&"?text="&_xlfn.ENCODEURL(_xlfn.SWITCH(AA11,"Bienvenida (primera visita)",Q11,"Seguimiento",S11,"Aviso de Etapa",U11,"Requisitos",AC11,"Datos de Facturación",AD11,"Cumpleaños",W11,"Aniversario",Y11,"")),"Enviar mensaje seleccionado")) | AC11: =IF(B11="","",_xlfn.SWITCH(F11&"|"&G11,"Crédito|Persona física","Hola, "&B11&", para continuar con el proceso de tu *"&D11&"* por "&F11&", estos son los documentos que necesitamos:"&CHAR(10)&CHAR(10)&"- INE"&CHAR(10)&"- Comprobante de domicilio (luz), a nombre del titular"&CHAR(10)&"- Estados de cuenta de los últimos 3 meses"&CHAR(10)&"- Constancia de situación fiscal (no mayor a 3 meses)","Crédito|Persona física con actividad empresarial","Hola, "&B11&", para continuar con el proceso de tu *"&D11&"* por "&F11&", estos son los documentos que necesitamos:"&CHAR(10)&CHAR(10)&"- INE"&CHAR(10)&"- Comprobante de domicilio (luz), a nombre del titular"&CHAR(10)&"- Estados de cuenta de los últimos 3 meses"&CHAR(10)&"- Constancia de situación fiscal (no mayor a 3 meses)"&CHAR(10)&"- Última declaración anual con acuse de recibo","Crédito|Persona moral","Hola, "&B11&", para continuar con el proceso de tu *"&D11&"* por "&F11&", estos son los documentos que necesitamos:"&CHAR(10)&CHAR(10)&"- Identificación oficial vigente del representante legal (INE o pasaporte)"&CHAR(10)&"- Comprobante de domicilio fiscal de la empresa (CFE, no mayor a 3 meses)"&CHAR(10)&"- Comprobante de domicilio del representante legal (CFE, no mayor a 3 meses)"&CHAR(10)&"- Últimos 3 meses de estados de cuenta bancarios de la empresa"&CHAR(10)&"- Constancia de situación fiscal de la empresa (no mayor a 3 meses)"&CHAR(10)&"- Constancia de situación fiscal del representante legal (no mayor a 3 meses)"&CHAR(10)&"- Declaración anual del último ejercicio, en digital, con acuse de recibo"&CHAR(10)&"- Estados financieros de la empresa (Resultados y Balance General), no mayor a 3 meses"&CHAR(10)&"- Escritura constitutiva, poderes o reformas de estatutos (primer acta, poder del representante y última acta)","Contado|Persona física","Hola, "&B11&", para continuar con el proceso de tu *"&D11&"* por "&F11&", estos son los documentos que necesitamos:"&CHAR(10)&CHAR(10)&"- INE"&CHAR(10)&"- Comprobante de domicilio"&CHAR(10)&"- Constancia de situación fiscal (no mayor a 3 meses)","Contado|Persona física con actividad empresarial","Hola, "&B11&", para continuar con el proceso de tu *"&D11&"* por "&F11&", estos son los documentos que necesitamos:"&CHAR(10)&CHAR(10)&"- INE"&CHAR(10)&"- Comprobante de domicilio"&CHAR(10)&"- Constancia de situación fiscal (no mayor a 3 meses)","Contado|Persona moral","Hola, "&B11&", para continuar con el proceso de tu *"&D11&"* por "&F11&", estos son los documentos que necesitamos:"&CHAR(10)&CHAR(10)&"- Identificación oficial vigente del representante legal y accionistas"&CHAR(10)&"- Comprobante de domicilio fiscal de la empresa (no mayor a 3 meses)"&CHAR(10)&"- Comprobante de domicilio del representante legal y accionistas (no mayor a 3 meses)"&CHAR(10)&"- Constancia de situación fiscal de la empresa (no mayor a 3 meses)"&CHAR(10)&"- Constancia de situación fiscal del representante legal y accionistas (no mayor a 3 meses)"&CHAR(10)&"- Escritura constitutiva, poderes o reformas de estatutos (primer acta, poder del representante y última acta)","Selecciona Método de Compra y Tipo de Persona.")&CHAR(10)&CHAR(10)&Config!$B$1) | AD11: =IFERROR(INDEX(Facturación!$Q:$Q,MATCH(B11,Facturación!$A:$A,0)),"")
A12: =IF(B12="","",ROW()-1) | B12: SAINTS ENTERPRISES SC | C12: 4423628789 | D12: CAMRY LE, 2026, COLOR PLATA, AUTOMATICO | N12: 46302 | Q12: =IF(OR(B12="",L12<>"Sí"),"","Hola, "&B12&", excelente día. Le saluda *Alejandro Estrada* de Toyota Corregidora."&CHAR(10)&"Muchas gracias por visitarnos y conocer la *"&D12&"*. Fue un placer atenderle. Me pongo a sus órdenes por este medio para resolver cualquier duda que haya surgido o para agendarle una prueba de manejo."&CHAR(10)&"Quedo muy pendiente de lo que necesite para ayudarle a estrenar su próximo Toyota. ¡Saludos!"&CHAR(10)&CHAR(10)&Config!$B$1) | R12: =IF(Q12="","",HYPERLINK("https://wa.me/52"&C12&"?text="&_xlfn.ENCODEURL(Q12),"Enviar Bienvenida")) | S12: =IF(B12="","","Hola, "&B12&", muy buen día."&CHAR(10)&"Espero que esté teniendo una excelente semana. Le escribo para saber si tiene alguna duda sobre la oferta del *"&D12&"* que revisamos, con gusto le apoyo con información técnica o con las opciones de financiamiento disponibles."&CHAR(10)&"Quedo atento a sus comentarios para seguir avanzando hacia la entrega de su próximo Toyota. Gracias por su tiempo y confianza."&CHAR(10)&CHAR(10)&Config!$B$1) | T12: =IF(S12="","",HYPERLINK("https://wa.me/52"&C12&"?text="&_xlfn.ENCODEURL(S12),"Enviar Seguimiento")) | U12: =IF(B12="","",_xlfn.SWITCH(M12,"Apartado","Hola, "&B12&", buen día. Le confirmo que su apartado por el *"&D12&"* quedó registrado correctamente. Seguimos con el proceso y le mantendré informado(a) de cada paso.","Toma de vehículo","Hola, "&B12&", le comparto que estamos en el proceso de toma de su vehículo actual. En cuanto tengamos el resultado le aviso para continuar con el siguiente paso.","Pago vehículo a cuenta","Hola, "&B12&", quedamos en proceso de pago del vehículo que se toma a cuenta. Cualquier documento o aclaración que se requiera se lo haré saber por este medio.","Firma de contrato","Hola, "&B12&", ya estamos listos para agendar la firma de su contrato. ¿Qué día y hora se le facilita para realizarla?","Facturación","Hola, "&B12&", su unidad ya está en proceso de facturación. En breve le comparto los datos para su confirmación.","Programación de entrega","Hola, "&B12&", con gusto le comparto que ya podemos programar la entrega de su *"&D12&"*. ¿Qué día y hora le acomodan mejor?","Entregado","Hola, "&B12&", ¡muchas felicidades por estrenar su *"&D12&"*! Fue un gusto acompañarle en este proceso. Quedo pendiente de cualquier duda y con gusto le agendo su próxima cita de servicio cuando lo necesite.","Hola, "&B12&", seguimos en contacto para avanzar con el proceso de su próximo Toyota.")&CHAR(10)&CHAR(10)&Config!$B$1) | V12: =IF(U12="","",HYPERLINK("https://wa.me/52"&C12&"?text="&_xlfn.ENCODEURL(U12),"Enviar aviso de etapa")) | W12: =IF(OR(B12="",O12=""),"","Hola, "&B12&", ¡feliz cumpleaños! Le deseo un excelente día rodeado de quienes más quiere. Ha sido un placer acompañarle desde que estrenó su Toyota. ¡Un abrazo!"&CHAR(10)&CHAR(10)&Config!$B$1) | X12: =IF(W12="","",HYPERLINK("https://wa.me/52"&C12&"?text="&_xlfn.ENCODEURL(W12),"Enviar felicitación")) | Y12: =IF(OR(B12="",P12=""),"","Hola, "&B12&", hoy se cumple un año más desde que estrenó su *"&D12&"*. Espero que haya sido un gran compañero de camino. Cualquier cosa que necesite, aquí estoy para apoyarle."&CHAR(10)&CHAR(10)&Config!$B$1) | Z12: =IF(Y12="","",HYPERLINK("https://wa.me/52"&C12&"?text="&_xlfn.ENCODEURL(Y12),"Enviar aniversario")) | AB12: =IF(OR(B12="",AA12=""),"",HYPERLINK("https://wa.me/52"&C12&"?text="&_xlfn.ENCODEURL(_xlfn.SWITCH(AA12,"Bienvenida (primera visita)",Q12,"Seguimiento",S12,"Aviso de Etapa",U12,"Requisitos",AC12,"Datos de Facturación",AD12,"Cumpleaños",W12,"Aniversario",Y12,"")),"Enviar mensaje seleccionado")) | AC12: =IF(B12="","",_xlfn.SWITCH(F12&"|"&G12,"Crédito|Persona física","Hola, "&B12&", para continuar con el proceso de tu *"&D12&"* por "&F12&", estos son los documentos que necesitamos:"&CHAR(10)&CHAR(10)&"- INE"&CHAR(10)&"- Comprobante de domicilio (luz), a nombre del titular"&CHAR(10)&"- Estados de cuenta de los últimos 3 meses"&CHAR(10)&"- Constancia de situación fiscal (no mayor a 3 meses)","Crédito|Persona física con actividad empresarial","Hola, "&B12&", para continuar con el proceso de tu *"&D12&"* por "&F12&", estos son los documentos que necesitamos:"&CHAR(10)&CHAR(10)&"- INE"&CHAR(10)&"- Comprobante de domicilio (luz), a nombre del titular"&CHAR(10)&"- Estados de cuenta de los últimos 3 meses"&CHAR(10)&"- Constancia de situación fiscal (no mayor a 3 meses)"&CHAR(10)&"- Última declaración anual con acuse de recibo","Crédito|Persona moral","Hola, "&B12&", para continuar con el proceso de tu *"&D12&"* por "&F12&", estos son los documentos que necesitamos:"&CHAR(10)&CHAR(10)&"- Identificación oficial vigente del representante legal (INE o pasaporte)"&CHAR(10)&"- Comprobante de domicilio fiscal de la empresa (CFE, no mayor a 3 meses)"&CHAR(10)&"- Comprobante de domicilio del representante legal (CFE, no mayor a 3 meses)"&CHAR(10)&"- Últimos 3 meses de estados de cuenta bancarios de la empresa"&CHAR(10)&"- Constancia de situación fiscal de la empresa (no mayor a 3 meses)"&CHAR(10)&"- Constancia de situación fiscal del representante legal (no mayor a 3 meses)"&CHAR(10)&"- Declaración anual del último ejercicio, en digital, con acuse de recibo"&CHAR(10)&"- Estados financieros de la empresa (Resultados y Balance General), no mayor a 3 meses"&CHAR(10)&"- Escritura constitutiva, poderes o reformas de estatutos (primer acta, poder del representante y última acta)","Contado|Persona física","Hola, "&B12&", para continuar con el proceso de tu *"&D12&"* por "&F12&", estos son los documentos que necesitamos:"&CHAR(10)&CHAR(10)&"- INE"&CHAR(10)&"- Comprobante de domicilio"&CHAR(10)&"- Constancia de situación fiscal (no mayor a 3 meses)","Contado|Persona física con actividad empresarial","Hola, "&B12&", para continuar con el proceso de tu *"&D12&"* por "&F12&", estos son los documentos que necesitamos:"&CHAR(10)&CHAR(10)&"- INE"&CHAR(10)&"- Comprobante de domicilio"&CHAR(10)&"- Constancia de situación fiscal (no mayor a 3 meses)","Contado|Persona moral","Hola, "&B12&", para continuar con el proceso de tu *"&D12&"* por "&F12&", estos son los documentos que necesitamos:"&CHAR(10)&CHAR(10)&"- Identificación oficial vigente del representante legal y accionistas"&CHAR(10)&"- Comprobante de domicilio fiscal de la empresa (no mayor a 3 meses)"&CHAR(10)&"- Comprobante de domicilio del representante legal y accionistas (no mayor a 3 meses)"&CHAR(10)&"- Constancia de situación fiscal de la empresa (no mayor a 3 meses)"&CHAR(10)&"- Constancia de situación fiscal del representante legal y accionistas (no mayor a 3 meses)"&CHAR(10)&"- Escritura constitutiva, poderes o reformas de estatutos (primer acta, poder del representante y última acta)","Selecciona Método de Compra y Tipo de Persona.")&CHAR(10)&CHAR(10)&Config!$B$1) | AD12: =IFERROR(INDEX(Facturación!$Q:$Q,MATCH(B12,Facturación!$A:$A,0)),"")
A13: =IF(B13="","",ROW()-1) | B13: JAVIER AVICK GONZALEZ MUÑOZ | C13: 4424839331 | D13: TACOMA TRD 4X2, 2026, COLOR ROJO, AUTOMATICA | N13: 46303 | Q13: =IF(OR(B13="",L13<>"Sí"),"","Hola, "&B13&", excelente día. Le saluda *Alejandro Estrada* de Toyota Corregidora."&CHAR(10)&"Muchas gracias por visitarnos y conocer la *"&D13&"*. Fue un placer atenderle. Me pongo a sus órdenes por este medio para resolver cualquier duda que haya surgido o para agendarle una prueba de manejo."&CHAR(10)&"Quedo muy pendiente de lo que necesite para ayudarle a estrenar su próximo Toyota. ¡Saludos!"&CHAR(10)&CHAR(10)&Config!$B$1) | R13: =IF(Q13="","",HYPERLINK("https://wa.me/52"&C13&"?text="&_xlfn.ENCODEURL(Q13),"Enviar Bienvenida")) | S13: =IF(B13="","","Hola, "&B13&", muy buen día."&CHAR(10)&"Espero que esté teniendo una excelente semana. Le escribo para saber si tiene alguna duda sobre la oferta del *"&D13&"* que revisamos, con gusto le apoyo con información técnica o con las opciones de financiamiento disponibles."&CHAR(10)&"Quedo atento a sus comentarios para seguir avanzando hacia la entrega de su próximo Toyota. Gracias por su tiempo y confianza."&CHAR(10)&CHAR(10)&Config!$B$1) | T13: =IF(S13="","",HYPERLINK("https://wa.me/52"&C13&"?text="&_xlfn.ENCODEURL(S13),"Enviar Seguimiento")) | U13: =IF(B13="","",_xlfn.SWITCH(M13,"Apartado","Hola, "&B13&", buen día. Le confirmo que su apartado por el *"&D13&"* quedó registrado correctamente. Seguimos con el proceso y le mantendré informado(a) de cada paso.","Toma de vehículo","Hola, "&B13&", le comparto que estamos en el proceso de toma de su vehículo actual. En cuanto tengamos el resultado le aviso para continuar con el siguiente paso.","Pago vehículo a cuenta","Hola, "&B13&", quedamos en proceso de pago del vehículo que se toma a cuenta. Cualquier documento o aclaración que se requiera se lo haré saber por este medio.","Firma de contrato","Hola, "&B13&", ya estamos listos para agendar la firma de su contrato. ¿Qué día y hora se le facilita para realizarla?","Facturación","Hola, "&B13&", su unidad ya está en proceso de facturación. En breve le comparto los datos para su confirmación.","Programación de entrega","Hola, "&B13&", con gusto le comparto que ya podemos programar la entrega de su *"&D13&"*. ¿Qué día y hora le acomodan mejor?","Entregado","Hola, "&B13&", ¡muchas felicidades por estrenar su *"&D13&"*! Fue un gusto acompañarle en este proceso. Quedo pendiente de cualquier duda y con gusto le agendo su próxima cita de servicio cuando lo necesite.","Hola, "&B13&", seguimos en contacto para avanzar con el proceso de su próximo Toyota.")&CHAR(10)&CHAR(10)&Config!$B$1) | V13: =IF(U13="","",HYPERLINK("https://wa.me/52"&C13&"?text="&_xlfn.ENCODEURL(U13),"Enviar aviso de etapa")) | W13: =IF(OR(B13="",O13=""),"","Hola, "&B13&", ¡feliz cumpleaños! Le deseo un excelente día rodeado de quienes más quiere. Ha sido un placer acompañarle desde que estrenó su Toyota. ¡Un abrazo!"&CHAR(10)&CHAR(10)&Config!$B$1) | X13: =IF(W13="","",HYPERLINK("https://wa.me/52"&C13&"?text="&_xlfn.ENCODEURL(W13),"Enviar felicitación")) | Y13: =IF(OR(B13="",P13=""),"","Hola, "&B13&", hoy se cumple un año más desde que estrenó su *"&D13&"*. Espero que haya sido un gran compañero de camino. Cualquier cosa que necesite, aquí estoy para apoyarle."&CHAR(10)&CHAR(10)&Config!$B$1) | Z13: =IF(Y13="","",HYPERLINK("https://wa.me/52"&C13&"?text="&_xlfn.ENCODEURL(Y13),"Enviar aniversario")) | AB13: =IF(OR(B13="",AA13=""),"",HYPERLINK("https://wa.me/52"&C13&"?text="&_xlfn.ENCODEURL(_xlfn.SWITCH(AA13,"Bienvenida (primera visita)",Q13,"Seguimiento",S13,"Aviso de Etapa",U13,"Requisitos",AC13,"Datos de Facturación",AD13,"Cumpleaños",W13,"Aniversario",Y13,"")),"Enviar mensaje seleccionado")) | AC13: =IF(B13="","",_xlfn.SWITCH(F13&"|"&G13,"Crédito|Persona física","Hola, "&B13&", para continuar con el proceso de tu *"&D13&"* por "&F13&", estos son los documentos que necesitamos:"&CHAR(10)&CHAR(10)&"- INE"&CHAR(10)&"- Comprobante de domicilio (luz), a nombre del titular"&CHAR(10)&"- Estados de cuenta de los últimos 3 meses"&CHAR(10)&"- Constancia de situación fiscal (no mayor a 3 meses)","Crédito|Persona física con actividad empresarial","Hola, "&B13&", para continuar con el proceso de tu *"&D13&"* por "&F13&", estos son los documentos que necesitamos:"&CHAR(10)&CHAR(10)&"- INE"&CHAR(10)&"- Comprobante de domicilio (luz), a nombre del titular"&CHAR(10)&"- Estados de cuenta de los últimos 3 meses"&CHAR(10)&"- Constancia de situación fiscal (no mayor a 3 meses)"&CHAR(10)&"- Última declaración anual con acuse de recibo","Crédito|Persona moral","Hola, "&B13&", para continuar con el proceso de tu *"&D13&"* por "&F13&", estos son los documentos que necesitamos:"&CHAR(10)&CHAR(10)&"- Identificación oficial vigente del representante legal (INE o pasaporte)"&CHAR(10)&"- Comprobante de domicilio fiscal de la empresa (CFE, no mayor a 3 meses)"&CHAR(10)&"- Comprobante de domicilio del representante legal (CFE, no mayor a 3 meses)"&CHAR(10)&"- Últimos 3 meses de estados de cuenta bancarios de la empresa"&CHAR(10)&"- Constancia de situación fiscal de la empresa (no mayor a 3 meses)"&CHAR(10)&"- Constancia de situación fiscal del representante legal (no mayor a 3 meses)"&CHAR(10)&"- Declaración anual del último ejercicio, en digital, con acuse de recibo"&CHAR(10)&"- Estados financieros de la empresa (Resultados y Balance General), no mayor a 3 meses"&CHAR(10)&"- Escritura constitutiva, poderes o reformas de estatutos (primer acta, poder del representante y última acta)","Contado|Persona física","Hola, "&B13&", para continuar con el proceso de tu *"&D13&"* por "&F13&", estos son los documentos que necesitamos:"&CHAR(10)&CHAR(10)&"- INE"&CHAR(10)&"- Comprobante de domicilio"&CHAR(10)&"- Constancia de situación fiscal (no mayor a 3 meses)","Contado|Persona física con actividad empresarial","Hola, "&B13&", para continuar con el proceso de tu *"&D13&"* por "&F13&", estos son los documentos que necesitamos:"&CHAR(10)&CHAR(10)&"- INE"&CHAR(10)&"- Comprobante de domicilio"&CHAR(10)&"- Constancia de situación fiscal (no mayor a 3 meses)","Contado|Persona moral","Hola, "&B13&", para continuar con el proceso de tu *"&D13&"* por "&F13&", estos son los documentos que necesitamos:"&CHAR(10)&CHAR(10)&"- Identificación oficial vigente del representante legal y accionistas"&CHAR(10)&"- Comprobante de domicilio fiscal de la empresa (no mayor a 3 meses)"&CHAR(10)&"- Comprobante de domicilio del representante legal y accionistas (no mayor a 3 meses)"&CHAR(10)&"- Constancia de situación fiscal de la empresa (no mayor a 3 meses)"&CHAR(10)&"- Constancia de situación fiscal del representante legal y accionistas (no mayor a 3 meses)"&CHAR(10)&"- Escritura constitutiva, poderes o reformas de estatutos (primer acta, poder del representante y última acta)","Selecciona Método de Compra y Tipo de Persona.")&CHAR(10)&CHAR(10)&Config!$B$1) | AD13: =IFERROR(INDEX(Facturación!$Q:$Q,MATCH(B13,Facturación!$A:$A,0)),"")
A14: =IF(B14="","",ROW()-1) | B14: ESTEFANA GARCIA SUAREZ | C14: 4421430912 | D14: HILUX DIESEL, 2027, COLOR BLANCO, AUTOMATICA | N14: 46304 | Q14: =IF(OR(B14="",L14<>"Sí"),"","Hola, "&B14&", excelente día. Le saluda *Alejandro Estrada* de Toyota Corregidora."&CHAR(10)&"Muchas gracias por visitarnos y conocer la *"&D14&"*. Fue un placer atenderle. Me pongo a sus órdenes por este medio para resolver cualquier duda que haya surgido o para agendarle una prueba de manejo."&CHAR(10)&"Quedo muy pendiente de lo que necesite para ayudarle a estrenar su próximo Toyota. ¡Saludos!"&CHAR(10)&CHAR(10)&Config!$B$1) | R14: =IF(Q14="","",HYPERLINK("https://wa.me/52"&C14&"?text="&_xlfn.ENCODEURL(Q14),"Enviar Bienvenida")) | S14: =IF(B14="","","Hola, "&B14&", muy buen día."&CHAR(10)&"Espero que esté teniendo una excelente semana. Le escribo para saber si tiene alguna duda sobre la oferta del *"&D14&"* que revisamos, con gusto le apoyo con información técnica o con las opciones de financiamiento disponibles."&CHAR(10)&"Quedo atento a sus comentarios para seguir avanzando hacia la entrega de su próximo Toyota. Gracias por su tiempo y confianza."&CHAR(10)&CHAR(10)&Config!$B$1) | T14: =IF(S14="","",HYPERLINK("https://wa.me/52"&C14&"?text="&_xlfn.ENCODEURL(S14),"Enviar Seguimiento")) | U14: =IF(B14="","",_xlfn.SWITCH(M14,"Apartado","Hola, "&B14&", buen día. Le confirmo que su apartado por el *"&D14&"* quedó registrado correctamente. Seguimos con el proceso y le mantendré informado(a) de cada paso.","Toma de vehículo","Hola, "&B14&", le comparto que estamos en el proceso de toma de su vehículo actual. En cuanto tengamos el resultado le aviso para continuar con el siguiente paso.","Pago vehículo a cuenta","Hola, "&B14&", quedamos en proceso de pago del vehículo que se toma a cuenta. Cualquier documento o aclaración que se requiera se lo haré saber por este medio.","Firma de contrato","Hola, "&B14&", ya estamos listos para agendar la firma de su contrato. ¿Qué día y hora se le facilita para realizarla?","Facturación","Hola, "&B14&", su unidad ya está en proceso de facturación. En breve le comparto los datos para su confirmación.","Programación de entrega","Hola, "&B14&", con gusto le comparto que ya podemos programar la entrega de su *"&D14&"*. ¿Qué día y hora le acomodan mejor?","Entregado","Hola, "&B14&", ¡muchas felicidades por estrenar su *"&D14&"*! Fue un gusto acompañarle en este proceso. Quedo pendiente de cualquier duda y con gusto le agendo su próxima cita de servicio cuando lo necesite.","Hola, "&B14&", seguimos en contacto para avanzar con el proceso de su próximo Toyota.")&CHAR(10)&CHAR(10)&Config!$B$1) | V14: =IF(U14="","",HYPERLINK("https://wa.me/52"&C14&"?text="&_xlfn.ENCODEURL(U14),"Enviar aviso de etapa")) | W14: =IF(OR(B14="",O14=""),"","Hola, "&B14&", ¡feliz cumpleaños! Le deseo un excelente día rodeado de quienes más quiere. Ha sido un placer acompañarle desde que estrenó su Toyota. ¡Un abrazo!"&CHAR(10)&CHAR(10)&Config!$B$1) | X14: =IF(W14="","",HYPERLINK("https://wa.me/52"&C14&"?text="&_xlfn.ENCODEURL(W14),"Enviar felicitación")) | Y14: =IF(OR(B14="",P14=""),"","Hola, "&B14&", hoy se cumple un año más desde que estrenó su *"&D14&"*. Espero que haya sido un gran compañero de camino. Cualquier cosa que necesite, aquí estoy para apoyarle."&CHAR(10)&CHAR(10)&Config!$B$1) | Z14: =IF(Y14="","",HYPERLINK("https://wa.me/52"&C14&"?text="&_xlfn.ENCODEURL(Y14),"Enviar aniversario")) | AB14: =IF(OR(B14="",AA14=""),"",HYPERLINK("https://wa.me/52"&C14&"?text="&_xlfn.ENCODEURL(_xlfn.SWITCH(AA14,"Bienvenida (primera visita)",Q14,"Seguimiento",S14,"Aviso de Etapa",U14,"Requisitos",AC14,"Datos de Facturación",AD14,"Cumpleaños",W14,"Aniversario",Y14,"")),"Enviar mensaje seleccionado")) | AC14: =IF(B14="","",_xlfn.SWITCH(F14&"|"&G14,"Crédito|Persona física","Hola, "&B14&", para continuar con el proceso de tu *"&D14&"* por "&F14&", estos son los documentos que necesitamos:"&CHAR(10)&CHAR(10)&"- INE"&CHAR(10)&"- Comprobante de domicilio (luz), a nombre del titular"&CHAR(10)&"- Estados de cuenta de los últimos 3 meses"&CHAR(10)&"- Constancia de situación fiscal (no mayor a 3 meses)","Crédito|Persona física con actividad empresarial","Hola, "&B14&", para continuar con el proceso de tu *"&D14&"* por "&F14&", estos son los documentos que necesitamos:"&CHAR(10)&CHAR(10)&"- INE"&CHAR(10)&"- Comprobante de domicilio (luz), a nombre del titular"&CHAR(10)&"- Estados de cuenta de los últimos 3 meses"&CHAR(10)&"- Constancia de situación fiscal (no mayor a 3 meses)"&CHAR(10)&"- Última declaración anual con acuse de recibo","Crédito|Persona moral","Hola, "&B14&", para continuar con el proceso de tu *"&D14&"* por "&F14&", estos son los documentos que necesitamos:"&CHAR(10)&CHAR(10)&"- Identificación oficial vigente del representante legal (INE o pasaporte)"&CHAR(10)&"- Comprobante de domicilio fiscal de la empresa (CFE, no mayor a 3 meses)"&CHAR(10)&"- Comprobante de domicilio del representante legal (CFE, no mayor a 3 meses)"&CHAR(10)&"- Últimos 3 meses de estados de cuenta bancarios de la empresa"&CHAR(10)&"- Constancia de situación fiscal de la empresa (no mayor a 3 meses)"&CHAR(10)&"- Constancia de situación fiscal del representante legal (no mayor a 3 meses)"&CHAR(10)&"- Declaración anual del último ejercicio, en digital, con acuse de recibo"&CHAR(10)&"- Estados financieros de la empresa (Resultados y Balance General), no mayor a 3 meses"&CHAR(10)&"- Escritura constitutiva, poderes o reformas de estatutos (primer acta, poder del representante y última acta)","Contado|Persona física","Hola, "&B14&", para continuar con el proceso de tu *"&D14&"* por "&F14&", estos son los documentos que necesitamos:"&CHAR(10)&CHAR(10)&"- INE"&CHAR(10)&"- Comprobante de domicilio"&CHAR(10)&"- Constancia de situación fiscal (no mayor a 3 meses)","Contado|Persona física con actividad empresarial","Hola, "&B14&", para continuar con el proceso de tu *"&D14&"* por "&F14&", estos son los documentos que necesitamos:"&CHAR(10)&CHAR(10)&"- INE"&CHAR(10)&"- Comprobante de domicilio"&CHAR(10)&"- Constancia de situación fiscal (no mayor a 3 meses)","Contado|Persona moral","Hola, "&B14&", para continuar con el proceso de tu *"&D14&"* por "&F14&", estos son los documentos que necesitamos:"&CHAR(10)&CHAR(10)&"- Identificación oficial vigente del representante legal y accionistas"&CHAR(10)&"- Comprobante de domicilio fiscal de la empresa (no mayor a 3 meses)"&CHAR(10)&"- Comprobante de domicilio del representante legal y accionistas (no mayor a 3 meses)"&CHAR(10)&"- Constancia de situación fiscal de la empresa (no mayor a 3 meses)"&CHAR(10)&"- Constancia de situación fiscal del representante legal y accionistas (no mayor a 3 meses)"&CHAR(10)&"- Escritura constitutiva, poderes o reformas de estatutos (primer acta, poder del representante y última acta)","Selecciona Método de Compra y Tipo de Persona.")&CHAR(10)&CHAR(10)&Config!$B$1) | AD14: =IFERROR(INDEX(Facturación!$Q:$Q,MATCH(B14,Facturación!$A:$A,0)),"")
A15: =IF(B15="","",ROW()-1) | B15: ESTEFANA GARCIA SUAREZ | C15: 4421430912 | D15: HILUX DIESEL, 2027, COLOR BLANCO, AUTOMATICA | N15: 46304 | Q15: =IF(OR(B15="",L15<>"Sí"),"","Hola, "&B15&", excelente día. Le saluda *Alejandro Estrada* de Toyota Corregidora."&CHAR(10)&"Muchas gracias por visitarnos y conocer la *"&D15&"*. Fue un placer atenderle. Me pongo a sus órdenes por este medio para resolver cualquier duda que haya surgido o para agendarle una prueba de manejo."&CHAR(10)&"Quedo muy pendiente de lo que necesite para ayudarle a estrenar su próximo Toyota. ¡Saludos!"&CHAR(10)&CHAR(10)&Config!$B$1) | R15: =IF(Q15="","",HYPERLINK("https://wa.me/52"&C15&"?text="&_xlfn.ENCODEURL(Q15),"Enviar Bienvenida")) | S15: =IF(B15="","","Hola, "&B15&", muy buen día."&CHAR(10)&"Espero que esté teniendo una excelente semana. Le escribo para saber si tiene alguna duda sobre la oferta del *"&D15&"* que revisamos, con gusto le apoyo con información técnica o con las opciones de financiamiento disponibles."&CHAR(10)&"Quedo atento a sus comentarios para seguir avanzando hacia la entrega de su próximo Toyota. Gracias por su tiempo y confianza."&CHAR(10)&CHAR(10)&Config!$B$1) | T15: =IF(S15="","",HYPERLINK("https://wa.me/52"&C15&"?text="&_xlfn.ENCODEURL(S15),"Enviar Seguimiento")) | U15: =IF(B15="","",_xlfn.SWITCH(M15,"Apartado","Hola, "&B15&", buen día. Le confirmo que su apartado por el *"&D15&"* quedó registrado correctamente. Seguimos con el proceso y le mantendré informado(a) de cada paso.","Toma de vehículo","Hola, "&B15&", le comparto que estamos en el proceso de toma de su vehículo actual. En cuanto tengamos el resultado le aviso para continuar con el siguiente paso.","Pago vehículo a cuenta","Hola, "&B15&", quedamos en proceso de pago del vehículo que se toma a cuenta. Cualquier documento o aclaración que se requiera se lo haré saber por este medio.","Firma de contrato","Hola, "&B15&", ya estamos listos para agendar la firma de su contrato. ¿Qué día y hora se le facilita para realizarla?","Facturación","Hola, "&B15&", su unidad ya está en proceso de facturación. En breve le comparto los datos para su confirmación.","Programación de entrega","Hola, "&B15&", con gusto le comparto que ya podemos programar la entrega de su *"&D15&"*. ¿Qué día y hora le acomodan mejor?","Entregado","Hola, "&B15&", ¡muchas felicidades por estrenar su *"&D15&"*! Fue un gusto acompañarle en este proceso. Quedo pendiente de cualquier duda y con gusto le agendo su próxima cita de servicio cuando lo necesite.","Hola, "&B15&", seguimos en contacto para avanzar con el proceso de su próximo Toyota.")&CHAR(10)&CHAR(10)&Config!$B$1) | V15: =IF(U15="","",HYPERLINK("https://wa.me/52"&C15&"?text="&_xlfn.ENCODEURL(U15),"Enviar aviso de etapa")) | W15: =IF(OR(B15="",O15=""),"","Hola, "&B15&", ¡feliz cumpleaños! Le deseo un excelente día rodeado de quienes más quiere. Ha sido un placer acompañarle desde que estrenó su Toyota. ¡Un abrazo!"&CHAR(10)&CHAR(10)&Config!$B$1) | X15: =IF(W15="","",HYPERLINK("https://wa.me/52"&C15&"?text="&_xlfn.ENCODEURL(W15),"Enviar felicitación")) | Y15: =IF(OR(B15="",P15=""),"","Hola, "&B15&", hoy se cumple un año más desde que estrenó su *"&D15&"*. Espero que haya sido un gran compañero de camino. Cualquier cosa que necesite, aquí estoy para apoyarle."&CHAR(10)&CHAR(10)&Config!$B$1) | Z15: =IF(Y15="","",HYPERLINK("https://wa.me/52"&C15&"?text="&_xlfn.ENCODEURL(Y15),"Enviar aniversario")) | AB15: =IF(OR(B15="",AA15=""),"",HYPERLINK("https://wa.me/52"&C15&"?text="&_xlfn.ENCODEURL(_xlfn.SWITCH(AA15,"Bienvenida (primera visita)",Q15,"Seguimiento",S15,"Aviso de Etapa",U15,"Requisitos",AC15,"Datos de Facturación",AD15,"Cumpleaños",W15,"Aniversario",Y15,"")),"Enviar mensaje seleccionado")) | AC15: =IF(B15="","",_xlfn.SWITCH(F15&"|"&G15,"Crédito|Persona física","Hola, "&B15&", para continuar con el proceso de tu *"&D15&"* por "&F15&", estos son los documentos que necesitamos:"&CHAR(10)&CHAR(10)&"- INE"&CHAR(10)&"- Comprobante de domicilio (luz), a nombre del titular"&CHAR(10)&"- Estados de cuenta de los últimos 3 meses"&CHAR(10)&"- Constancia de situación fiscal (no mayor a 3 meses)","Crédito|Persona física con actividad empresarial","Hola, "&B15&", para continuar con el proceso de tu *"&D15&"* por "&F15&", estos son los documentos que necesitamos:"&CHAR(10)&CHAR(10)&"- INE"&CHAR(10)&"- Comprobante de domicilio (luz), a nombre del titular"&CHAR(10)&"- Estados de cuenta de los últimos 3 meses"&CHAR(10)&"- Constancia de situación fiscal (no mayor a 3 meses)"&CHAR(10)&"- Última declaración anual con acuse de recibo","Crédito|Persona moral","Hola, "&B15&", para continuar con el proceso de tu *"&D15&"* por "&F15&", estos son los documentos que necesitamos:"&CHAR(10)&CHAR(10)&"- Identificación oficial vigente del representante legal (INE o pasaporte)"&CHAR(10)&"- Comprobante de domicilio fiscal de la empresa (CFE, no mayor a 3 meses)"&CHAR(10)&"- Comprobante de domicilio del representante legal (CFE, no mayor a 3 meses)"&CHAR(10)&"- Últimos 3 meses de estados de cuenta bancarios de la empresa"&CHAR(10)&"- Constancia de situación fiscal de la empresa (no mayor a 3 meses)"&CHAR(10)&"- Constancia de situación fiscal del representante legal (no mayor a 3 meses)"&CHAR(10)&"- Declaración anual del último ejercicio, en digital, con acuse de recibo"&CHAR(10)&"- Estados financieros de la empresa (Resultados y Balance General), no mayor a 3 meses"&CHAR(10)&"- Escritura constitutiva, poderes o reformas de estatutos (primer acta, poder del representante y última acta)","Contado|Persona física","Hola, "&B15&", para continuar con el proceso de tu *"&D15&"* por "&F15&", estos son los documentos que necesitamos:"&CHAR(10)&CHAR(10)&"- INE"&CHAR(10)&"- Comprobante de domicilio"&CHAR(10)&"- Constancia de situación fiscal (no mayor a 3 meses)","Contado|Persona física con actividad empresarial","Hola, "&B15&", para continuar con el proceso de tu *"&D15&"* por "&F15&", estos son los documentos que necesitamos:"&CHAR(10)&CHAR(10)&"- INE"&CHAR(10)&"- Comprobante de domicilio"&CHAR(10)&"- Constancia de situación fiscal (no mayor a 3 meses)","Contado|Persona moral","Hola, "&B15&", para continuar con el proceso de tu *"&D15&"* por "&F15&", estos son los documentos que necesitamos:"&CHAR(10)&CHAR(10)&"- Identificación oficial vigente del representante legal y accionistas"&CHAR(10)&"- Comprobante de domicilio fiscal de la empresa (no mayor a 3 meses)"&CHAR(10)&"- Comprobante de domicilio del representante legal y accionistas (no mayor a 3 meses)"&CHAR(10)&"- Constancia de situación fiscal de la empresa (no mayor a 3 meses)"&CHAR(10)&"- Constancia de situación fiscal del representante legal y accionistas (no mayor a 3 meses)"&CHAR(10)&"- Escritura constitutiva, poderes o reformas de estatutos (primer acta, poder del representante y última acta)","Selecciona Método de Compra y Tipo de Persona.")&CHAR(10)&CHAR(10)&Config!$B$1) | AD15: =IFERROR(INDEX(Facturación!$Q:$Q,MATCH(B15,Facturación!$A:$A,0)),"")
A16: =IF(B16="","",ROW()-1) | B16: ANA CRISTINA RAMOS HERNANDEZ | C16: 4425543638 | D16: RAV4 XLE, COLOR ROJO, 2026, AUTOMATICA | N16: 46307 | Q16: =IF(OR(B16="",L16<>"Sí"),"","Hola, "&B16&", excelente día. Le saluda *Alejandro Estrada* de Toyota Corregidora."&CHAR(10)&"Muchas gracias por visitarnos y conocer la *"&D16&"*. Fue un placer atenderle. Me pongo a sus órdenes por este medio para resolver cualquier duda que haya surgido o para agendarle una prueba de manejo."&CHAR(10)&"Quedo muy pendiente de lo que necesite para ayudarle a estrenar su próximo Toyota. ¡Saludos!"&CHAR(10)&CHAR(10)&Config!$B$1) | R16: =IF(Q16="","",HYPERLINK("https://wa.me/52"&C16&"?text="&_xlfn.ENCODEURL(Q16),"Enviar Bienvenida")) | S16: =IF(B16="","","Hola, "&B16&", muy buen día."&CHAR(10)&"Espero que esté teniendo una excelente semana. Le escribo para saber si tiene alguna duda sobre la oferta del *"&D16&"* que revisamos, con gusto le apoyo con información técnica o con las opciones de financiamiento disponibles."&CHAR(10)&"Quedo atento a sus comentarios para seguir avanzando hacia la entrega de su próximo Toyota. Gracias por su tiempo y confianza."&CHAR(10)&CHAR(10)&Config!$B$1) | T16: =IF(S16="","",HYPERLINK("https://wa.me/52"&C16&"?text="&_xlfn.ENCODEURL(S16),"Enviar Seguimiento")) | U16: =IF(B16="","",_xlfn.SWITCH(M16,"Apartado","Hola, "&B16&", buen día. Le confirmo que su apartado por el *"&D16&"* quedó registrado correctamente. Seguimos con el proceso y le mantendré informado(a) de cada paso.","Toma de vehículo","Hola, "&B16&", le comparto que estamos en el proceso de toma de su vehículo actual. En cuanto tengamos el resultado le aviso para continuar con el siguiente paso.","Pago vehículo a cuenta","Hola, "&B16&", quedamos en proceso de pago del vehículo que se toma a cuenta. Cualquier documento o aclaración que se requiera se lo haré saber por este medio.","Firma de contrato","Hola, "&B16&", ya estamos listos para agendar la firma de su contrato. ¿Qué día y hora se le facilita para realizarla?","Facturación","Hola, "&B16&", su unidad ya está en proceso de facturación. En breve le comparto los datos para su confirmación.","Programación de entrega","Hola, "&B16&", con gusto le comparto que ya podemos programar la entrega de su *"&D16&"*. ¿Qué día y hora le acomodan mejor?","Entregado","Hola, "&B16&", ¡muchas felicidades por estrenar su *"&D16&"*! Fue un gusto acompañarle en este proceso. Quedo pendiente de cualquier duda y con gusto le agendo su próxima cita de servicio cuando lo necesite.","Hola, "&B16&", seguimos en contacto para avanzar con el proceso de su próximo Toyota.")&CHAR(10)&CHAR(10)&Config!$B$1) | V16: =IF(U16="","",HYPERLINK("https://wa.me/52"&C16&"?text="&_xlfn.ENCODEURL(U16),"Enviar aviso de etapa")) | W16: =IF(OR(B16="",O16=""),"","Hola, "&B16&", ¡feliz cumpleaños! Le deseo un excelente día rodeado de quienes más quiere. Ha sido un placer acompañarle desde que estrenó su Toyota. ¡Un abrazo!"&CHAR(10)&CHAR(10)&Config!$B$1) | X16: =IF(W16="","",HYPERLINK("https://wa.me/52"&C16&"?text="&_xlfn.ENCODEURL(W16),"Enviar felicitación")) | Y16: =IF(OR(B16="",P16=""),"","Hola, "&B16&", hoy se cumple un año más desde que estrenó su *"&D16&"*. Espero que haya sido un gran compañero de camino. Cualquier cosa que necesite, aquí estoy para apoyarle."&CHAR(10)&CHAR(10)&Config!$B$1) | Z16: =IF(Y16="","",HYPERLINK("https://wa.me/52"&C16&"?text="&_xlfn.ENCODEURL(Y16),"Enviar aniversario")) | AB16: =IF(OR(B16="",AA16=""),"",HYPERLINK("https://wa.me/52"&C16&"?text="&_xlfn.ENCODEURL(_xlfn.SWITCH(AA16,"Bienvenida (primera visita)",Q16,"Seguimiento",S16,"Aviso de Etapa",U16,"Requisitos",AC16,"Datos de Facturación",AD16,"Cumpleaños",W16,"Aniversario",Y16,"")),"Enviar mensaje seleccionado")) | AC16: =IF(B16="","",_xlfn.SWITCH(F16&"|"&G16,"Crédito|Persona física","Hola, "&B16&", para continuar con el proceso de tu *"&D16&"* por "&F16&", estos son los documentos que necesitamos:"&CHAR(10)&CHAR(10)&"- INE"&CHAR(10)&"- Comprobante de domicilio (luz), a nombre del titular"&CHAR(10)&"- Estados de cuenta de los últimos 3 meses"&CHAR(10)&"- Constancia de situación fiscal (no mayor a 3 meses)","Crédito|Persona física con actividad empresarial","Hola, "&B16&", para continuar con el proceso de tu *"&D16&"* por "&F16&", estos son los documentos que necesitamos:"&CHAR(10)&CHAR(10)&"- INE"&CHAR(10)&"- Comprobante de domicilio (luz), a nombre del titular"&CHAR(10)&"- Estados de cuenta de los últimos 3 meses"&CHAR(10)&"- Constancia de situación fiscal (no mayor a 3 meses)"&CHAR(10)&"- Última declaración anual con acuse de recibo","Crédito|Persona moral","Hola, "&B16&", para continuar con el proceso de tu *"&D16&"* por "&F16&", estos son los documentos que necesitamos:"&CHAR(10)&CHAR(10)&"- Identificación oficial vigente del representante legal (INE o pasaporte)"&CHAR(10)&"- Comprobante de domicilio fiscal de la empresa (CFE, no mayor a 3 meses)"&CHAR(10)&"- Comprobante de domicilio del representante legal (CFE, no mayor a 3 meses)"&CHAR(10)&"- Últimos 3 meses de estados de cuenta bancarios de la empresa"&CHAR(10)&"- Constancia de situación fiscal de la empresa (no mayor a 3 meses)"&CHAR(10)&"- Constancia de situación fiscal del representante legal (no mayor a 3 meses)"&CHAR(10)&"- Declaración anual del último ejercicio, en digital, con acuse de recibo"&CHAR(10)&"- Estados financieros de la empresa (Resultados y Balance General), no mayor a 3 meses"&CHAR(10)&"- Escritura constitutiva, poderes o reformas de estatutos (primer acta, poder del representante y última acta)","Contado|Persona física","Hola, "&B16&", para continuar con el proceso de tu *"&D16&"* por "&F16&", estos son los documentos que necesitamos:"&CHAR(10)&CHAR(10)&"- INE"&CHAR(10)&"- Comprobante de domicilio"&CHAR(10)&"- Constancia de situación fiscal (no mayor a 3 meses)","Contado|Persona física con actividad empresarial","Hola, "&B16&", para continuar con el proceso de tu *"&D16&"* por "&F16&", estos son los documentos que necesitamos:"&CHAR(10)&CHAR(10)&"- INE"&CHAR(10)&"- Comprobante de domicilio"&CHAR(10)&"- Constancia de situación fiscal (no mayor a 3 meses)","Contado|Persona moral","Hola, "&B16&", para continuar con el proceso de tu *"&D16&"* por "&F16&", estos son los documentos que necesitamos:"&CHAR(10)&CHAR(10)&"- Identificación oficial vigente del representante legal y accionistas"&CHAR(10)&"- Comprobante de domicilio fiscal de la empresa (no mayor a 3 meses)"&CHAR(10)&"- Comprobante de domicilio del representante legal y accionistas (no mayor a 3 meses)"&CHAR(10)&"- Constancia de situación fiscal de la empresa (no mayor a 3 meses)"&CHAR(10)&"- Constancia de situación fiscal del representante legal y accionistas (no mayor a 3 meses)"&CHAR(10)&"- Escritura constitutiva, poderes o reformas de estatutos (primer acta, poder del representante y última acta)","Selecciona Método de Compra y Tipo de Persona.")&CHAR(10)&CHAR(10)&Config!$B$1) | AD16: =IFERROR(INDEX(Facturación!$Q:$Q,MATCH(B16,Facturación!$A:$A,0)),"")
A17: =IF(B17="","",ROW()-1) | B17: ANA CRISTINA RAMOS HERNANDEZ | C17: 4425543638 | D17: RAV4 XLE, COLOR ROJO, 2026, AUTOMATICA | N17: 46307 | Q17: =IF(OR(B17="",L17<>"Sí"),"","Hola, "&B17&", excelente día. Le saluda *Alejandro Estrada* de Toyota Corregidora."&CHAR(10)&"Muchas gracias por visitarnos y conocer la *"&D17&"*. Fue un placer atenderle. Me pongo a sus órdenes por este medio para resolver cualquier duda que haya surgido o para agendarle una prueba de manejo."&CHAR(10)&"Quedo muy pendiente de lo que necesite para ayudarle a estrenar su próximo Toyota. ¡Saludos!"&CHAR(10)&CHAR(10)&Config!$B$1) | R17: =IF(Q17="","",HYPERLINK("https://wa.me/52"&C17&"?text="&_xlfn.ENCODEURL(Q17),"Enviar Bienvenida")) | S17: =IF(B17="","","Hola, "&B17&", muy buen día."&CHAR(10)&"Espero que esté teniendo una excelente semana. Le escribo para saber si tiene alguna duda sobre la oferta del *"&D17&"* que revisamos, con gusto le apoyo con información técnica o con las opciones de financiamiento disponibles."&CHAR(10)&"Quedo atento a sus comentarios para seguir avanzando hacia la entrega de su próximo Toyota. Gracias por su tiempo y confianza."&CHAR(10)&CHAR(10)&Config!$B$1) | T17: =IF(S17="","",HYPERLINK("https://wa.me/52"&C17&"?text="&_xlfn.ENCODEURL(S17),"Enviar Seguimiento")) | U17: =IF(B17="","",_xlfn.SWITCH(M17,"Apartado","Hola, "&B17&", buen día. Le confirmo que su apartado por el *"&D17&"* quedó registrado correctamente. Seguimos con el proceso y le mantendré informado(a) de cada paso.","Toma de vehículo","Hola, "&B17&", le comparto que estamos en el proceso de toma de su vehículo actual. En cuanto tengamos el resultado le aviso para continuar con el siguiente paso.","Pago vehículo a cuenta","Hola, "&B17&", quedamos en proceso de pago del vehículo que se toma a cuenta. Cualquier documento o aclaración que se requiera se lo haré saber por este medio.","Firma de contrato","Hola, "&B17&", ya estamos listos para agendar la firma de su contrato. ¿Qué día y hora se le facilita para realizarla?","Facturación","Hola, "&B17&", su unidad ya está en proceso de facturación. En breve le comparto los datos para su confirmación.","Programación de entrega","Hola, "&B17&", con gusto le comparto que ya podemos programar la entrega de su *"&D17&"*. ¿Qué día y hora le acomodan mejor?","Entregado","Hola, "&B17&", ¡muchas felicidades por estrenar su *"&D17&"*! Fue un gusto acompañarle en este proceso. Quedo pendiente de cualquier duda y con gusto le agendo su próxima cita de servicio cuando lo necesite.","Hola, "&B17&", seguimos en contacto para avanzar con el proceso de su próximo Toyota.")&CHAR(10)&CHAR(10)&Config!$B$1) | V17: =IF(U17="","",HYPERLINK("https://wa.me/52"&C17&"?text="&_xlfn.ENCODEURL(U17),"Enviar aviso de etapa")) | W17: =IF(OR(B17="",O17=""),"","Hola, "&B17&", ¡feliz cumpleaños! Le deseo un excelente día rodeado de quienes más quiere. Ha sido un placer acompañarle desde que estrenó su Toyota. ¡Un abrazo!"&CHAR(10)&CHAR(10)&Config!$B$1) | X17: =IF(W17="","",HYPERLINK("https://wa.me/52"&C17&"?text="&_xlfn.ENCODEURL(W17),"Enviar felicitación")) | Y17: =IF(OR(B17="",P17=""),"","Hola, "&B17&", hoy se cumple un año más desde que estrenó su *"&D17&"*. Espero que haya sido un gran compañero de camino. Cualquier cosa que necesite, aquí estoy para apoyarle."&CHAR(10)&CHAR(10)&Config!$B$1) | Z17: =IF(Y17="","",HYPERLINK("https://wa.me/52"&C17&"?text="&_xlfn.ENCODEURL(Y17),"Enviar aniversario")) | AB17: =IF(OR(B17="",AA17=""),"",HYPERLINK("https://wa.me/52"&C17&"?text="&_xlfn.ENCODEURL(_xlfn.SWITCH(AA17,"Bienvenida (primera visita)",Q17,"Seguimiento",S17,"Aviso de Etapa",U17,"Requisitos",AC17,"Datos de Facturación",AD17,"Cumpleaños",W17,"Aniversario",Y17,"")),"Enviar mensaje seleccionado")) | AC17: =IF(B17="","",_xlfn.SWITCH(F17&"|"&G17,"Crédito|Persona física","Hola, "&B17&", para continuar con el proceso de tu *"&D17&"* por "&F17&", estos son los documentos que necesitamos:"&CHAR(10)&CHAR(10)&"- INE"&CHAR(10)&"- Comprobante de domicilio (luz), a nombre del titular"&CHAR(10)&"- Estados de cuenta de los últimos 3 meses"&CHAR(10)&"- Constancia de situación fiscal (no mayor a 3 meses)","Crédito|Persona física con actividad empresarial","Hola, "&B17&", para continuar con el proceso de tu *"&D17&"* por "&F17&", estos son los documentos que necesitamos:"&CHAR(10)&CHAR(10)&"- INE"&CHAR(10)&"- Comprobante de domicilio (luz), a nombre del titular"&CHAR(10)&"- Estados de cuenta de los últimos 3 meses"&CHAR(10)&"- Constancia de situación fiscal (no mayor a 3 meses)"&CHAR(10)&"- Última declaración anual con acuse de recibo","Crédito|Persona moral","Hola, "&B17&", para continuar con el proceso de tu *"&D17&"* por "&F17&", estos son los documentos que necesitamos:"&CHAR(10)&CHAR(10)&"- Identificación oficial vigente del representante legal (INE o pasaporte)"&CHAR(10)&"- Comprobante de domicilio fiscal de la empresa (CFE, no mayor a 3 meses)"&CHAR(10)&"- Comprobante de domicilio del representante legal (CFE, no mayor a 3 meses)"&CHAR(10)&"- Últimos 3 meses de estados de cuenta bancarios de la empresa"&CHAR(10)&"- Constancia de situación fiscal de la empresa (no mayor a 3 meses)"&CHAR(10)&"- Constancia de situación fiscal del representante legal (no mayor a 3 meses)"&CHAR(10)&"- Declaración anual del último ejercicio, en digital, con acuse de recibo"&CHAR(10)&"- Estados financieros de la empresa (Resultados y Balance General), no mayor a 3 meses"&CHAR(10)&"- Escritura constitutiva, poderes o reformas de estatutos (primer acta, poder del representante y última acta)","Contado|Persona física","Hola, "&B17&", para continuar con el proceso de tu *"&D17&"* por "&F17&", estos son los documentos que necesitamos:"&CHAR(10)&CHAR(10)&"- INE"&CHAR(10)&"- Comprobante de domicilio"&CHAR(10)&"- Constancia de situación fiscal (no mayor a 3 meses)","Contado|Persona física con actividad empresarial","Hola, "&B17&", para continuar con el proceso de tu *"&D17&"* por "&F17&", estos son los documentos que necesitamos:"&CHAR(10)&CHAR(10)&"- INE"&CHAR(10)&"- Comprobante de domicilio"&CHAR(10)&"- Constancia de situación fiscal (no mayor a 3 meses)","Contado|Persona moral","Hola, "&B17&", para continuar con el proceso de tu *"&D17&"* por "&F17&", estos son los documentos que necesitamos:"&CHAR(10)&CHAR(10)&"- Identificación oficial vigente del representante legal y accionistas"&CHAR(10)&"- Comprobante de domicilio fiscal de la empresa (no mayor a 3 meses)"&CHAR(10)&"- Comprobante de domicilio del representante legal y accionistas (no mayor a 3 meses)"&CHAR(10)&"- Constancia de situación fiscal de la empresa (no mayor a 3 meses)"&CHAR(10)&"- Constancia de situación fiscal del representante legal y accionistas (no mayor a 3 meses)"&CHAR(10)&"- Escritura constitutiva, poderes o reformas de estatutos (primer acta, poder del representante y última acta)","Selecciona Método de Compra y Tipo de Persona.")&CHAR(10)&CHAR(10)&Config!$B$1) | AD17: =IFERROR(INDEX(Facturación!$Q:$Q,MATCH(B17,Facturación!$A:$A,0)),"")
A18: =IF(B18="","",ROW()-1) | Q18: =IF(OR(B18="",L18<>"Sí"),"","Hola, "&B18&", excelente día. Le saluda *Alejandro Estrada* de Toyota Corregidora."&CHAR(10)&"Muchas gracias por visitarnos y conocer la *"&D18&"*. Fue un placer atenderle. Me pongo a sus órdenes por este medio para resolver cualquier duda que haya surgido o para agendarle una prueba de manejo."&CHAR(10)&"Quedo muy pendiente de lo que necesite para ayudarle a estrenar su próximo Toyota. ¡Saludos!"&CHAR(10)&CHAR(10)&Config!$B$1) | R18: =IF(Q18="","",HYPERLINK("https://wa.me/52"&C18&"?text="&_xlfn.ENCODEURL(Q18),"Enviar Bienvenida")) | S18: =IF(B18="","","Hola, "&B18&", muy buen día."&CHAR(10)&"Espero que esté teniendo una excelente semana. Le escribo para saber si tiene alguna duda sobre la oferta del *"&D18&"* que revisamos, con gusto le apoyo con información técnica o con las opciones de financiamiento disponibles."&CHAR(10)&"Quedo atento a sus comentarios para seguir avanzando hacia la entrega de su próximo Toyota. Gracias por su tiempo y confianza."&CHAR(10)&CHAR(10)&Config!$B$1) | T18: =IF(S18="","",HYPERLINK("https://wa.me/52"&C18&"?text="&_xlfn.ENCODEURL(S18),"Enviar Seguimiento")) | U18: =IF(B18="","",_xlfn.SWITCH(M18,"Apartado","Hola, "&B18&", buen día. Le confirmo que su apartado por el *"&D18&"* quedó registrado correctamente. Seguimos con el proceso y le mantendré informado(a) de cada paso.","Toma de vehículo","Hola, "&B18&", le comparto que estamos en el proceso de toma de su vehículo actual. En cuanto tengamos el resultado le aviso para continuar con el siguiente paso.","Pago vehículo a cuenta","Hola, "&B18&", quedamos en proceso de pago del vehículo que se toma a cuenta. Cualquier documento o aclaración que se requiera se lo haré saber por este medio.","Firma de contrato","Hola, "&B18&", ya estamos listos para agendar la firma de su contrato. ¿Qué día y hora se le facilita para realizarla?","Facturación","Hola, "&B18&", su unidad ya está en proceso de facturación. En breve le comparto los datos para su confirmación.","Programación de entrega","Hola, "&B18&", con gusto le comparto que ya podemos programar la entrega de su *"&D18&"*. ¿Qué día y hora le acomodan mejor?","Entregado","Hola, "&B18&", ¡muchas felicidades por estrenar su *"&D18&"*! Fue un gusto acompañarle en este proceso. Quedo pendiente de cualquier duda y con gusto le agendo su próxima cita de servicio cuando lo necesite.","Hola, "&B18&", seguimos en contacto para avanzar con el proceso de su próximo Toyota.")&CHAR(10)&CHAR(10)&Config!$B$1) | V18: =IF(U18="","",HYPERLINK("https://wa.me/52"&C18&"?text="&_xlfn.ENCODEURL(U18),"Enviar aviso de etapa")) | W18: =IF(OR(B18="",O18=""),"","Hola, "&B18&", ¡feliz cumpleaños! Le deseo un excelente día rodeado de quienes más quiere. Ha sido un placer acompañarle desde que estrenó su Toyota. ¡Un abrazo!"&CHAR(10)&CHAR(10)&Config!$B$1) | X18: =IF(W18="","",HYPERLINK("https://wa.me/52"&C18&"?text="&_xlfn.ENCODEURL(W18),"Enviar felicitación")) | Y18: =IF(OR(B18="",P18=""),"","Hola, "&B18&", hoy se cumple un año más desde que estrenó su *"&D18&"*. Espero que haya sido un gran compañero de camino. Cualquier cosa que necesite, aquí estoy para apoyarle."&CHAR(10)&CHAR(10)&Config!$B$1) | Z18: =IF(Y18="","",HYPERLINK("https://wa.me/52"&C18&"?text="&_xlfn.ENCODEURL(Y18),"Enviar aniversario")) | AB18: =IF(OR(B18="",AA18=""),"",HYPERLINK("https://wa.me/52"&C18&"?text="&_xlfn.ENCODEURL(_xlfn.SWITCH(AA18,"Bienvenida (primera visita)",Q18,"Seguimiento",S18,"Aviso de Etapa",U18,"Requisitos",AC18,"Datos de Facturación",AD18,"Cumpleaños",W18,"Aniversario",Y18,"")),"Enviar mensaje seleccionado")) | AC18: =IF(B18="","",_xlfn.SWITCH(F18&"|"&G18,"Crédito|Persona física","Hola, "&B18&", para continuar con el proceso de tu *"&D18&"* por "&F18&", estos son los documentos que necesitamos:"&CHAR(10)&CHAR(10)&"- INE"&CHAR(10)&"- Comprobante de domicilio (luz), a nombre del titular"&CHAR(10)&"- Estados de cuenta de los últimos 3 meses"&CHAR(10)&"- Constancia de situación fiscal (no mayor a 3 meses)","Crédito|Persona física con actividad empresarial","Hola, "&B18&", para continuar con el proceso de tu *"&D18&"* por "&F18&", estos son los documentos que necesitamos:"&CHAR(10)&CHAR(10)&"- INE"&CHAR(10)&"- Comprobante de domicilio (luz), a nombre del titular"&CHAR(10)&"- Estados de cuenta de los últimos 3 meses"&CHAR(10)&"- Constancia de situación fiscal (no mayor a 3 meses)"&CHAR(10)&"- Última declaración anual con acuse de recibo","Crédito|Persona moral","Hola, "&B18&", para continuar con el proceso de tu *"&D18&"* por "&F18&", estos son los documentos que necesitamos:"&CHAR(10)&CHAR(10)&"- Identificación oficial vigente del representante legal (INE o pasaporte)"&CHAR(10)&"- Comprobante de domicilio fiscal de la empresa (CFE, no mayor a 3 meses)"&CHAR(10)&"- Comprobante de domicilio del representante legal (CFE, no mayor a 3 meses)"&CHAR(10)&"- Últimos 3 meses de estados de cuenta bancarios de la empresa"&CHAR(10)&"- Constancia de situación fiscal de la empresa (no mayor a 3 meses)"&CHAR(10)&"- Constancia de situación fiscal del representante legal (no mayor a 3 meses)"&CHAR(10)&"- Declaración anual del último ejercicio, en digital, con acuse de recibo"&CHAR(10)&"- Estados financieros de la empresa (Resultados y Balance General), no mayor a 3 meses"&CHAR(10)&"- Escritura constitutiva, poderes o reformas de estatutos (primer acta, poder del representante y última acta)","Contado|Persona física","Hola, "&B18&", para continuar con el proceso de tu *"&D18&"* por "&F18&", estos son los documentos que necesitamos:"&CHAR(10)&CHAR(10)&"- INE"&CHAR(10)&"- Comprobante de domicilio"&CHAR(10)&"- Constancia de situación fiscal (no mayor a 3 meses)","Contado|Persona física con actividad empresarial","Hola, "&B18&", para continuar con el proceso de tu *"&D18&"* por "&F18&", estos son los documentos que necesitamos:"&CHAR(10)&CHAR(10)&"- INE"&CHAR(10)&"- Comprobante de domicilio"&CHAR(10)&"- Constancia de situación fiscal (no mayor a 3 meses)","Contado|Persona moral","Hola, "&B18&", para continuar con el proceso de tu *"&D18&"* por "&F18&", estos son los documentos que necesitamos:"&CHAR(10)&CHAR(10)&"- Identificación oficial vigente del representante legal y accionistas"&CHAR(10)&"- Comprobante de domicilio fiscal de la empresa (no mayor a 3 meses)"&CHAR(10)&"- Comprobante de domicilio del representante legal y accionistas (no mayor a 3 meses)"&CHAR(10)&"- Constancia de situación fiscal de la empresa (no mayor a 3 meses)"&CHAR(10)&"- Constancia de situación fiscal del representante legal y accionistas (no mayor a 3 meses)"&CHAR(10)&"- Escritura constitutiva, poderes o reformas de estatutos (primer acta, poder del representante y última acta)","Selecciona Método de Compra y Tipo de Persona.")&CHAR(10)&CHAR(10)&Config!$B$1) | AD18: =IFERROR(INDEX(Facturación!$Q:$Q,MATCH(B18,Facturación!$A:$A,0)),"")
A19: =IF(B19="","",ROW()-1) | Q19: =IF(OR(B19="",L19<>"Sí"),"","Hola, "&B19&", excelente día. Le saluda *Alejandro Estrada* de Toyota Corregidora."&CHAR(10)&"Muchas gracias por visitarnos y conocer la *"&D19&"*. Fue un placer atenderle. Me pongo a sus órdenes por este medio para resolver cualquier duda que haya surgido o para agendarle una prueba de manejo."&CHAR(10)&"Quedo muy pendiente de lo que necesite para ayudarle a estrenar su próximo Toyota. ¡Saludos!"&CHAR(10)&CHAR(10)&Config!$B$1) | R19: =IF(Q19="","",HYPERLINK("https://wa.me/52"&C19&"?text="&_xlfn.ENCODEURL(Q19),"Enviar Bienvenida")) | S19: =IF(B19="","","Hola, "&B19&", muy buen día."&CHAR(10)&"Espero que esté teniendo una excelente semana. Le escribo para saber si tiene alguna duda sobre la oferta del *"&D19&"* que revisamos, con gusto le apoyo con información técnica o con las opciones de financiamiento disponibles."&CHAR(10)&"Quedo atento a sus comentarios para seguir avanzando hacia la entrega de su próximo Toyota. Gracias por su tiempo y confianza."&CHAR(10)&CHAR(10)&Config!$B$1) | T19: =IF(S19="","",HYPERLINK("https://wa.me/52"&C19&"?text="&_xlfn.ENCODEURL(S19),"Enviar Seguimiento")) | U19: =IF(B19="","",_xlfn.SWITCH(M19,"Apartado","Hola, "&B19&", buen día. Le confirmo que su apartado por el *"&D19&"* quedó registrado correctamente. Seguimos con el proceso y le mantendré informado(a) de cada paso.","Toma de vehículo","Hola, "&B19&", le comparto que estamos en el proceso de toma de su vehículo actual. En cuanto tengamos el resultado le aviso para continuar con el siguiente paso.","Pago vehículo a cuenta","Hola, "&B19&", quedamos en proceso de pago del vehículo que se toma a cuenta. Cualquier documento o aclaración que se requiera se lo haré saber por este medio.","Firma de contrato","Hola, "&B19&", ya estamos listos para agendar la firma de su contrato. ¿Qué día y hora se le facilita para realizarla?","Facturación","Hola, "&B19&", su unidad ya está en proceso de facturación. En breve le comparto los datos para su confirmación.","Programación de entrega","Hola, "&B19&", con gusto le comparto que ya podemos programar la entrega de su *"&D19&"*. ¿Qué día y hora le acomodan mejor?","Entregado","Hola, "&B19&", ¡muchas felicidades por estrenar su *"&D19&"*! Fue un gusto acompañarle en este proceso. Quedo pendiente de cualquier duda y con gusto le agendo su próxima cita de servicio cuando lo necesite.","Hola, "&B19&", seguimos en contacto para avanzar con el proceso de su próximo Toyota.")&CHAR(10)&CHAR(10)&Config!$B$1) | V19: =IF(U19="","",HYPERLINK("https://wa.me/52"&C19&"?text="&_xlfn.ENCODEURL(U19),"Enviar aviso de etapa")) | W19: =IF(OR(B19="",O19=""),"","Hola, "&B19&", ¡feliz cumpleaños! Le deseo un excelente día rodeado de quienes más quiere. Ha sido un placer acompañarle desde que estrenó su Toyota. ¡Un abrazo!"&CHAR(10)&CHAR(10)&Config!$B$1) | X19: =IF(W19="","",HYPERLINK("https://wa.me/52"&C19&"?text="&_xlfn.ENCODEURL(W19),"Enviar felicitación")) | Y19: =IF(OR(B19="",P19=""),"","Hola, "&B19&", hoy se cumple un año más desde que estrenó su *"&D19&"*. Espero que haya sido un gran compañero de camino. Cualquier cosa que necesite, aquí estoy para apoyarle."&CHAR(10)&CHAR(10)&Config!$B$1) | Z19: =IF(Y19="","",HYPERLINK("https://wa.me/52"&C19&"?text="&_xlfn.ENCODEURL(Y19),"Enviar aniversario")) | AB19: =IF(OR(B19="",AA19=""),"",HYPERLINK("https://wa.me/52"&C19&"?text="&_xlfn.ENCODEURL(_xlfn.SWITCH(AA19,"Bienvenida (primera visita)",Q19,"Seguimiento",S19,"Aviso de Etapa",U19,"Requisitos",AC19,"Datos de Facturación",AD19,"Cumpleaños",W19,"Aniversario",Y19,"")),"Enviar mensaje seleccionado")) | AC19: =IF(B19="","",_xlfn.SWITCH(F19&"|"&G19,"Crédito|Persona física","Hola, "&B19&", para continuar con el proceso de tu *"&D19&"* por "&F19&", estos son los documentos que necesitamos:"&CHAR(10)&CHAR(10)&"- INE"&CHAR(10)&"- Comprobante de domicilio (luz), a nombre del titular"&CHAR(10)&"- Estados de cuenta de los últimos 3 meses"&CHAR(10)&"- Constancia de situación fiscal (no mayor a 3 meses)","Crédito|Persona física con actividad empresarial","Hola, "&B19&", para continuar con el proceso de tu *"&D19&"* por "&F19&", estos son los documentos que necesitamos:"&CHAR(10)&CHAR(10)&"- INE"&CHAR(10)&"- Comprobante de domicilio (luz), a nombre del titular"&CHAR(10)&"- Estados de cuenta de los últimos 3 meses"&CHAR(10)&"- Constancia de situación fiscal (no mayor a 3 meses)"&CHAR(10)&"- Última declaración anual con acuse de recibo","Crédito|Persona moral","Hola, "&B19&", para continuar con el proceso de tu *"&D19&"* por "&F19&", estos son los documentos que necesitamos:"&CHAR(10)&CHAR(10)&"- Identificación oficial vigente del representante legal (INE o pasaporte)"&CHAR(10)&"- Comprobante de domicilio fiscal de la empresa (CFE, no mayor a 3 meses)"&CHAR(10)&"- Comprobante de domicilio del representante legal (CFE, no mayor a 3 meses)"&CHAR(10)&"- Últimos 3 meses de estados de cuenta bancarios de la empresa"&CHAR(10)&"- Constancia de situación fiscal de la empresa (no mayor a 3 meses)"&CHAR(10)&"- Constancia de situación fiscal del representante legal (no mayor a 3 meses)"&CHAR(10)&"- Declaración anual del último ejercicio, en digital, con acuse de recibo"&CHAR(10)&"- Estados financieros de la empresa (Resultados y Balance General), no mayor a 3 meses"&CHAR(10)&"- Escritura constitutiva, poderes o reformas de estatutos (primer acta, poder del representante y última acta)","Contado|Persona física","Hola, "&B19&", para continuar con el proceso de tu *"&D19&"* por "&F19&", estos son los documentos que necesitamos:"&CHAR(10)&CHAR(10)&"- INE"&CHAR(10)&"- Comprobante de domicilio"&CHAR(10)&"- Constancia de situación fiscal (no mayor a 3 meses)","Contado|Persona física con actividad empresarial","Hola, "&B19&", para continuar con el proceso de tu *"&D19&"* por "&F19&", estos son los documentos que necesitamos:"&CHAR(10)&CHAR(10)&"- INE"&CHAR(10)&"- Comprobante de domicilio"&CHAR(10)&"- Constancia de situación fiscal (no mayor a 3 meses)","Contado|Persona moral","Hola, "&B19&", para continuar con el proceso de tu *"&D19&"* por "&F19&", estos son los documentos que necesitamos:"&CHAR(10)&CHAR(10)&"- Identificación oficial vigente del representante legal y accionistas"&CHAR(10)&"- Comprobante de domicilio fiscal de la empresa (no mayor a 3 meses)"&CHAR(10)&"- Comprobante de domicilio del representante legal y accionistas (no mayor a 3 meses)"&CHAR(10)&"- Constancia de situación fiscal de la empresa (no mayor a 3 meses)"&CHAR(10)&"- Constancia de situación fiscal del representante legal y accionistas (no mayor a 3 meses)"&CHAR(10)&"- Escritura constitutiva, poderes o reformas de estatutos (primer acta, poder del representante y última acta)","Selecciona Método de Compra y Tipo de Persona.")&CHAR(10)&CHAR(10)&Config!$B$1) | AD19: =IFERROR(INDEX(Facturación!$Q:$Q,MATCH(B19,Facturación!$A:$A,0)),"")
A20: =IF(B20="","",ROW()-1) | Q20: =IF(OR(B20="",L20<>"Sí"),"","Hola, "&B20&", excelente día. Le saluda *Alejandro Estrada* de Toyota Corregidora."&CHAR(10)&"Muchas gracias por visitarnos y conocer la *"&D20&"*. Fue un placer atenderle. Me pongo a sus órdenes por este medio para resolver cualquier duda que haya surgido o para agendarle una prueba de manejo."&CHAR(10)&"Quedo muy pendiente de lo que necesite para ayudarle a estrenar su próximo Toyota. ¡Saludos!"&CHAR(10)&CHAR(10)&Config!$B$1) | R20: =IF(Q20="","",HYPERLINK("https://wa.me/52"&C20&"?text="&_xlfn.ENCODEURL(Q20),"Enviar Bienvenida")) | S20: =IF(B20="","","Hola, "&B20&", muy buen día."&CHAR(10)&"Espero que esté teniendo una excelente semana. Le escribo para saber si tiene alguna duda sobre la oferta del *"&D20&"* que revisamos, con gusto le apoyo con información técnica o con las opciones de financiamiento disponibles."&CHAR(10)&"Quedo atento a sus comentarios para seguir avanzando hacia la entrega de su próximo Toyota. Gracias por su tiempo y confianza."&CHAR(10)&CHAR(10)&Config!$B$1) | T20: =IF(S20="","",HYPERLINK("https://wa.me/52"&C20&"?text="&_xlfn.ENCODEURL(S20),"Enviar Seguimiento")) | U20: =IF(B20="","",_xlfn.SWITCH(M20,"Apartado","Hola, "&B20&", buen día. Le confirmo que su apartado por el *"&D20&"* quedó registrado correctamente. Seguimos con el proceso y le mantendré informado(a) de cada paso.","Toma de vehículo","Hola, "&B20&", le comparto que estamos en el proceso de toma de su vehículo actual. En cuanto tengamos el resultado le aviso para continuar con el siguiente paso.","Pago vehículo a cuenta","Hola, "&B20&", quedamos en proceso de pago del vehículo que se toma a cuenta. Cualquier documento o aclaración que se requiera se lo haré saber por este medio.","Firma de contrato","Hola, "&B20&", ya estamos listos para agendar la firma de su contrato. ¿Qué día y hora se le facilita para realizarla?","Facturación","Hola, "&B20&", su unidad ya está en proceso de facturación. En breve le comparto los datos para su confirmación.","Programación de entrega","Hola, "&B20&", con gusto le comparto que ya podemos programar la entrega de su *"&D20&"*. ¿Qué día y hora le acomodan mejor?","Entregado","Hola, "&B20&", ¡muchas felicidades por estrenar su *"&D20&"*! Fue un gusto acompañarle en este proceso. Quedo pendiente de cualquier duda y con gusto le agendo su próxima cita de servicio cuando lo necesite.","Hola, "&B20&", seguimos en contacto para avanzar con el proceso de su próximo Toyota.")&CHAR(10)&CHAR(10)&Config!$B$1) | V20: =IF(U20="","",HYPERLINK("https://wa.me/52"&C20&"?text="&_xlfn.ENCODEURL(U20),"Enviar aviso de etapa")) | W20: =IF(OR(B20="",O20=""),"","Hola, "&B20&", ¡feliz cumpleaños! Le deseo un excelente día rodeado de quienes más quiere. Ha sido un placer acompañarle desde que estrenó su Toyota. ¡Un abrazo!"&CHAR(10)&CHAR(10)&Config!$B$1) | X20: =IF(W20="","",HYPERLINK("https://wa.me/52"&C20&"?text="&_xlfn.ENCODEURL(W20),"Enviar felicitación")) | Y20: =IF(OR(B20="",P20=""),"","Hola, "&B20&", hoy se cumple un año más desde que estrenó su *"&D20&"*. Espero que haya sido un gran compañero de camino. Cualquier cosa que necesite, aquí estoy para apoyarle."&CHAR(10)&CHAR(10)&Config!$B$1) | Z20: =IF(Y20="","",HYPERLINK("https://wa.me/52"&C20&"?text="&_xlfn.ENCODEURL(Y20),"Enviar aniversario")) | AB20: =IF(OR(B20="",AA20=""),"",HYPERLINK("https://wa.me/52"&C20&"?text="&_xlfn.ENCODEURL(_xlfn.SWITCH(AA20,"Bienvenida (primera visita)",Q20,"Seguimiento",S20,"Aviso de Etapa",U20,"Requisitos",AC20,"Datos de Facturación",AD20,"Cumpleaños",W20,"Aniversario",Y20,"")),"Enviar mensaje seleccionado")) | AC20: =IF(B20="","",_xlfn.SWITCH(F20&"|"&G20,"Crédito|Persona física","Hola, "&B20&", para continuar con el proceso de tu *"&D20&"* por "&F20&", estos son los documentos que necesitamos:"&CHAR(10)&CHAR(10)&"- INE"&CHAR(10)&"- Comprobante de domicilio (luz), a nombre del titular"&CHAR(10)&"- Estados de cuenta de los últimos 3 meses"&CHAR(10)&"- Constancia de situación fiscal (no mayor a 3 meses)","Crédito|Persona física con actividad empresarial","Hola, "&B20&", para continuar con el proceso de tu *"&D20&"* por "&F20&", estos son los documentos que necesitamos:"&CHAR(10)&CHAR(10)&"- INE"&CHAR(10)&"- Comprobante de domicilio (luz), a nombre del titular"&CHAR(10)&"- Estados de cuenta de los últimos 3 meses"&CHAR(10)&"- Constancia de situación fiscal (no mayor a 3 meses)"&CHAR(10)&"- Última declaración anual con acuse de recibo","Crédito|Persona moral","Hola, "&B20&", para continuar con el proceso de tu *"&D20&"* por "&F20&", estos son los documentos que necesitamos:"&CHAR(10)&CHAR(10)&"- Identificación oficial vigente del representante legal (INE o pasaporte)"&CHAR(10)&"- Comprobante de domicilio fiscal de la empresa (CFE, no mayor a 3 meses)"&CHAR(10)&"- Comprobante de domicilio del representante legal (CFE, no mayor a 3 meses)"&CHAR(10)&"- Últimos 3 meses de estados de cuenta bancarios de la empresa"&CHAR(10)&"- Constancia de situación fiscal de la empresa (no mayor a 3 meses)"&CHAR(10)&"- Constancia de situación fiscal del representante legal (no mayor a 3 meses)"&CHAR(10)&"- Declaración anual del último ejercicio, en digital, con acuse de recibo"&CHAR(10)&"- Estados financieros de la empresa (Resultados y Balance General), no mayor a 3 meses"&CHAR(10)&"- Escritura constitutiva, poderes o reformas de estatutos (primer acta, poder del representante y última acta)","Contado|Persona física","Hola, "&B20&", para continuar con el proceso de tu *"&D20&"* por "&F20&", estos son los documentos que necesitamos:"&CHAR(10)&CHAR(10)&"- INE"&CHAR(10)&"- Comprobante de domicilio"&CHAR(10)&"- Constancia de situación fiscal (no mayor a 3 meses)","Contado|Persona física con actividad empresarial","Hola, "&B20&", para continuar con el proceso de tu *"&D20&"* por "&F20&", estos son los documentos que necesitamos:"&CHAR(10)&CHAR(10)&"- INE"&CHAR(10)&"- Comprobante de domicilio"&CHAR(10)&"- Constancia de situación fiscal (no mayor a 3 meses)","Contado|Persona moral","Hola, "&B20&", para continuar con el proceso de tu *"&D20&"* por "&F20&", estos son los documentos que necesitamos:"&CHAR(10)&CHAR(10)&"- Identificación oficial vigente del representante legal y accionistas"&CHAR(10)&"- Comprobante de domicilio fiscal de la empresa (no mayor a 3 meses)"&CHAR(10)&"- Comprobante de domicilio del representante legal y accionistas (no mayor a 3 meses)"&CHAR(10)&"- Constancia de situación fiscal de la empresa (no mayor a 3 meses)"&CHAR(10)&"- Constancia de situación fiscal del representante legal y accionistas (no mayor a 3 meses)"&CHAR(10)&"- Escritura constitutiva, poderes o reformas de estatutos (primer acta, poder del representante y última acta)","Selecciona Método de Compra y Tipo de Persona.")&CHAR(10)&CHAR(10)&Config!$B$1) | AD20: =IFERROR(INDEX(Facturación!$Q:$Q,MATCH(B20,Facturación!$A:$A,0)),"")
A21: =IF(B21="","",ROW()-1) | Q21: =IF(OR(B21="",L21<>"Sí"),"","Hola, "&B21&", excelente día. Le saluda *Alejandro Estrada* de Toyota Corregidora."&CHAR(10)&"Muchas gracias por visitarnos y conocer la *"&D21&"*. Fue un placer atenderle. Me pongo a sus órdenes por este medio para resolver cualquier duda que haya surgido o para agendarle una prueba de manejo."&CHAR(10)&"Quedo muy pendiente de lo que necesite para ayudarle a estrenar su próximo Toyota. ¡Saludos!"&CHAR(10)&CHAR(10)&Config!$B$1) | R21: =IF(Q21="","",HYPERLINK("https://wa.me/52"&C21&"?text="&_xlfn.ENCODEURL(Q21),"Enviar Bienvenida")) | S21: =IF(B21="","","Hola, "&B21&", muy buen día."&CHAR(10)&"Espero que esté teniendo una excelente semana. Le escribo para saber si tiene alguna duda sobre la oferta del *"&D21&"* que revisamos, con gusto le apoyo con información técnica o con las opciones de financiamiento disponibles."&CHAR(10)&"Quedo atento a sus comentarios para seguir avanzando hacia la entrega de su próximo Toyota. Gracias por su tiempo y confianza."&CHAR(10)&CHAR(10)&Config!$B$1) | T21: =IF(S21="","",HYPERLINK("https://wa.me/52"&C21&"?text="&_xlfn.ENCODEURL(S21),"Enviar Seguimiento")) | U21: =IF(B21="","",_xlfn.SWITCH(M21,"Apartado","Hola, "&B21&", buen día. Le confirmo que su apartado por el *"&D21&"* quedó registrado correctamente. Seguimos con el proceso y le mantendré informado(a) de cada paso.","Toma de vehículo","Hola, "&B21&", le comparto que estamos en el proceso de toma de su vehículo actual. En cuanto tengamos el resultado le aviso para continuar con el siguiente paso.","Pago vehículo a cuenta","Hola, "&B21&", quedamos en proceso de pago del vehículo que se toma a cuenta. Cualquier documento o aclaración que se requiera se lo haré saber por este medio.","Firma de contrato","Hola, "&B21&", ya estamos listos para agendar la firma de su contrato. ¿Qué día y hora se le facilita para realizarla?","Facturación","Hola, "&B21&", su unidad ya está en proceso de facturación. En breve le comparto los datos para su confirmación.","Programación de entrega","Hola, "&B21&", con gusto le comparto que ya podemos programar la entrega de su *"&D21&"*. ¿Qué día y hora le acomodan mejor?","Entregado","Hola, "&B21&", ¡muchas felicidades por estrenar su *"&D21&"*! Fue un gusto acompañarle en este proceso. Quedo pendiente de cualquier duda y con gusto le agendo su próxima cita de servicio cuando lo necesite.","Hola, "&B21&", seguimos en contacto para avanzar con el proceso de su próximo Toyota.")&CHAR(10)&CHAR(10)&Config!$B$1) | V21: =IF(U21="","",HYPERLINK("https://wa.me/52"&C21&"?text="&_xlfn.ENCODEURL(U21),"Enviar aviso de etapa")) | W21: =IF(OR(B21="",O21=""),"","Hola, "&B21&", ¡feliz cumpleaños! Le deseo un excelente día rodeado de quienes más quiere. Ha sido un placer acompañarle desde que estrenó su Toyota. ¡Un abrazo!"&CHAR(10)&CHAR(10)&Config!$B$1) | X21: =IF(W21="","",HYPERLINK("https://wa.me/52"&C21&"?text="&_xlfn.ENCODEURL(W21),"Enviar felicitación")) | Y21: =IF(OR(B21="",P21=""),"","Hola, "&B21&", hoy se cumple un año más desde que estrenó su *"&D21&"*. Espero que haya sido un gran compañero de camino. Cualquier cosa que necesite, aquí estoy para apoyarle."&CHAR(10)&CHAR(10)&Config!$B$1) | Z21: =IF(Y21="","",HYPERLINK("https://wa.me/52"&C21&"?text="&_xlfn.ENCODEURL(Y21),"Enviar aniversario")) | AB21: =IF(OR(B21="",AA21=""),"",HYPERLINK("https://wa.me/52"&C21&"?text="&_xlfn.ENCODEURL(_xlfn.SWITCH(AA21,"Bienvenida (primera visita)",Q21,"Seguimiento",S21,"Aviso de Etapa",U21,"Requisitos",AC21,"Datos de Facturación",AD21,"Cumpleaños",W21,"Aniversario",Y21,"")),"Enviar mensaje seleccionado")) | AC21: =IF(B21="","",_xlfn.SWITCH(F21&"|"&G21,"Crédito|Persona física","Hola, "&B21&", para continuar con el proceso de tu *"&D21&"* por "&F21&", estos son los documentos que necesitamos:"&CHAR(10)&CHAR(10)&"- INE"&CHAR(10)&"- Comprobante de domicilio (luz), a nombre del titular"&CHAR(10)&"- Estados de cuenta de los últimos 3 meses"&CHAR(10)&"- Constancia de situación fiscal (no mayor a 3 meses)","Crédito|Persona física con actividad empresarial","Hola, "&B21&", para continuar con el proceso de tu *"&D21&"* por "&F21&", estos son los documentos que necesitamos:"&CHAR(10)&CHAR(10)&"- INE"&CHAR(10)&"- Comprobante de domicilio (luz), a nombre del titular"&CHAR(10)&"- Estados de cuenta de los últimos 3 meses"&CHAR(10)&"- Constancia de situación fiscal (no mayor a 3 meses)"&CHAR(10)&"- Última declaración anual con acuse de recibo","Crédito|Persona moral","Hola, "&B21&", para continuar con el proceso de tu *"&D21&"* por "&F21&", estos son los documentos que necesitamos:"&CHAR(10)&CHAR(10)&"- Identificación oficial vigente del representante legal (INE o pasaporte)"&CHAR(10)&"- Comprobante de domicilio fiscal de la empresa (CFE, no mayor a 3 meses)"&CHAR(10)&"- Comprobante de domicilio del representante legal (CFE, no mayor a 3 meses)"&CHAR(10)&"- Últimos 3 meses de estados de cuenta bancarios de la empresa"&CHAR(10)&"- Constancia de situación fiscal de la empresa (no mayor a 3 meses)"&CHAR(10)&"- Constancia de situación fiscal del representante legal (no mayor a 3 meses)"&CHAR(10)&"- Declaración anual del último ejercicio, en digital, con acuse de recibo"&CHAR(10)&"- Estados financieros de la empresa (Resultados y Balance General), no mayor a 3 meses"&CHAR(10)&"- Escritura constitutiva, poderes o reformas de estatutos (primer acta, poder del representante y última acta)","Contado|Persona física","Hola, "&B21&", para continuar con el proceso de tu *"&D21&"* por "&F21&", estos son los documentos que necesitamos:"&CHAR(10)&CHAR(10)&"- INE"&CHAR(10)&"- Comprobante de domicilio"&CHAR(10)&"- Constancia de situación fiscal (no mayor a 3 meses)","Contado|Persona física con actividad empresarial","Hola, "&B21&", para continuar con el proceso de tu *"&D21&"* por "&F21&", estos son los documentos que necesitamos:"&CHAR(10)&CHAR(10)&"- INE"&CHAR(10)&"- Comprobante de domicilio"&CHAR(10)&"- Constancia de situación fiscal (no mayor a 3 meses)","Contado|Persona moral","Hola, "&B21&", para continuar con el proceso de tu *"&D21&"* por "&F21&", estos son los documentos que necesitamos:"&CHAR(10)&CHAR(10)&"- Identificación oficial vigente del representante legal y accionistas"&CHAR(10)&"- Comprobante de domicilio fiscal de la empresa (no mayor a 3 meses)"&CHAR(10)&"- Comprobante de domicilio del representante legal y accionistas (no mayor a 3 meses)"&CHAR(10)&"- Constancia de situación fiscal de la empresa (no mayor a 3 meses)"&CHAR(10)&"- Constancia de situación fiscal del representante legal y accionistas (no mayor a 3 meses)"&CHAR(10)&"- Escritura constitutiva, poderes o reformas de estatutos (primer acta, poder del representante y última acta)","Selecciona Método de Compra y Tipo de Persona.")&CHAR(10)&CHAR(10)&Config!$B$1) | AD21: =IFERROR(INDEX(Facturación!$Q:$Q,MATCH(B21,Facturación!$A:$A,0)),"")
A22: =IF(B22="","",ROW()-1) | Q22: =IF(OR(B22="",L22<>"Sí"),"","Hola, "&B22&", excelente día. Le saluda *Alejandro Estrada* de Toyota Corregidora."&CHAR(10)&"Muchas gracias por visitarnos y conocer la *"&D22&"*. Fue un placer atenderle. Me pongo a sus órdenes por este medio para resolver cualquier duda que haya surgido o para agendarle una prueba de manejo."&CHAR(10)&"Quedo muy pendiente de lo que necesite para ayudarle a estrenar su próximo Toyota. ¡Saludos!"&CHAR(10)&CHAR(10)&Config!$B$1) | R22: =IF(Q22="","",HYPERLINK("https://wa.me/52"&C22&"?text="&_xlfn.ENCODEURL(Q22),"Enviar Bienvenida")) | S22: =IF(B22="","","Hola, "&B22&", muy buen día."&CHAR(10)&"Espero que esté teniendo una excelente semana. Le escribo para saber si tiene alguna duda sobre la oferta del *"&D22&"* que revisamos, con gusto le apoyo con información técnica o con las opciones de financiamiento disponibles."&CHAR(10)&"Quedo atento a sus comentarios para seguir avanzando hacia la entrega de su próximo Toyota. Gracias por su tiempo y confianza."&CHAR(10)&CHAR(10)&Config!$B$1) | T22: =IF(S22="","",HYPERLINK("https://wa.me/52"&C22&"?text="&_xlfn.ENCODEURL(S22),"Enviar Seguimiento")) | U22: =IF(B22="","",_xlfn.SWITCH(M22,"Apartado","Hola, "&B22&", buen día. Le confirmo que su apartado por el *"&D22&"* quedó registrado correctamente. Seguimos con el proceso y le mantendré informado(a) de cada paso.","Toma de vehículo","Hola, "&B22&", le comparto que estamos en el proceso de toma de su vehículo actual. En cuanto tengamos el resultado le aviso para continuar con el siguiente paso.","Pago vehículo a cuenta","Hola, "&B22&", quedamos en proceso de pago del vehículo que se toma a cuenta. Cualquier documento o aclaración que se requiera se lo haré saber por este medio.","Firma de contrato","Hola, "&B22&", ya estamos listos para agendar la firma de su contrato. ¿Qué día y hora se le facilita para realizarla?","Facturación","Hola, "&B22&", su unidad ya está en proceso de facturación. En breve le comparto los datos para su confirmación.","Programación de entrega","Hola, "&B22&", con gusto le comparto que ya podemos programar la entrega de su *"&D22&"*. ¿Qué día y hora le acomodan mejor?","Entregado","Hola, "&B22&", ¡muchas felicidades por estrenar su *"&D22&"*! Fue un gusto acompañarle en este proceso. Quedo pendiente de cualquier duda y con gusto le agendo su próxima cita de servicio cuando lo necesite.","Hola, "&B22&", seguimos en contacto para avanzar con el proceso de su próximo Toyota.")&CHAR(10)&CHAR(10)&Config!$B$1) | V22: =IF(U22="","",HYPERLINK("https://wa.me/52"&C22&"?text="&_xlfn.ENCODEURL(U22),"Enviar aviso de etapa")) | W22: =IF(OR(B22="",O22=""),"","Hola, "&B22&", ¡feliz cumpleaños! Le deseo un excelente día rodeado de quienes más quiere. Ha sido un placer acompañarle desde que estrenó su Toyota. ¡Un abrazo!"&CHAR(10)&CHAR(10)&Config!$B$1) | X22: =IF(W22="","",HYPERLINK("https://wa.me/52"&C22&"?text="&_xlfn.ENCODEURL(W22),"Enviar felicitación")) | Y22: =IF(OR(B22="",P22=""),"","Hola, "&B22&", hoy se cumple un año más desde que estrenó su *"&D22&"*. Espero que haya sido un gran compañero de camino. Cualquier cosa que necesite, aquí estoy para apoyarle."&CHAR(10)&CHAR(10)&Config!$B$1) | Z22: =IF(Y22="","",HYPERLINK("https://wa.me/52"&C22&"?text="&_xlfn.ENCODEURL(Y22),"Enviar aniversario")) | AB22: =IF(OR(B22="",AA22=""),"",HYPERLINK("https://wa.me/52"&C22&"?text="&_xlfn.ENCODEURL(_xlfn.SWITCH(AA22,"Bienvenida (primera visita)",Q22,"Seguimiento",S22,"Aviso de Etapa",U22,"Requisitos",AC22,"Datos de Facturación",AD22,"Cumpleaños",W22,"Aniversario",Y22,"")),"Enviar mensaje seleccionado")) | AC22: =IF(B22="","",_xlfn.SWITCH(F22&"|"&G22,"Crédito|Persona física","Hola, "&B22&", para continuar con el proceso de tu *"&D22&"* por "&F22&", estos son los documentos que necesitamos:"&CHAR(10)&CHAR(10)&"- INE"&CHAR(10)&"- Comprobante de domicilio (luz), a nombre del titular"&CHAR(10)&"- Estados de cuenta de los últimos 3 meses"&CHAR(10)&"- Constancia de situación fiscal (no mayor a 3 meses)","Crédito|Persona física con actividad empresarial","Hola, "&B22&", para continuar con el proceso de tu *"&D22&"* por "&F22&", estos son los documentos que necesitamos:"&CHAR(10)&CHAR(10)&"- INE"&CHAR(10)&"- Comprobante de domicilio (luz), a nombre del titular"&CHAR(10)&"- Estados de cuenta de los últimos 3 meses"&CHAR(10)&"- Constancia de situación fiscal (no mayor a 3 meses)"&CHAR(10)&"- Última declaración anual con acuse de recibo","Crédito|Persona moral","Hola, "&B22&", para continuar con el proceso de tu *"&D22&"* por "&F22&", estos son los documentos que necesitamos:"&CHAR(10)&CHAR(10)&"- Identificación oficial vigente del representante legal (INE o pasaporte)"&CHAR(10)&"- Comprobante de domicilio fiscal de la empresa (CFE, no mayor a 3 meses)"&CHAR(10)&"- Comprobante de domicilio del representante legal (CFE, no mayor a 3 meses)"&CHAR(10)&"- Últimos 3 meses de estados de cuenta bancarios de la empresa"&CHAR(10)&"- Constancia de situación fiscal de la empresa (no mayor a 3 meses)"&CHAR(10)&"- Constancia de situación fiscal del representante legal (no mayor a 3 meses)"&CHAR(10)&"- Declaración anual del último ejercicio, en digital, con acuse de recibo"&CHAR(10)&"- Estados financieros de la empresa (Resultados y Balance General), no mayor a 3 meses"&CHAR(10)&"- Escritura constitutiva, poderes o reformas de estatutos (primer acta, poder del representante y última acta)","Contado|Persona física","Hola, "&B22&", para continuar con el proceso de tu *"&D22&"* por "&F22&", estos son los documentos que necesitamos:"&CHAR(10)&CHAR(10)&"- INE"&CHAR(10)&"- Comprobante de domicilio"&CHAR(10)&"- Constancia de situación fiscal (no mayor a 3 meses)","Contado|Persona física con actividad empresarial","Hola, "&B22&", para continuar con el proceso de tu *"&D22&"* por "&F22&", estos son los documentos que necesitamos:"&CHAR(10)&CHAR(10)&"- INE"&CHAR(10)&"- Comprobante de domicilio"&CHAR(10)&"- Constancia de situación fiscal (no mayor a 3 meses)","Contado|Persona moral","Hola, "&B22&", para continuar con el proceso de tu *"&D22&"* por "&F22&", estos son los documentos que necesitamos:"&CHAR(10)&CHAR(10)&"- Identificación oficial vigente del representante legal y accionistas"&CHAR(10)&"- Comprobante de domicilio fiscal de la empresa (no mayor a 3 meses)"&CHAR(10)&"- Comprobante de domicilio del representante legal y accionistas (no mayor a 3 meses)"&CHAR(10)&"- Constancia de situación fiscal de la empresa (no mayor a 3 meses)"&CHAR(10)&"- Constancia de situación fiscal del representante legal y accionistas (no mayor a 3 meses)"&CHAR(10)&"- Escritura constitutiva, poderes o reformas de estatutos (primer acta, poder del representante y última acta)","Selecciona Método de Compra y Tipo de Persona.")&CHAR(10)&CHAR(10)&Config!$B$1) | AD22: =IFERROR(INDEX(Facturación!$Q:$Q,MATCH(B22,Facturación!$A:$A,0)),"")
A23: =IF(B23="","",ROW()-1) | Q23: =IF(OR(B23="",L23<>"Sí"),"","Hola, "&B23&", excelente día. Le saluda *Alejandro Estrada* de Toyota Corregidora."&CHAR(10)&"Muchas gracias por visitarnos y conocer la *"&D23&"*. Fue un placer atenderle. Me pongo a sus órdenes por este medio para resolver cualquier duda que haya surgido o para agendarle una prueba de manejo."&CHAR(10)&"Quedo muy pendiente de lo que necesite para ayudarle a estrenar su próximo Toyota. ¡Saludos!"&CHAR(10)&CHAR(10)&Config!$B$1) | R23: =IF(Q23="","",HYPERLINK("https://wa.me/52"&C23&"?text="&_xlfn.ENCODEURL(Q23),"Enviar Bienvenida")) | S23: =IF(B23="","","Hola, "&B23&", muy buen día."&CHAR(10)&"Espero que esté teniendo una excelente semana. Le escribo para saber si tiene alguna duda sobre la oferta del *"&D23&"* que revisamos, con gusto le apoyo con información técnica o con las opciones de financiamiento disponibles."&CHAR(10)&"Quedo atento a sus comentarios para seguir avanzando hacia la entrega de su próximo Toyota. Gracias por su tiempo y confianza."&CHAR(10)&CHAR(10)&Config!$B$1) | T23: =IF(S23="","",HYPERLINK("https://wa.me/52"&C23&"?text="&_xlfn.ENCODEURL(S23),"Enviar Seguimiento")) | U23: =IF(B23="","",_xlfn.SWITCH(M23,"Apartado","Hola, "&B23&", buen día. Le confirmo que su apartado por el *"&D23&"* quedó registrado correctamente. Seguimos con el proceso y le mantendré informado(a) de cada paso.","Toma de vehículo","Hola, "&B23&", le comparto que estamos en el proceso de toma de su vehículo actual. En cuanto tengamos el resultado le aviso para continuar con el siguiente paso.","Pago vehículo a cuenta","Hola, "&B23&", quedamos en proceso de pago del vehículo que se toma a cuenta. Cualquier documento o aclaración que se requiera se lo haré saber por este medio.","Firma de contrato","Hola, "&B23&", ya estamos listos para agendar la firma de su contrato. ¿Qué día y hora se le facilita para realizarla?","Facturación","Hola, "&B23&", su unidad ya está en proceso de facturación. En breve le comparto los datos para su confirmación.","Programación de entrega","Hola, "&B23&", con gusto le comparto que ya podemos programar la entrega de su *"&D23&"*. ¿Qué día y hora le acomodan mejor?","Entregado","Hola, "&B23&", ¡muchas felicidades por estrenar su *"&D23&"*! Fue un gusto acompañarle en este proceso. Quedo pendiente de cualquier duda y con gusto le agendo su próxima cita de servicio cuando lo necesite.","Hola, "&B23&", seguimos en contacto para avanzar con el proceso de su próximo Toyota.")&CHAR(10)&CHAR(10)&Config!$B$1) | V23: =IF(U23="","",HYPERLINK("https://wa.me/52"&C23&"?text="&_xlfn.ENCODEURL(U23),"Enviar aviso de etapa")) | W23: =IF(OR(B23="",O23=""),"","Hola, "&B23&", ¡feliz cumpleaños! Le deseo un excelente día rodeado de quienes más quiere. Ha sido un placer acompañarle desde que estrenó su Toyota. ¡Un abrazo!"&CHAR(10)&CHAR(10)&Config!$B$1) | X23: =IF(W23="","",HYPERLINK("https://wa.me/52"&C23&"?text="&_xlfn.ENCODEURL(W23),"Enviar felicitación")) | Y23: =IF(OR(B23="",P23=""),"","Hola, "&B23&", hoy se cumple un año más desde que estrenó su *"&D23&"*. Espero que haya sido un gran compañero de camino. Cualquier cosa que necesite, aquí estoy para apoyarle."&CHAR(10)&CHAR(10)&Config!$B$1) | Z23: =IF(Y23="","",HYPERLINK("https://wa.me/52"&C23&"?text="&_xlfn.ENCODEURL(Y23),"Enviar aniversario")) | AB23: =IF(OR(B23="",AA23=""),"",HYPERLINK("https://wa.me/52"&C23&"?text="&_xlfn.ENCODEURL(_xlfn.SWITCH(AA23,"Bienvenida (primera visita)",Q23,"Seguimiento",S23,"Aviso de Etapa",U23,"Requisitos",AC23,"Datos de Facturación",AD23,"Cumpleaños",W23,"Aniversario",Y23,"")),"Enviar mensaje seleccionado")) | AC23: =IF(B23="","",_xlfn.SWITCH(F23&"|"&G23,"Crédito|Persona física","Hola, "&B23&", para continuar con el proceso de tu *"&D23&"* por "&F23&", estos son los documentos que necesitamos:"&CHAR(10)&CHAR(10)&"- INE"&CHAR(10)&"- Comprobante de domicilio (luz), a nombre del titular"&CHAR(10)&"- Estados de cuenta de los últimos 3 meses"&CHAR(10)&"- Constancia de situación fiscal (no mayor a 3 meses)","Crédito|Persona física con actividad empresarial","Hola, "&B23&", para continuar con el proceso de tu *"&D23&"* por "&F23&", estos son los documentos que necesitamos:"&CHAR(10)&CHAR(10)&"- INE"&CHAR(10)&"- Comprobante de domicilio (luz), a nombre del titular"&CHAR(10)&"- Estados de cuenta de los últimos 3 meses"&CHAR(10)&"- Constancia de situación fiscal (no mayor a 3 meses)"&CHAR(10)&"- Última declaración anual con acuse de recibo","Crédito|Persona moral","Hola, "&B23&", para continuar con el proceso de tu *"&D23&"* por "&F23&", estos son los documentos que necesitamos:"&CHAR(10)&CHAR(10)&"- Identificación oficial vigente del representante legal (INE o pasaporte)"&CHAR(10)&"- Comprobante de domicilio fiscal de la empresa (CFE, no mayor a 3 meses)"&CHAR(10)&"- Comprobante de domicilio del representante legal (CFE, no mayor a 3 meses)"&CHAR(10)&"- Últimos 3 meses de estados de cuenta bancarios de la empresa"&CHAR(10)&"- Constancia de situación fiscal de la empresa (no mayor a 3 meses)"&CHAR(10)&"- Constancia de situación fiscal del representante legal (no mayor a 3 meses)"&CHAR(10)&"- Declaración anual del último ejercicio, en digital, con acuse de recibo"&CHAR(10)&"- Estados financieros de la empresa (Resultados y Balance General), no mayor a 3 meses"&CHAR(10)&"- Escritura constitutiva, poderes o reformas de estatutos (primer acta, poder del representante y última acta)","Contado|Persona física","Hola, "&B23&", para continuar con el proceso de tu *"&D23&"* por "&F23&", estos son los documentos que necesitamos:"&CHAR(10)&CHAR(10)&"- INE"&CHAR(10)&"- Comprobante de domicilio"&CHAR(10)&"- Constancia de situación fiscal (no mayor a 3 meses)","Contado|Persona física con actividad empresarial","Hola, "&B23&", para continuar con el proceso de tu *"&D23&"* por "&F23&", estos son los documentos que necesitamos:"&CHAR(10)&CHAR(10)&"- INE"&CHAR(10)&"- Comprobante de domicilio"&CHAR(10)&"- Constancia de situación fiscal (no mayor a 3 meses)","Contado|Persona moral","Hola, "&B23&", para continuar con el proceso de tu *"&D23&"* por "&F23&", estos son los documentos que necesitamos:"&CHAR(10)&CHAR(10)&"- Identificación oficial vigente del representante legal y accionistas"&CHAR(10)&"- Comprobante de domicilio fiscal de la empresa (no mayor a 3 meses)"&CHAR(10)&"- Comprobante de domicilio del representante legal y accionistas (no mayor a 3 meses)"&CHAR(10)&"- Constancia de situación fiscal de la empresa (no mayor a 3 meses)"&CHAR(10)&"- Constancia de situación fiscal del representante legal y accionistas (no mayor a 3 meses)"&CHAR(10)&"- Escritura constitutiva, poderes o reformas de estatutos (primer acta, poder del representante y última acta)","Selecciona Método de Compra y Tipo de Persona.")&CHAR(10)&CHAR(10)&Config!$B$1) | AD23: =IFERROR(INDEX(Facturación!$Q:$Q,MATCH(B23,Facturación!$A:$A,0)),"")
A24: =IF(B24="","",ROW()-1) | Q24: =IF(OR(B24="",L24<>"Sí"),"","Hola, "&B24&", excelente día. Le saluda *Alejandro Estrada* de Toyota Corregidora."&CHAR(10)&"Muchas gracias por visitarnos y conocer la *"&D24&"*. Fue un placer atenderle. Me pongo a sus órdenes por este medio para resolver cualquier duda que haya surgido o para agendarle una prueba de manejo."&CHAR(10)&"Quedo muy pendiente de lo que necesite para ayudarle a estrenar su próximo Toyota. ¡Saludos!"&CHAR(10)&CHAR(10)&Config!$B$1) | R24: =IF(Q24="","",HYPERLINK("https://wa.me/52"&C24&"?text="&_xlfn.ENCODEURL(Q24),"Enviar Bienvenida")) | S24: =IF(B24="","","Hola, "&B24&", muy buen día."&CHAR(10)&"Espero que esté teniendo una excelente semana. Le escribo para saber si tiene alguna duda sobre la oferta del *"&D24&"* que revisamos, con gusto le apoyo con información técnica o con las opciones de financiamiento disponibles."&CHAR(10)&"Quedo atento a sus comentarios para seguir avanzando hacia la entrega de su próximo Toyota. Gracias por su tiempo y confianza."&CHAR(10)&CHAR(10)&Config!$B$1) | T24: =IF(S24="","",HYPERLINK("https://wa.me/52"&C24&"?text="&_xlfn.ENCODEURL(S24),"Enviar Seguimiento")) | U24: =IF(B24="","",_xlfn.SWITCH(M24,"Apartado","Hola, "&B24&", buen día. Le confirmo que su apartado por el *"&D24&"* quedó registrado correctamente. Seguimos con el proceso y le mantendré informado(a) de cada paso.","Toma de vehículo","Hola, "&B24&", le comparto que estamos en el proceso de toma de su vehículo actual. En cuanto tengamos el resultado le aviso para continuar con el siguiente paso.","Pago vehículo a cuenta","Hola, "&B24&", quedamos en proceso de pago del vehículo que se toma a cuenta. Cualquier documento o aclaración que se requiera se lo haré saber por este medio.","Firma de contrato","Hola, "&B24&", ya estamos listos para agendar la firma de su contrato. ¿Qué día y hora se le facilita para realizarla?","Facturación","Hola, "&B24&", su unidad ya está en proceso de facturación. En breve le comparto los datos para su confirmación.","Programación de entrega","Hola, "&B24&", con gusto le comparto que ya podemos programar la entrega de su *"&D24&"*. ¿Qué día y hora le acomodan mejor?","Entregado","Hola, "&B24&", ¡muchas felicidades por estrenar su *"&D24&"*! Fue un gusto acompañarle en este proceso. Quedo pendiente de cualquier duda y con gusto le agendo su próxima cita de servicio cuando lo necesite.","Hola, "&B24&", seguimos en contacto para avanzar con el proceso de su próximo Toyota.")&CHAR(10)&CHAR(10)&Config!$B$1) | V24: =IF(U24="","",HYPERLINK("https://wa.me/52"&C24&"?text="&_xlfn.ENCODEURL(U24),"Enviar aviso de etapa")) | W24: =IF(OR(B24="",O24=""),"","Hola, "&B24&", ¡feliz cumpleaños! Le deseo un excelente día rodeado de quienes más quiere. Ha sido un placer acompañarle desde que estrenó su Toyota. ¡Un abrazo!"&CHAR(10)&CHAR(10)&Config!$B$1) | X24: =IF(W24="","",HYPERLINK("https://wa.me/52"&C24&"?text="&_xlfn.ENCODEURL(W24),"Enviar felicitación")) | Y24: =IF(OR(B24="",P24=""),"","Hola, "&B24&", hoy se cumple un año más desde que estrenó su *"&D24&"*. Espero que haya sido un gran compañero de camino. Cualquier cosa que necesite, aquí estoy para apoyarle."&CHAR(10)&CHAR(10)&Config!$B$1) | Z24: =IF(Y24="","",HYPERLINK("https://wa.me/52"&C24&"?text="&_xlfn.ENCODEURL(Y24),"Enviar aniversario")) | AB24: =IF(OR(B24="",AA24=""),"",HYPERLINK("https://wa.me/52"&C24&"?text="&_xlfn.ENCODEURL(_xlfn.SWITCH(AA24,"Bienvenida (primera visita)",Q24,"Seguimiento",S24,"Aviso de Etapa",U24,"Requisitos",AC24,"Datos de Facturación",AD24,"Cumpleaños",W24,"Aniversario",Y24,"")),"Enviar mensaje seleccionado")) | AC24: =IF(B24="","",_xlfn.SWITCH(F24&"|"&G24,"Crédito|Persona física","Hola, "&B24&", para continuar con el proceso de tu *"&D24&"* por "&F24&", estos son los documentos que necesitamos:"&CHAR(10)&CHAR(10)&"- INE"&CHAR(10)&"- Comprobante de domicilio (luz), a nombre del titular"&CHAR(10)&"- Estados de cuenta de los últimos 3 meses"&CHAR(10)&"- Constancia de situación fiscal (no mayor a 3 meses)","Crédito|Persona física con actividad empresarial","Hola, "&B24&", para continuar con el proceso de tu *"&D24&"* por "&F24&", estos son los documentos que necesitamos:"&CHAR(10)&CHAR(10)&"- INE"&CHAR(10)&"- Comprobante de domicilio (luz), a nombre del titular"&CHAR(10)&"- Estados de cuenta de los últimos 3 meses"&CHAR(10)&"- Constancia de situación fiscal (no mayor a 3 meses)"&CHAR(10)&"- Última declaración anual con acuse de recibo","Crédito|Persona moral","Hola, "&B24&", para continuar con el proceso de tu *"&D24&"* por "&F24&", estos son los documentos que necesitamos:"&CHAR(10)&CHAR(10)&"- Identificación oficial vigente del representante legal (INE o pasaporte)"&CHAR(10)&"- Comprobante de domicilio fiscal de la empresa (CFE, no mayor a 3 meses)"&CHAR(10)&"- Comprobante de domicilio del representante legal (CFE, no mayor a 3 meses)"&CHAR(10)&"- Últimos 3 meses de estados de cuenta bancarios de la empresa"&CHAR(10)&"- Constancia de situación fiscal de la empresa (no mayor a 3 meses)"&CHAR(10)&"- Constancia de situación fiscal del representante legal (no mayor a 3 meses)"&CHAR(10)&"- Declaración anual del último ejercicio, en digital, con acuse de recibo"&CHAR(10)&"- Estados financieros de la empresa (Resultados y Balance General), no mayor a 3 meses"&CHAR(10)&"- Escritura constitutiva, poderes o reformas de estatutos (primer acta, poder del representante y última acta)","Contado|Persona física","Hola, "&B24&", para continuar con el proceso de tu *"&D24&"* por "&F24&", estos son los documentos que necesitamos:"&CHAR(10)&CHAR(10)&"- INE"&CHAR(10)&"- Comprobante de domicilio"&CHAR(10)&"- Constancia de situación fiscal (no mayor a 3 meses)","Contado|Persona física con actividad empresarial","Hola, "&B24&", para continuar con el proceso de tu *"&D24&"* por "&F24&", estos son los documentos que necesitamos:"&CHAR(10)&CHAR(10)&"- INE"&CHAR(10)&"- Comprobante de domicilio"&CHAR(10)&"- Constancia de situación fiscal (no mayor a 3 meses)","Contado|Persona moral","Hola, "&B24&", para continuar con el proceso de tu *"&D24&"* por "&F24&", estos son los documentos que necesitamos:"&CHAR(10)&CHAR(10)&"- Identificación oficial vigente del representante legal y accionistas"&CHAR(10)&"- Comprobante de domicilio fiscal de la empresa (no mayor a 3 meses)"&CHAR(10)&"- Comprobante de domicilio del representante legal y accionistas (no mayor a 3 meses)"&CHAR(10)&"- Constancia de situación fiscal de la empresa (no mayor a 3 meses)"&CHAR(10)&"- Constancia de situación fiscal del representante legal y accionistas (no mayor a 3 meses)"&CHAR(10)&"- Escritura constitutiva, poderes o reformas de estatutos (primer acta, poder del representante y última acta)","Selecciona Método de Compra y Tipo de Persona.")&CHAR(10)&CHAR(10)&Config!$B$1) | AD24: =IFERROR(INDEX(Facturación!$Q:$Q,MATCH(B24,Facturación!$A:$A,0)),"")
A25: =IF(B25="","",ROW()-1) | Q25: =IF(OR(B25="",L25<>"Sí"),"","Hola, "&B25&", excelente día. Le saluda *Alejandro Estrada* de Toyota Corregidora."&CHAR(10)&"Muchas gracias por visitarnos y conocer la *"&D25&"*. Fue un placer atenderle. Me pongo a sus órdenes por este medio para resolver cualquier duda que haya surgido o para agendarle una prueba de manejo."&CHAR(10)&"Quedo muy pendiente de lo que necesite para ayudarle a estrenar su próximo Toyota. ¡Saludos!"&CHAR(10)&CHAR(10)&Config!$B$1) | R25: =IF(Q25="","",HYPERLINK("https://wa.me/52"&C25&"?text="&_xlfn.ENCODEURL(Q25),"Enviar Bienvenida")) | S25: =IF(B25="","","Hola, "&B25&", muy buen día."&CHAR(10)&"Espero que esté teniendo una excelente semana. Le escribo para saber si tiene alguna duda sobre la oferta del *"&D25&"* que revisamos, con gusto le apoyo con información técnica o con las opciones de financiamiento disponibles."&CHAR(10)&"Quedo atento a sus comentarios para seguir avanzando hacia la entrega de su próximo Toyota. Gracias por su tiempo y confianza."&CHAR(10)&CHAR(10)&Config!$B$1) | T25: =IF(S25="","",HYPERLINK("https://wa.me/52"&C25&"?text="&_xlfn.ENCODEURL(S25),"Enviar Seguimiento")) | U25: =IF(B25="","",_xlfn.SWITCH(M25,"Apartado","Hola, "&B25&", buen día. Le confirmo que su apartado por el *"&D25&"* quedó registrado correctamente. Seguimos con el proceso y le mantendré informado(a) de cada paso.","Toma de vehículo","Hola, "&B25&", le comparto que estamos en el proceso de toma de su vehículo actual. En cuanto tengamos el resultado le aviso para continuar con el siguiente paso.","Pago vehículo a cuenta","Hola, "&B25&", quedamos en proceso de pago del vehículo que se toma a cuenta. Cualquier documento o aclaración que se requiera se lo haré saber por este medio.","Firma de contrato","Hola, "&B25&", ya estamos listos para agendar la firma de su contrato. ¿Qué día y hora se le facilita para realizarla?","Facturación","Hola, "&B25&", su unidad ya está en proceso de facturación. En breve le comparto los datos para su confirmación.","Programación de entrega","Hola, "&B25&", con gusto le comparto que ya podemos programar la entrega de su *"&D25&"*. ¿Qué día y hora le acomodan mejor?","Entregado","Hola, "&B25&", ¡muchas felicidades por estrenar su *"&D25&"*! Fue un gusto acompañarle en este proceso. Quedo pendiente de cualquier duda y con gusto le agendo su próxima cita de servicio cuando lo necesite.","Hola, "&B25&", seguimos en contacto para avanzar con el proceso de su próximo Toyota.")&CHAR(10)&CHAR(10)&Config!$B$1) | V25: =IF(U25="","",HYPERLINK("https://wa.me/52"&C25&"?text="&_xlfn.ENCODEURL(U25),"Enviar aviso de etapa")) | W25: =IF(OR(B25="",O25=""),"","Hola, "&B25&", ¡feliz cumpleaños! Le deseo un excelente día rodeado de quienes más quiere. Ha sido un placer acompañarle desde que estrenó su Toyota. ¡Un abrazo!"&CHAR(10)&CHAR(10)&Config!$B$1) | X25: =IF(W25="","",HYPERLINK("https://wa.me/52"&C25&"?text="&_xlfn.ENCODEURL(W25),"Enviar felicitación")) | Y25: =IF(OR(B25="",P25=""),"","Hola, "&B25&", hoy se cumple un año más desde que estrenó su *"&D25&"*. Espero que haya sido un gran compañero de camino. Cualquier cosa que necesite, aquí estoy para apoyarle."&CHAR(10)&CHAR(10)&Config!$B$1) | Z25: =IF(Y25="","",HYPERLINK("https://wa.me/52"&C25&"?text="&_xlfn.ENCODEURL(Y25),"Enviar aniversario")) | AB25: =IF(OR(B25="",AA25=""),"",HYPERLINK("https://wa.me/52"&C25&"?text="&_xlfn.ENCODEURL(_xlfn.SWITCH(AA25,"Bienvenida (primera visita)",Q25,"Seguimiento",S25,"Aviso de Etapa",U25,"Requisitos",AC25,"Datos de Facturación",AD25,"Cumpleaños",W25,"Aniversario",Y25,"")),"Enviar mensaje seleccionado")) | AC25: =IF(B25="","",_xlfn.SWITCH(F25&"|"&G25,"Crédito|Persona física","Hola, "&B25&", para continuar con el proceso de tu *"&D25&"* por "&F25&", estos son los documentos que necesitamos:"&CHAR(10)&CHAR(10)&"- INE"&CHAR(10)&"- Comprobante de domicilio (luz), a nombre del titular"&CHAR(10)&"- Estados de cuenta de los últimos 3 meses"&CHAR(10)&"- Constancia de situación fiscal (no mayor a 3 meses)","Crédito|Persona física con actividad empresarial","Hola, "&B25&", para continuar con el proceso de tu *"&D25&"* por "&F25&", estos son los documentos que necesitamos:"&CHAR(10)&CHAR(10)&"- INE"&CHAR(10)&"- Comprobante de domicilio (luz), a nombre del titular"&CHAR(10)&"- Estados de cuenta de los últimos 3 meses"&CHAR(10)&"- Constancia de situación fiscal (no mayor a 3 meses)"&CHAR(10)&"- Última declaración anual con acuse de recibo","Crédito|Persona moral","Hola, "&B25&", para continuar con el proceso de tu *"&D25&"* por "&F25&", estos son los documentos que necesitamos:"&CHAR(10)&CHAR(10)&"- Identificación oficial vigente del representante legal (INE o pasaporte)"&CHAR(10)&"- Comprobante de domicilio fiscal de la empresa (CFE, no mayor a 3 meses)"&CHAR(10)&"- Comprobante de domicilio del representante legal (CFE, no mayor a 3 meses)"&CHAR(10)&"- Últimos 3 meses de estados de cuenta bancarios de la empresa"&CHAR(10)&"- Constancia de situación fiscal de la empresa (no mayor a 3 meses)"&CHAR(10)&"- Constancia de situación fiscal del representante legal (no mayor a 3 meses)"&CHAR(10)&"- Declaración anual del último ejercicio, en digital, con acuse de recibo"&CHAR(10)&"- Estados financieros de la empresa (Resultados y Balance General), no mayor a 3 meses"&CHAR(10)&"- Escritura constitutiva, poderes o reformas de estatutos (primer acta, poder del representante y última acta)","Contado|Persona física","Hola, "&B25&", para continuar con el proceso de tu *"&D25&"* por "&F25&", estos son los documentos que necesitamos:"&CHAR(10)&CHAR(10)&"- INE"&CHAR(10)&"- Comprobante de domicilio"&CHAR(10)&"- Constancia de situación fiscal (no mayor a 3 meses)","Contado|Persona física con actividad empresarial","Hola, "&B25&", para continuar con el proceso de tu *"&D25&"* por "&F25&", estos son los documentos que necesitamos:"&CHAR(10)&CHAR(10)&"- INE"&CHAR(10)&"- Comprobante de domicilio"&CHAR(10)&"- Constancia de situación fiscal (no mayor a 3 meses)","Contado|Persona moral","Hola, "&B25&", para continuar con el proceso de tu *"&D25&"* por "&F25&", estos son los documentos que necesitamos:"&CHAR(10)&CHAR(10)&"- Identificación oficial vigente del representante legal y accionistas"&CHAR(10)&"- Comprobante de domicilio fiscal de la empresa (no mayor a 3 meses)"&CHAR(10)&"- Comprobante de domicilio del representante legal y accionistas (no mayor a 3 meses)"&CHAR(10)&"- Constancia de situación fiscal de la empresa (no mayor a 3 meses)"&CHAR(10)&"- Constancia de situación fiscal del representante legal y accionistas (no mayor a 3 meses)"&CHAR(10)&"- Escritura constitutiva, poderes o reformas de estatutos (primer acta, poder del representante y última acta)","Selecciona Método de Compra y Tipo de Persona.")&CHAR(10)&CHAR(10)&Config!$B$1) | AD25: =IFERROR(INDEX(Facturación!$Q:$Q,MATCH(B25,Facturación!$A:$A,0)),"")
A26: =IF(B26="","",ROW()-1) | Q26: =IF(OR(B26="",L26<>"Sí"),"","Hola, "&B26&", excelente día. Le saluda *Alejandro Estrada* de Toyota Corregidora."&CHAR(10)&"Muchas gracias por visitarnos y conocer la *"&D26&"*. Fue un placer atenderle. Me pongo a sus órdenes por este medio para resolver cualquier duda que haya surgido o para agendarle una prueba de manejo."&CHAR(10)&"Quedo muy pendiente de lo que necesite para ayudarle a estrenar su próximo Toyota. ¡Saludos!"&CHAR(10)&CHAR(10)&Config!$B$1) | R26: =IF(Q26="","",HYPERLINK("https://wa.me/52"&C26&"?text="&_xlfn.ENCODEURL(Q26),"Enviar Bienvenida")) | S26: =IF(B26="","","Hola, "&B26&", muy buen día."&CHAR(10)&"Espero que esté teniendo una excelente semana. Le escribo para saber si tiene alguna duda sobre la oferta del *"&D26&"* que revisamos, con gusto le apoyo con información técnica o con las opciones de financiamiento disponibles."&CHAR(10)&"Quedo atento a sus comentarios para seguir avanzando hacia la entrega de su próximo Toyota. Gracias por su tiempo y confianza."&CHAR(10)&CHAR(10)&Config!$B$1) | T26: =IF(S26="","",HYPERLINK("https://wa.me/52"&C26&"?text="&_xlfn.ENCODEURL(S26),"Enviar Seguimiento")) | U26: =IF(B26="","",_xlfn.SWITCH(M26,"Apartado","Hola, "&B26&", buen día. Le confirmo que su apartado por el *"&D26&"* quedó registrado correctamente. Seguimos con el proceso y le mantendré informado(a) de cada paso.","Toma de vehículo","Hola, "&B26&", le comparto que estamos en el proceso de toma de su vehículo actual. En cuanto tengamos el resultado le aviso para continuar con el siguiente paso.","Pago vehículo a cuenta","Hola, "&B26&", quedamos en proceso de pago del vehículo que se toma a cuenta. Cualquier documento o aclaración que se requiera se lo haré saber por este medio.","Firma de contrato","Hola, "&B26&", ya estamos listos para agendar la firma de su contrato. ¿Qué día y hora se le facilita para realizarla?","Facturación","Hola, "&B26&", su unidad ya está en proceso de facturación. En breve le comparto los datos para su confirmación.","Programación de entrega","Hola, "&B26&", con gusto le comparto que ya podemos programar la entrega de su *"&D26&"*. ¿Qué día y hora le acomodan mejor?","Entregado","Hola, "&B26&", ¡muchas felicidades por estrenar su *"&D26&"*! Fue un gusto acompañarle en este proceso. Quedo pendiente de cualquier duda y con gusto le agendo su próxima cita de servicio cuando lo necesite.","Hola, "&B26&", seguimos en contacto para avanzar con el proceso de su próximo Toyota.")&CHAR(10)&CHAR(10)&Config!$B$1) | V26: =IF(U26="","",HYPERLINK("https://wa.me/52"&C26&"?text="&_xlfn.ENCODEURL(U26),"Enviar aviso de etapa")) | W26: =IF(OR(B26="",O26=""),"","Hola, "&B26&", ¡feliz cumpleaños! Le deseo un excelente día rodeado de quienes más quiere. Ha sido un placer acompañarle desde que estrenó su Toyota. ¡Un abrazo!"&CHAR(10)&CHAR(10)&Config!$B$1) | X26: =IF(W26="","",HYPERLINK("https://wa.me/52"&C26&"?text="&_xlfn.ENCODEURL(W26),"Enviar felicitación")) | Y26: =IF(OR(B26="",P26=""),"","Hola, "&B26&", hoy se cumple un año más desde que estrenó su *"&D26&"*. Espero que haya sido un gran compañero de camino. Cualquier cosa que necesite, aquí estoy para apoyarle."&CHAR(10)&CHAR(10)&Config!$B$1) | Z26: =IF(Y26="","",HYPERLINK("https://wa.me/52"&C26&"?text="&_xlfn.ENCODEURL(Y26),"Enviar aniversario")) | AB26: =IF(OR(B26="",AA26=""),"",HYPERLINK("https://wa.me/52"&C26&"?text="&_xlfn.ENCODEURL(_xlfn.SWITCH(AA26,"Bienvenida (primera visita)",Q26,"Seguimiento",S26,"Aviso de Etapa",U26,"Requisitos",AC26,"Datos de Facturación",AD26,"Cumpleaños",W26,"Aniversario",Y26,"")),"Enviar mensaje seleccionado")) | AC26: =IF(B26="","",_xlfn.SWITCH(F26&"|"&G26,"Crédito|Persona física","Hola, "&B26&", para continuar con el proceso de tu *"&D26&"* por "&F26&", estos son los documentos que necesitamos:"&CHAR(10)&CHAR(10)&"- INE"&CHAR(10)&"- Comprobante de domicilio (luz), a nombre del titular"&CHAR(10)&"- Estados de cuenta de los últimos 3 meses"&CHAR(10)&"- Constancia de situación fiscal (no mayor a 3 meses)","Crédito|Persona física con actividad empresarial","Hola, "&B26&", para continuar con el proceso de tu *"&D26&"* por "&F26&", estos son los documentos que necesitamos:"&CHAR(10)&CHAR(10)&"- INE"&CHAR(10)&"- Comprobante de domicilio (luz), a nombre del titular"&CHAR(10)&"- Estados de cuenta de los últimos 3 meses"&CHAR(10)&"- Constancia de situación fiscal (no mayor a 3 meses)"&CHAR(10)&"- Última declaración anual con acuse de recibo","Crédito|Persona moral","Hola, "&B26&", para continuar con el proceso de tu *"&D26&"* por "&F26&", estos son los documentos que necesitamos:"&CHAR(10)&CHAR(10)&"- Identificación oficial vigente del representante legal (INE o pasaporte)"&CHAR(10)&"- Comprobante de domicilio fiscal de la empresa (CFE, no mayor a 3 meses)"&CHAR(10)&"- Comprobante de domicilio del representante legal (CFE, no mayor a 3 meses)"&CHAR(10)&"- Últimos 3 meses de estados de cuenta bancarios de la empresa"&CHAR(10)&"- Constancia de situación fiscal de la empresa (no mayor a 3 meses)"&CHAR(10)&"- Constancia de situación fiscal del representante legal (no mayor a 3 meses)"&CHAR(10)&"- Declaración anual del último ejercicio, en digital, con acuse de recibo"&CHAR(10)&"- Estados financieros de la empresa (Resultados y Balance General), no mayor a 3 meses"&CHAR(10)&"- Escritura constitutiva, poderes o reformas de estatutos (primer acta, poder del representante y última acta)","Contado|Persona física","Hola, "&B26&", para continuar con el proceso de tu *"&D26&"* por "&F26&", estos son los documentos que necesitamos:"&CHAR(10)&CHAR(10)&"- INE"&CHAR(10)&"- Comprobante de domicilio"&CHAR(10)&"- Constancia de situación fiscal (no mayor a 3 meses)","Contado|Persona física con actividad empresarial","Hola, "&B26&", para continuar con el proceso de tu *"&D26&"* por "&F26&", estos son los documentos que necesitamos:"&CHAR(10)&CHAR(10)&"- INE"&CHAR(10)&"- Comprobante de domicilio"&CHAR(10)&"- Constancia de situación fiscal (no mayor a 3 meses)","Contado|Persona moral","Hola, "&B26&", para continuar con el proceso de tu *"&D26&"* por "&F26&", estos son los documentos que necesitamos:"&CHAR(10)&CHAR(10)&"- Identificación oficial vigente del representante legal y accionistas"&CHAR(10)&"- Comprobante de domicilio fiscal de la empresa (no mayor a 3 meses)"&CHAR(10)&"- Comprobante de domicilio del representante legal y accionistas (no mayor a 3 meses)"&CHAR(10)&"- Constancia de situación fiscal de la empresa (no mayor a 3 meses)"&CHAR(10)&"- Constancia de situación fiscal del representante legal y accionistas (no mayor a 3 meses)"&CHAR(10)&"- Escritura constitutiva, poderes o reformas de estatutos (primer acta, poder del representante y última acta)","Selecciona Método de Compra y Tipo de Persona.")&CHAR(10)&CHAR(10)&Config!$B$1) | AD26: =IFERROR(INDEX(Facturación!$Q:$Q,MATCH(B26,Facturación!$A:$A,0)),"")
A27: =IF(B27="","",ROW()-1) | Q27: =IF(OR(B27="",L27<>"Sí"),"","Hola, "&B27&", excelente día. Le saluda *Alejandro Estrada* de Toyota Corregidora."&CHAR(10)&"Muchas gracias por visitarnos y conocer la *"&D27&"*. Fue un placer atenderle. Me pongo a sus órdenes por este medio para resolver cualquier duda que haya surgido o para agendarle una prueba de manejo."&CHAR(10)&"Quedo muy pendiente de lo que necesite para ayudarle a estrenar su próximo Toyota. ¡Saludos!"&CHAR(10)&CHAR(10)&Config!$B$1) | R27: =IF(Q27="","",HYPERLINK("https://wa.me/52"&C27&"?text="&_xlfn.ENCODEURL(Q27),"Enviar Bienvenida")) | S27: =IF(B27="","","Hola, "&B27&", muy buen día."&CHAR(10)&"Espero que esté teniendo una excelente semana. Le escribo para saber si tiene alguna duda sobre la oferta del *"&D27&"* que revisamos, con gusto le apoyo con información técnica o con las opciones de financiamiento disponibles."&CHAR(10)&"Quedo atento a sus comentarios para seguir avanzando hacia la entrega de su próximo Toyota. Gracias por su tiempo y confianza."&CHAR(10)&CHAR(10)&Config!$B$1) | T27: =IF(S27="","",HYPERLINK("https://wa.me/52"&C27&"?text="&_xlfn.ENCODEURL(S27),"Enviar Seguimiento")) | U27: =IF(B27="","",_xlfn.SWITCH(M27,"Apartado","Hola, "&B27&", buen día. Le confirmo que su apartado por el *"&D27&"* quedó registrado correctamente. Seguimos con el proceso y le mantendré informado(a) de cada paso.","Toma de vehículo","Hola, "&B27&", le comparto que estamos en el proceso de toma de su vehículo actual. En cuanto tengamos el resultado le aviso para continuar con el siguiente paso.","Pago vehículo a cuenta","Hola, "&B27&", quedamos en proceso de pago del vehículo que se toma a cuenta. Cualquier documento o aclaración que se requiera se lo haré saber por este medio.","Firma de contrato","Hola, "&B27&", ya estamos listos para agendar la firma de su contrato. ¿Qué día y hora se le facilita para realizarla?","Facturación","Hola, "&B27&", su unidad ya está en proceso de facturación. En breve le comparto los datos para su confirmación.","Programación de entrega","Hola, "&B27&", con gusto le comparto que ya podemos programar la entrega de su *"&D27&"*. ¿Qué día y hora le acomodan mejor?","Entregado","Hola, "&B27&", ¡muchas felicidades por estrenar su *"&D27&"*! Fue un gusto acompañarle en este proceso. Quedo pendiente de cualquier duda y con gusto le agendo su próxima cita de servicio cuando lo necesite.","Hola, "&B27&", seguimos en contacto para avanzar con el proceso de su próximo Toyota.")&CHAR(10)&CHAR(10)&Config!$B$1) | V27: =IF(U27="","",HYPERLINK("https://wa.me/52"&C27&"?text="&_xlfn.ENCODEURL(U27),"Enviar aviso de etapa")) | W27: =IF(OR(B27="",O27=""),"","Hola, "&B27&", ¡feliz cumpleaños! Le deseo un excelente día rodeado de quienes más quiere. Ha sido un placer acompañarle desde que estrenó su Toyota. ¡Un abrazo!"&CHAR(10)&CHAR(10)&Config!$B$1) | X27: =IF(W27="","",HYPERLINK("https://wa.me/52"&C27&"?text="&_xlfn.ENCODEURL(W27),"Enviar felicitación")) | Y27: =IF(OR(B27="",P27=""),"","Hola, "&B27&", hoy se cumple un año más desde que estrenó su *"&D27&"*. Espero que haya sido un gran compañero de camino. Cualquier cosa que necesite, aquí estoy para apoyarle."&CHAR(10)&CHAR(10)&Config!$B$1) | Z27: =IF(Y27="","",HYPERLINK("https://wa.me/52"&C27&"?text="&_xlfn.ENCODEURL(Y27),"Enviar aniversario")) | AB27: =IF(OR(B27="",AA27=""),"",HYPERLINK("https://wa.me/52"&C27&"?text="&_xlfn.ENCODEURL(_xlfn.SWITCH(AA27,"Bienvenida (primera visita)",Q27,"Seguimiento",S27,"Aviso de Etapa",U27,"Requisitos",AC27,"Datos de Facturación",AD27,"Cumpleaños",W27,"Aniversario",Y27,"")),"Enviar mensaje seleccionado")) | AC27: =IF(B27="","",_xlfn.SWITCH(F27&"|"&G27,"Crédito|Persona física","Hola, "&B27&", para continuar con el proceso de tu *"&D27&"* por "&F27&", estos son los documentos que necesitamos:"&CHAR(10)&CHAR(10)&"- INE"&CHAR(10)&"- Comprobante de domicilio (luz), a nombre del titular"&CHAR(10)&"- Estados de cuenta de los últimos 3 meses"&CHAR(10)&"- Constancia de situación fiscal (no mayor a 3 meses)","Crédito|Persona física con actividad empresarial","Hola, "&B27&", para continuar con el proceso de tu *"&D27&"* por "&F27&", estos son los documentos que necesitamos:"&CHAR(10)&CHAR(10)&"- INE"&CHAR(10)&"- Comprobante de domicilio (luz), a nombre del titular"&CHAR(10)&"- Estados de cuenta de los últimos 3 meses"&CHAR(10)&"- Constancia de situación fiscal (no mayor a 3 meses)"&CHAR(10)&"- Última declaración anual con acuse de recibo","Crédito|Persona moral","Hola, "&B27&", para continuar con el proceso de tu *"&D27&"* por "&F27&", estos son los documentos que necesitamos:"&CHAR(10)&CHAR(10)&"- Identificación oficial vigente del representante legal (INE o pasaporte)"&CHAR(10)&"- Comprobante de domicilio fiscal de la empresa (CFE, no mayor a 3 meses)"&CHAR(10)&"- Comprobante de domicilio del representante legal (CFE, no mayor a 3 meses)"&CHAR(10)&"- Últimos 3 meses de estados de cuenta bancarios de la empresa"&CHAR(10)&"- Constancia de situación fiscal de la empresa (no mayor a 3 meses)"&CHAR(10)&"- Constancia de situación fiscal del representante legal (no mayor a 3 meses)"&CHAR(10)&"- Declaración anual del último ejercicio, en digital, con acuse de recibo"&CHAR(10)&"- Estados financieros de la empresa (Resultados y Balance General), no mayor a 3 meses"&CHAR(10)&"- Escritura constitutiva, poderes o reformas de estatutos (primer acta, poder del representante y última acta)","Contado|Persona física","Hola, "&B27&", para continuar con el proceso de tu *"&D27&"* por "&F27&", estos son los documentos que necesitamos:"&CHAR(10)&CHAR(10)&"- INE"&CHAR(10)&"- Comprobante de domicilio"&CHAR(10)&"- Constancia de situación fiscal (no mayor a 3 meses)","Contado|Persona física con actividad empresarial","Hola, "&B27&", para continuar con el proceso de tu *"&D27&"* por "&F27&", estos son los documentos que necesitamos:"&CHAR(10)&CHAR(10)&"- INE"&CHAR(10)&"- Comprobante de domicilio"&CHAR(10)&"- Constancia de situación fiscal (no mayor a 3 meses)","Contado|Persona moral","Hola, "&B27&", para continuar con el proceso de tu *"&D27&"* por "&F27&", estos son los documentos que necesitamos:"&CHAR(10)&CHAR(10)&"- Identificación oficial vigente del representante legal y accionistas"&CHAR(10)&"- Comprobante de domicilio fiscal de la empresa (no mayor a 3 meses)"&CHAR(10)&"- Comprobante de domicilio del representante legal y accionistas (no mayor a 3 meses)"&CHAR(10)&"- Constancia de situación fiscal de la empresa (no mayor a 3 meses)"&CHAR(10)&"- Constancia de situación fiscal del representante legal y accionistas (no mayor a 3 meses)"&CHAR(10)&"- Escritura constitutiva, poderes o reformas de estatutos (primer acta, poder del representante y última acta)","Selecciona Método de Compra y Tipo de Persona.")&CHAR(10)&CHAR(10)&Config!$B$1) | AD27: =IFERROR(INDEX(Facturación!$Q:$Q,MATCH(B27,Facturación!$A:$A,0)),"")
A28: =IF(B28="","",ROW()-1) | Q28: =IF(OR(B28="",L28<>"Sí"),"","Hola, "&B28&", excelente día. Le saluda *Alejandro Estrada* de Toyota Corregidora."&CHAR(10)&"Muchas gracias por visitarnos y conocer la *"&D28&"*. Fue un placer atenderle. Me pongo a sus órdenes por este medio para resolver cualquier duda que haya surgido o para agendarle una prueba de manejo."&CHAR(10)&"Quedo muy pendiente de lo que necesite para ayudarle a estrenar su próximo Toyota. ¡Saludos!"&CHAR(10)&CHAR(10)&Config!$B$1) | R28: =IF(Q28="","",HYPERLINK("https://wa.me/52"&C28&"?text="&_xlfn.ENCODEURL(Q28),"Enviar Bienvenida")) | S28: =IF(B28="","","Hola, "&B28&", muy buen día."&CHAR(10)&"Espero que esté teniendo una excelente semana. Le escribo para saber si tiene alguna duda sobre la oferta del *"&D28&"* que revisamos, con gusto le apoyo con información técnica o con las opciones de financiamiento disponibles."&CHAR(10)&"Quedo atento a sus comentarios para seguir avanzando hacia la entrega de su próximo Toyota. Gracias por su tiempo y confianza."&CHAR(10)&CHAR(10)&Config!$B$1) | T28: =IF(S28="","",HYPERLINK("https://wa.me/52"&C28&"?text="&_xlfn.ENCODEURL(S28),"Enviar Seguimiento")) | U28: =IF(B28="","",_xlfn.SWITCH(M28,"Apartado","Hola, "&B28&", buen día. Le confirmo que su apartado por el *"&D28&"* quedó registrado correctamente. Seguimos con el proceso y le mantendré informado(a) de cada paso.","Toma de vehículo","Hola, "&B28&", le comparto que estamos en el proceso de toma de su vehículo actual. En cuanto tengamos el resultado le aviso para continuar con el siguiente paso.","Pago vehículo a cuenta","Hola, "&B28&", quedamos en proceso de pago del vehículo que se toma a cuenta. Cualquier documento o aclaración que se requiera se lo haré saber por este medio.","Firma de contrato","Hola, "&B28&", ya estamos listos para agendar la firma de su contrato. ¿Qué día y hora se le facilita para realizarla?","Facturación","Hola, "&B28&", su unidad ya está en proceso de facturación. En breve le comparto los datos para su confirmación.","Programación de entrega","Hola, "&B28&", con gusto le comparto que ya podemos programar la entrega de su *"&D28&"*. ¿Qué día y hora le acomodan mejor?","Entregado","Hola, "&B28&", ¡muchas felicidades por estrenar su *"&D28&"*! Fue un gusto acompañarle en este proceso. Quedo pendiente de cualquier duda y con gusto le agendo su próxima cita de servicio cuando lo necesite.","Hola, "&B28&", seguimos en contacto para avanzar con el proceso de su próximo Toyota.")&CHAR(10)&CHAR(10)&Config!$B$1) | V28: =IF(U28="","",HYPERLINK("https://wa.me/52"&C28&"?text="&_xlfn.ENCODEURL(U28),"Enviar aviso de etapa")) | W28: =IF(OR(B28="",O28=""),"","Hola, "&B28&", ¡feliz cumpleaños! Le deseo un excelente día rodeado de quienes más quiere. Ha sido un placer acompañarle desde que estrenó su Toyota. ¡Un abrazo!"&CHAR(10)&CHAR(10)&Config!$B$1) | X28: =IF(W28="","",HYPERLINK("https://wa.me/52"&C28&"?text="&_xlfn.ENCODEURL(W28),"Enviar felicitación")) | Y28: =IF(OR(B28="",P28=""),"","Hola, "&B28&", hoy se cumple un año más desde que estrenó su *"&D28&"*. Espero que haya sido un gran compañero de camino. Cualquier cosa que necesite, aquí estoy para apoyarle."&CHAR(10)&CHAR(10)&Config!$B$1) | Z28: =IF(Y28="","",HYPERLINK("https://wa.me/52"&C28&"?text="&_xlfn.ENCODEURL(Y28),"Enviar aniversario")) | AB28: =IF(OR(B28="",AA28=""),"",HYPERLINK("https://wa.me/52"&C28&"?text="&_xlfn.ENCODEURL(_xlfn.SWITCH(AA28,"Bienvenida (primera visita)",Q28,"Seguimiento",S28,"Aviso de Etapa",U28,"Requisitos",AC28,"Datos de Facturación",AD28,"Cumpleaños",W28,"Aniversario",Y28,"")),"Enviar mensaje seleccionado")) | AC28: =IF(B28="","",_xlfn.SWITCH(F28&"|"&G28,"Crédito|Persona física","Hola, "&B28&", para continuar con el proceso de tu *"&D28&"* por "&F28&", estos son los documentos que necesitamos:"&CHAR(10)&CHAR(10)&"- INE"&CHAR(10)&"- Comprobante de domicilio (luz), a nombre del titular"&CHAR(10)&"- Estados de cuenta de los últimos 3 meses"&CHAR(10)&"- Constancia de situación fiscal (no mayor a 3 meses)","Crédito|Persona física con actividad empresarial","Hola, "&B28&", para continuar con el proceso de tu *"&D28&"* por "&F28&", estos son los documentos que necesitamos:"&CHAR(10)&CHAR(10)&"- INE"&CHAR(10)&"- Comprobante de domicilio (luz), a nombre del titular"&CHAR(10)&"- Estados de cuenta de los últimos 3 meses"&CHAR(10)&"- Constancia de situación fiscal (no mayor a 3 meses)"&CHAR(10)&"- Última declaración anual con acuse de recibo","Crédito|Persona moral","Hola, "&B28&", para continuar con el proceso de tu *"&D28&"* por "&F28&", estos son los documentos que necesitamos:"&CHAR(10)&CHAR(10)&"- Identificación oficial vigente del representante legal (INE o pasaporte)"&CHAR(10)&"- Comprobante de domicilio fiscal de la empresa (CFE, no mayor a 3 meses)"&CHAR(10)&"- Comprobante de domicilio del representante legal (CFE, no mayor a 3 meses)"&CHAR(10)&"- Últimos 3 meses de estados de cuenta bancarios de la empresa"&CHAR(10)&"- Constancia de situación fiscal de la empresa (no mayor a 3 meses)"&CHAR(10)&"- Constancia de situación fiscal del representante legal (no mayor a 3 meses)"&CHAR(10)&"- Declaración anual del último ejercicio, en digital, con acuse de recibo"&CHAR(10)&"- Estados financieros de la empresa (Resultados y Balance General), no mayor a 3 meses"&CHAR(10)&"- Escritura constitutiva, poderes o reformas de estatutos (primer acta, poder del representante y última acta)","Contado|Persona física","Hola, "&B28&", para continuar con el proceso de tu *"&D28&"* por "&F28&", estos son los documentos que necesitamos:"&CHAR(10)&CHAR(10)&"- INE"&CHAR(10)&"- Comprobante de domicilio"&CHAR(10)&"- Constancia de situación fiscal (no mayor a 3 meses)","Contado|Persona física con actividad empresarial","Hola, "&B28&", para continuar con el proceso de tu *"&D28&"* por "&F28&", estos son los documentos que necesitamos:"&CHAR(10)&CHAR(10)&"- INE"&CHAR(10)&"- Comprobante de domicilio"&CHAR(10)&"- Constancia de situación fiscal (no mayor a 3 meses)","Contado|Persona moral","Hola, "&B28&", para continuar con el proceso de tu *"&D28&"* por "&F28&", estos son los documentos que necesitamos:"&CHAR(10)&CHAR(10)&"- Identificación oficial vigente del representante legal y accionistas"&CHAR(10)&"- Comprobante de domicilio fiscal de la empresa (no mayor a 3 meses)"&CHAR(10)&"- Comprobante de domicilio del representante legal y accionistas (no mayor a 3 meses)"&CHAR(10)&"- Constancia de situación fiscal de la empresa (no mayor a 3 meses)"&CHAR(10)&"- Constancia de situación fiscal del representante legal y accionistas (no mayor a 3 meses)"&CHAR(10)&"- Escritura constitutiva, poderes o reformas de estatutos (primer acta, poder del representante y última acta)","Selecciona Método de Compra y Tipo de Persona.")&CHAR(10)&CHAR(10)&Config!$B$1) | AD28: =IFERROR(INDEX(Facturación!$Q:$Q,MATCH(B28,Facturación!$A:$A,0)),"")
A29: =IF(B29="","",ROW()-1) | Q29: =IF(OR(B29="",L29<>"Sí"),"","Hola, "&B29&", excelente día. Le saluda *Alejandro Estrada* de Toyota Corregidora."&CHAR(10)&"Muchas gracias por visitarnos y conocer la *"&D29&"*. Fue un placer atenderle. Me pongo a sus órdenes por este medio para resolver cualquier duda que haya surgido o para agendarle una prueba de manejo."&CHAR(10)&"Quedo muy pendiente de lo que necesite para ayudarle a estrenar su próximo Toyota. ¡Saludos!"&CHAR(10)&CHAR(10)&Config!$B$1) | R29: =IF(Q29="","",HYPERLINK("https://wa.me/52"&C29&"?text="&_xlfn.ENCODEURL(Q29),"Enviar Bienvenida")) | S29: =IF(B29="","","Hola, "&B29&", muy buen día."&CHAR(10)&"Espero que esté teniendo una excelente semana. Le escribo para saber si tiene alguna duda sobre la oferta del *"&D29&"* que revisamos, con gusto le apoyo con información técnica o con las opciones de financiamiento disponibles."&CHAR(10)&"Quedo atento a sus comentarios para seguir avanzando hacia la entrega de su próximo Toyota. Gracias por su tiempo y confianza."&CHAR(10)&CHAR(10)&Config!$B$1) | T29: =IF(S29="","",HYPERLINK("https://wa.me/52"&C29&"?text="&_xlfn.ENCODEURL(S29),"Enviar Seguimiento")) | U29: =IF(B29="","",_xlfn.SWITCH(M29,"Apartado","Hola, "&B29&", buen día. Le confirmo que su apartado por el *"&D29&"* quedó registrado correctamente. Seguimos con el proceso y le mantendré informado(a) de cada paso.","Toma de vehículo","Hola, "&B29&", le comparto que estamos en el proceso de toma de su vehículo actual. En cuanto tengamos el resultado le aviso para continuar con el siguiente paso.","Pago vehículo a cuenta","Hola, "&B29&", quedamos en proceso de pago del vehículo que se toma a cuenta. Cualquier documento o aclaración que se requiera se lo haré saber por este medio.","Firma de contrato","Hola, "&B29&", ya estamos listos para agendar la firma de su contrato. ¿Qué día y hora se le facilita para realizarla?","Facturación","Hola, "&B29&", su unidad ya está en proceso de facturación. En breve le comparto los datos para su confirmación.","Programación de entrega","Hola, "&B29&", con gusto le comparto que ya podemos programar la entrega de su *"&D29&"*. ¿Qué día y hora le acomodan mejor?","Entregado","Hola, "&B29&", ¡muchas felicidades por estrenar su *"&D29&"*! Fue un gusto acompañarle en este proceso. Quedo pendiente de cualquier duda y con gusto le agendo su próxima cita de servicio cuando lo necesite.","Hola, "&B29&", seguimos en contacto para avanzar con el proceso de su próximo Toyota.")&CHAR(10)&CHAR(10)&Config!$B$1) | V29: =IF(U29="","",HYPERLINK("https://wa.me/52"&C29&"?text="&_xlfn.ENCODEURL(U29),"Enviar aviso de etapa")) | W29: =IF(OR(B29="",O29=""),"","Hola, "&B29&", ¡feliz cumpleaños! Le deseo un excelente día rodeado de quienes más quiere. Ha sido un placer acompañarle desde que estrenó su Toyota. ¡Un abrazo!"&CHAR(10)&CHAR(10)&Config!$B$1) | X29: =IF(W29="","",HYPERLINK("https://wa.me/52"&C29&"?text="&_xlfn.ENCODEURL(W29),"Enviar felicitación")) | Y29: =IF(OR(B29="",P29=""),"","Hola, "&B29&", hoy se cumple un año más desde que estrenó su *"&D29&"*. Espero que haya sido un gran compañero de camino. Cualquier cosa que necesite, aquí estoy para apoyarle."&CHAR(10)&CHAR(10)&Config!$B$1) | Z29: =IF(Y29="","",HYPERLINK("https://wa.me/52"&C29&"?text="&_xlfn.ENCODEURL(Y29),"Enviar aniversario")) | AB29: =IF(OR(B29="",AA29=""),"",HYPERLINK("https://wa.me/52"&C29&"?text="&_xlfn.ENCODEURL(_xlfn.SWITCH(AA29,"Bienvenida (primera visita)",Q29,"Seguimiento",S29,"Aviso de Etapa",U29,"Requisitos",AC29,"Datos de Facturación",AD29,"Cumpleaños",W29,"Aniversario",Y29,"")),"Enviar mensaje seleccionado")) | AC29: =IF(B29="","",_xlfn.SWITCH(F29&"|"&G29,"Crédito|Persona física","Hola, "&B29&", para continuar con el proceso de tu *"&D29&"* por "&F29&", estos son los documentos que necesitamos:"&CHAR(10)&CHAR(10)&"- INE"&CHAR(10)&"- Comprobante de domicilio (luz), a nombre del titular"&CHAR(10)&"- Estados de cuenta de los últimos 3 meses"&CHAR(10)&"- Constancia de situación fiscal (no mayor a 3 meses)","Crédito|Persona física con actividad empresarial","Hola, "&B29&", para continuar con el proceso de tu *"&D29&"* por "&F29&", estos son los documentos que necesitamos:"&CHAR(10)&CHAR(10)&"- INE"&CHAR(10)&"- Comprobante de domicilio (luz), a nombre del titular"&CHAR(10)&"- Estados de cuenta de los últimos 3 meses"&CHAR(10)&"- Constancia de situación fiscal (no mayor a 3 meses)"&CHAR(10)&"- Última declaración anual con acuse de recibo","Crédito|Persona moral","Hola, "&B29&", para continuar con el proceso de tu *"&D29&"* por "&F29&", estos son los documentos que necesitamos:"&CHAR(10)&CHAR(10)&"- Identificación oficial vigente del representante legal (INE o pasaporte)"&CHAR(10)&"- Comprobante de domicilio fiscal de la empresa (CFE, no mayor a 3 meses)"&CHAR(10)&"- Comprobante de domicilio del representante legal (CFE, no mayor a 3 meses)"&CHAR(10)&"- Últimos 3 meses de estados de cuenta bancarios de la empresa"&CHAR(10)&"- Constancia de situación fiscal de la empresa (no mayor a 3 meses)"&CHAR(10)&"- Constancia de situación fiscal del representante legal (no mayor a 3 meses)"&CHAR(10)&"- Declaración anual del último ejercicio, en digital, con acuse de recibo"&CHAR(10)&"- Estados financieros de la empresa (Resultados y Balance General), no mayor a 3 meses"&CHAR(10)&"- Escritura constitutiva, poderes o reformas de estatutos (primer acta, poder del representante y última acta)","Contado|Persona física","Hola, "&B29&", para continuar con el proceso de tu *"&D29&"* por "&F29&", estos son los documentos que necesitamos:"&CHAR(10)&CHAR(10)&"- INE"&CHAR(10)&"- Comprobante de domicilio"&CHAR(10)&"- Constancia de situación fiscal (no mayor a 3 meses)","Contado|Persona física con actividad empresarial","Hola, "&B29&", para continuar con el proceso de tu *"&D29&"* por "&F29&", estos son los documentos que necesitamos:"&CHAR(10)&CHAR(10)&"- INE"&CHAR(10)&"- Comprobante de domicilio"&CHAR(10)&"- Constancia de situación fiscal (no mayor a 3 meses)","Contado|Persona moral","Hola, "&B29&", para continuar con el proceso de tu *"&D29&"* por "&F29&", estos son los documentos que necesitamos:"&CHAR(10)&CHAR(10)&"- Identificación oficial vigente del representante legal y accionistas"&CHAR(10)&"- Comprobante de domicilio fiscal de la empresa (no mayor a 3 meses)"&CHAR(10)&"- Comprobante de domicilio del representante legal y accionistas (no mayor a 3 meses)"&CHAR(10)&"- Constancia de situación fiscal de la empresa (no mayor a 3 meses)"&CHAR(10)&"- Constancia de situación fiscal del representante legal y accionistas (no mayor a 3 meses)"&CHAR(10)&"- Escritura constitutiva, poderes o reformas de estatutos (primer acta, poder del representante y última acta)","Selecciona Método de Compra y Tipo de Persona.")&CHAR(10)&CHAR(10)&Config!$B$1) | AD29: =IFERROR(INDEX(Facturación!$Q:$Q,MATCH(B29,Facturación!$A:$A,0)),"")
